Workbook

Sheet Highway
A1: Statement For Selected Period | C1: Total Revenue | G1: 2021 | I1: 2022 | K1: 2023
A2: August 28 2023 - September 3 2023 | C2: 19246.99 | G2: January | I2: January | J2: 18130.06 | K2: January | L2: 63461.24
A3: September 4 2023 - September 10 2023 | C3: 14356.63 | G3: February | I3: February | J3: 39412.26 | K3: February | L3: 56826.84
A4: September 11 2023 - September 17 2023 | C4: 13870.89 | G4: March | I4: March | J4: 66452.65 | K4: March | L4: 54406.31
A5: September 18 2023 - September 24 2023 | C5: 14354.51 | G5: April | I5: April | J5: 63986.87 | K5: April | L5: 87441.54
A6: September 25 2023 - October 1 2023 | C6: 11876.87 | G6: May | I6: May | J6: 80342.74 | K6: May | L6: 71540.19
A7: October 2 2023 - October 8 2023 | C7: 15468 | G7: June | I7: June | J7: 69278.77 | K7: June | L7: 80490.19
A8: October 9 2023 - October 15 2023 | C8: 14791.27 | G8: July | H8: 29200.29 | I8: July | J8: 93630.05 | K8: July | L8: 80901.93
A9: October 16 2023 - October 22 2023 | C9: 13591.26 | G9: August | H9: 29200.29 | I9: August | J9: 89897.43 | K9: August | L9: 78025.38
A10: October 23 2023 - October 29 2023 | C10: 13390.93 | G10: September | H10: 38093.04 | I10: September | J10: 81288.88 | K10: September | L10: 65349.57
A11: October 30 2023 - November 5 2023 | C11: 14787.15 | G11: October | H11: 43748.26 | I11: October | J11: 80599.73 | K11: October | L11: 62182.59
A12: November 6 2023 - November 12 2023 | C12: 11788.3 | G12: November | H12: 57688.09 | I12: November | J12: 47414.18 | K12: November
A13: November 13 2023 - November 19 2023 | C13: 12920.71 | G13: December | H13: 49551.8 | I13: December | J13: 70946.08 | K13: December
A14: November 20 2023 - November 26 2023 | C14: 15064.65
A15: November 27 2023 - December 03 2024 | C15: 14390.04
A16: December 04 2023 - December 10 2024 | C16: 13466.62
A17: December 11 2023 - December 17 2024 | C17: 14152.59
A18: December 18 2023 - December 24 2024 | C18: 16836.46
A19: December 25 2023 - December 31 2024 | C19: 24926.22
A20: Jan 1 - Jan 07 2024 | C20: 17046.54
A21: Jan 8 - Jan 14 2024 | C21: 11512.96
A22: Jan 15 - Jan 21 2024 | C22: 11871.2
A23: Jan 22 - Jan 28 2025 | C23: 12831.63
A24: Jan 29 - Feb 04 2026 | C24: 12981.55
A25: Feb 05 - Feb 11 2026 | C25: 11512.96
... A66: Nov 18 - Nov 24 2024 | C66: 11890.27
A67: Nov 25 - Dec 01 2024 | C67: 14674.88 | F67: In-Store | G67: Skip | H67: DD | I67: Uber (TB) | J67: Uber Website
A68: Dec 02 - Dec 08 2024 | C68: 13074.02
A69: Dec 09 - Dec 15 2024 | C69: 13673.26 | M69: =SUM(M70:M71) -> 2641.62
A70: Dec 16 - Dec 22 2024 | C70: 14020.88 | K70: 3682.96 | L70: 1516.54 | M70: =K70-L70 -> 2166.42
A71: Dec 23 - Dec 29 2024 | C71: 22334.02 | F71: =SUM(C71-(I71+G71+H71)) -> 17858.33 | G71: 167.98 | H71: 72.54 | I71: 4235.17 | K71: 756.52 | L71: 281.32 | M71: =K71-L71 -> 475.2
A72: Dec 30 - Jan 05 2025 | C72: 18755.59 | F72: =SUM(C72-(I72+G72+H72)) -> 14841.51 | G72: 64.78 | H72: 7.2 | I72: 3842.1
A73: Jan 06 - Jan 12 2025 | C73: 13898.98 | F73: In-Store | G73: Skip | H73: DD | I73: Uber (TB) | J73: Uber Website | L73: Highway Uber | M73: Pizza Highway Uber
A74: Jan 13 - Jan 19 2025 | C74: 14787.59 | F74: 12005.1 | G74: 79.13 | H74: 61.74 | I74: 4393.88 | J74: 2641.62 | K74: =SUM(F74,G74,H74,J74) -> 14787.59
A75: Jan 20 - Jan 26 2025 | C75: 13933.15 | F75: 10361.99 | G75: 184.76 | H75: 137.97 | I75: 4864.51 | J75: =SUM(L75:M75) -> 3248.43 | K75: =SUM(F75,G75,H75,J75) -> 13933.15 | L75: 805.91 | M75: 2442.52
A76: Jan 27 - Feb 02 2025 | C76: 13637.18 | F76: 10759.87 | G76: 0 | H76: 84 | I76: 2793.31 | J76: =SUM(L76:M76) -> 3293.25 | K76: =SUM(F76,G76,H76,J76) -> 14137.12 | L76: 787.96 | M76: 2505.29
A77: Feb 03 - Feb 09 2025 | C77: 11683.72 | F77: 9636.07 | G77: 155.86 | H77: 19.17 | I77: 2050.41 | J77: =SUM(L77:M77) -> 1872.62 | K77: =SUM(F77,G77,H77,J77) -> 11683.72 | L77: 196.93 | M77: 1675.69
A78: Feb 10 - Feb 16 2025 | C78: 12823.09 | F78: 10552.83 | G78: 103.06 | H78: 34.5 | I78: 2570.83 | J78: =SUM(L78:M78) -> 2132.7 | K78: =SUM(F78,G78,H78,J78) -> 12823.09 | L78: 932.29 | M78: 1200.41
A79: Feb 17 - Feb 23 2025 | C79: 13647.35 | F79: 11974.8 | G79: 157.5 | H79: 41.68 | I79: 1670.92 | J79: =SUM(L79:M79) -> 1473.37 | K79: =SUM(F79,G79,H79,J79) -> 13647.35 | L79: 483.5 | M79: 989.87
A80: Feb 24 - Mar 02 2025 | C80: 11761.23 | F80: 10244.94 | G80: 185.6 | H80: 0 | I80: 1589.93 | J80: =SUM(L80:M80) -> 1330.69 | K80: =SUM(F80,G80,H80,J80) -> 11761.23 | L80: 247.92 | M80: 1082.77
D81: Bill Count | E81: TB Total | F81: In-Store | G81: Skip | H81: DD | I81: Uber (TB) | J81: PK Uber (Rev) | K81: PK Uber (Marketing) | L81: Karahi Uber (Rev) | M81: Karahi Uber (Marketing) | N81: Final Uber | O81: Total
A82: Mar 03 - Mar 09 2025 | C82: 14891.97 | F82: 13909.7 | G82: 69.4 | H82: 0 | I82: 942.99 | J82: 746.27 | K82: 116.25 | L82: 462.85 | M82: 180 | N82: =(J82-K82)+(L82-M82) -> 912.87 | O82: =SUM(F82,G82,H82,N82) -> 14891.97
A83: Mar 10 - Mar 16 2025 | C83: 13562.67 | F83: 12075.21 | G83: 112.79 | H83: 0 | I83: 1429.54 | J83: 1010.63 | K83: 203.4 | L83: 872.05 | M83: 304.61 | N83: =(J83-K83)+(L83-M83) -> 1374.67 | O83: =SUM(F83,G83,H83,N83) -> 13562.67
A84: Mar 17 - Mar 23 2025 | C84: 15565.08 | F84: 13916.46 | G84: 32.4 | H84: 0 | I84: 1907.03 | J84: 1428.04 | K84: 290.02 | L84: 725.13 | M84: 246.93 | N84: =(J84-K84)+(L84-M84) -> 1616.22 | O84: =SUM(F84,G84,H84,N84) -> 15565.08
A85: Mar 24 - Mar 30 2025 | C85: 23113.63 | F85: 20852.28 | G85: 38.4 | H85: 0 | I85: 1816.28 | J85: 1365.85 | K85: 146.38 | L85: 1467.88 | M85: 464.4 | N85: =(J85-K85)+(L85-M85) -> 2222.95 | O85: =SUM(F85,G85,H85,N85) -> 23113.63
A86: Mar 31 - Apr 6 2025 | C86: 15364.57 | F86: 13068.64 | G86: 142.59 | H86: 88.2 | I86: 1829.78 | J86: 1144.71 | K86: 4.22 | L86: 1263.05 | M86: 338.4 | N86: =(J86-K86)+(L86-M86) -> 2065.14 | O86: =SUM(F86,G86,H86,N86) -> 15364.57
A87: Apr 7 - Apr 13 2025 | C87: 12478.91 | F87: 11465.82 | G87: 80.4 | H87: 0 | I87: 868.86 | J87: 784.43 | K87: 52.22 | L87: 300.48 | M87: 100 | N87: =(J87-K87)+(L87-M87) -> 932.69 | O87: =SUM(F87,G87,H87,N87) -> 12478.91
A88: Apr 14 - Apr 20 2025 | C88: 16230.17 | F88: 14342.29 | G88: 67.2 | H88: 0 | I88: 1781.2 | J88: 1338.01 | K88: 88.67 | L88: 801.42 | M88: 230.08 | N88: =(J88-K88)+(L88-M88) -> 1820.68 | O88: =SUM(F88,G88,H88,N88) -> 16230.17
A89: Apr 21 - Apr 27 2025 | C89: 12872.24 | F89: 11142.93 | G89: 217.48 | H89: 0 | I89: 1545.81 | J89: 1207.89 | K89: 75.35 | L89: 386.97 | M89: 7.68 | N89: =(J89-K89)+(L89-M89) -> 1511.83 | O89: =SUM(F89,G89,H89,N89) -> 12872.24
A90: Apr 28 - May 04 2025 | C90: 13895.8 | F90: 12387.89 | G90: 58.8 | H90: 0 | I90: 1325.39 | J90: 1134.36 | K90: 86.36 | L90: 413.59 | M90: 12.48 | N90: =(J90-K90)+(L90-M90) -> 1449.11 | O90: =SUM(F90,G90,H90,N90) -> 13895.8
A91: May 05 - May 11 2025 | C91: 13769.59 | E91: 13748.61 | F91: 12562.75 | G91: 143.69 | H91: 0 | I91: 1042.17 | J91: 802.34 | K91: 77.57 | L91: 422.98 | M91: 84.6 | N91: =(J91-K91)+(L91-M91) -> 1063.15 | O91: =SUM(F91,G91,H91,N91) -> 13769.59
A92: May 12 - May 18 2025 | C92: 12300.93 | E92: 12290.66 | F92: 10739.46 | G92: 173.79 | H92: 0 | I92: 1377.41 | J92: 1252.76 | K92: 103.85 | L92: 238.77 | M92: 0 | N92: =(J92-K92)+(L92-M92) -> 1387.68 | O92: =SUM(F92,G92,H92,N92) -> 12300.93
A93: May 19 - May 25 2025 | C93: 13972.67 | E93: 13981.9 | F93: 12784.11 | G93: 168.4 | H93: 0 | I93: 1029.39 | J93: 1008.11 | K93: 85.41 | L93: 97.46 | M93: 0 | N93: =(J93-K93)+(L93-M93) -> 1020.16 | O93: =SUM(F93,G93,H93,N93) -> 13972.67
A94: May 26 - June 01 2025 | C94: 11490.57 | E94: 11574.64 | F94: 10118.56 | G94: 32.4 | H94: 0 | I94: 1423.68 | J94: 1228.34 | K94: 84.07 | L94: 195.34 | M94: 0 | N94: =(J94-K94)+(L94-M94) -> 1339.61 | O94: =SUM(F94,G94,H94,N94) -> 11490.57
A95: June 02 - June 08 2025 | C95: 18161.64 | E95: 18206.2 | F95: 16664.27 | G95: 287.09 | H95: 0 | I95: 1254.84 | J95: 1082.72 | K95: 53.55 | L95: 181.11 | M95: 0 | N95: =(J95-K95)+(L95-M95) -> 1210.28 | O95: =SUM(F95,G95,H95,N95) -> 18161.64
A96: June 09 - June 15 2025 | C96: 16545.19 | E96: 16528.92 | F96: 15152.84 | G96: 168.77 | H96: 27 | I96: 1180.31 | J96: 984.81 | K96: 60.86 | L96: 272.63 | M96: 0 | N96: =(J96-K96)+(L96-M96) -> 1196.58 | O96: =SUM(F96,G96,H96,N96) -> 16545.19
A97: June 16 - June 22 2025 | C97: 12297.74 | E97: 12195.73 | F97: 11186.54 | G97: 126.6 | H97: 0 | I97: 882.59 | J97: 843.46 | K97: 40.49 | L97: 181.63 | M97: 0 | N97: =(J97-K97)+(L97-M97) -> 984.6 | O97: =SUM(F97,G97,H97,N97) -> 12297.74
A98: June 23 - June 29 2025 | C98: 12512.02 | E98: 12515.82 | F98: 11168.75 | G98: 166.8 | H98: 0 | I98: 1180.27 | J98: 775.67 | K98: 46.08 | L98: 446.88 | M98: 0 | N98: =(J98-K98)+(L98-M98) -> 1176.47 | O98: =SUM(F98,G98,H98,N98) -> 12512.02
A99: June 30 - July 06 2025 | C99: 13723.58 | E99: 13715.1 | F99: 12214.28 | G99: 159.9 | H99: 0 | I99: 1340.92 | J99: 1188.63 | K99: 16.32 | L99: 177.09 | M99: 0 | N99: =(J99-K99)+(L99-M99) -> 1349.4 | O99: =SUM(F99,G99,H99,N99) -> 13723.58
A100: July 07 - July 13 2025 | C100: 10386.93 | E100: 10417.25 | F100: 8805.33 | G100: 191.32 | H100: 330.67 | I100: 1089.93 | J100: 824.48 | K100: 30.32 | L100: 265.45 | M100: 0 | N100: =(J100-K100)+(L100-M100) -> 1059.61 | O100: =SUM(F100,G100,H100,N100) -> 10386.93
A101: July 14 - July 20 2025 | C101: 13643.59 | D101: 243 | E101: 13688.31 | F101: 11860.5 | G101: 26.7 | H101: 341.74 | I101: 1459.37 | J101: 1110.44 | K101: 44.72 | L101: 348.93 | M101: 0 | N101: =(J101-K101)+(L101-M101) -> 1414.65 | O101: =SUM(F101,G101,H101,N101) -> 13643.59
A102: July 21 - July 27 2025 | C102: 10566.3 | D102: 206 | E102: 10642.24 | F102: 9525.54 | G102: 0 | H102: 125.73 | I102: 990.97 | J102: 717.72 | K102: 36.65 | L102: 233.96 | M102: 0 | N102: =(J102-K102)+(L102-M102) -> 915.03 | O102: =SUM(F102,G102,H102,N102) -> 10566.3
A103: July 28 - Aug 03 2025 | C103: 12459.64 | D103: 225 | E103: 12405.39 | F103: 11157.71 | G103: 0 | H103: 89.2 | I103: 1158.48 | J103: 970.8 | K103: 58.54 | L103: 300.47 | M103: 0 | N103: =(J103-K103)+(L103-M103) -> 1212.73 | O103: =SUM(F103,G103,H103,N103) -> 12459.64
A104: Aug 04 - Aug 10 2025 | C104: 12855.72 | D104: 237 | E104: 12896.88 | F104: 11045.27 | G104: 0 | H104: 783.83 | I104: 1067.78 | J104: 987.1 | K104: 81.96 | L104: 121.48 | M104: 0 | N104: =(J104-K104)+(L104-M104) -> 1026.62 | O104: =SUM(F104,G104,H104,N104) -> 12855.72
A105: Aug 11 - Aug 17 2025 | C105: 12872.15 | D105: 242 | E105: 12639.76 | F105: 11463.17 | G105: 0 | H105: 197.88 | I105: 978.71 | J105: 877.55 | K105: 23.41 | L105: 356.96 | M105: 0 | N105: =(J105-K105)+(L105-M105) -> 1211.1 | O105: =SUM(F105,G105,H105,N105) -> 12872.15
A106: Aug 18 - Aug 24 2025 | C106: 10497 | D106: 187 | E106: 10497 | F106: 10497 | G106: 0 | H106: 0 | I106: 0 | J106: 0 | K106: 0 | L106: 0 | M106: 0 | N106: =(J106-K106)+(L106-M106) -> 0 | O106: =SUM(F106,G106,H106,N106) -> 10497
A107: Aug 25 - Aug 31 2025 | C107: 11997.6 | D107: 203 | E107: 11997.6 | F107: 11997.6 | G107: 0 | H107: 0 | I107: 0 | J107: 0 | K107: 0 | L107: 0 | M107: 0 | N107: =(J107-K107)+(L107-M107) -> 0 | O107: =SUM(F107,G107,H107,N107) -> 11997.6
A108: Sep 01 - Sep 07 2025 | C108: 8874.78 | D108: 161 | E108: 8874.78 | F108: 8874.78 | G108: 0 | H108: 0 | I108: 0 | J108: 0 | K108: 0 | L108: 0 | M108: 0 | N108: =(J108-K108)+(L108-M108) -> 0 | O108: =SUM(F108,G108,H108,N108) -> 8874.78
A109: Sep 08 - Sep 14 2025 | C109: 7867.66 | D109: 172 | E109: 7884.54 | F109: 6803.25 | G109: 16 | H109: 0 | I109: 1065.29 | J109: 857.56 | K109: 16.88 | L109: 207.73 | M109: 0 | N109: =(J109-K109)+(L109-M109) -> 1048.41 | O109: =SUM(F109,G109,H109,N109) -> 7867.66
A110: Sep 15 - Sep 21 2025 | C110: 10059.02 | D110: 192 | E110: 9851.17 | F110: 8317.36 | G110: 0 | H110: 356.07 | I110: 1177.74 | J110: 1168.2 | K110: 34.55 | L110: 251.94 | M110: 0 | N110: =(J110-K110)+(L110-M110) -> 1385.59 | O110: =SUM(F110,G110,H110,N110) -> 10059.02
A111: Sep 22 - Sep 28 2025 | C111: 10456.68 | D111: 211 | E111: 10490.45 | F111: 9252.2 | G111: 45.47 | H111: 208.17 | I111: 984.61 | J111: 749.11 | K111: 33.77 | L111: 235.5 | M111: 0 | N111: =(J111-K111)+(L111-M111) -> 950.84 | O111: =SUM(F111,G111,H111,N111) -> 10456.68
A112: Sep 29 - Oct 05 2025 | C112: 10003.53 | D112: 212 | E112: 10012.74 | F112: 7883.79 | G112: 35.99 | H112: 586.68 | I112: 1506.28 | J112: 1399.07 | K112: 9.21 | L112: 107.21 | M112: 0 | N112: =(J112-K112)+(L112-M112) -> 1497.07 | O112: =SUM(F112,G112,H112,N112) -> 10003.53
A113: Oct 6 - Oct 12 2025 | C113: 13215.5 | D113: 265 | E113: 13010.99 | F113: 11562.67 | G113: 44.4 | H113: 212.86 | I113: 1191.06 | J113: 1340.97 | K113: 0 | L113: 54.6 | M113: 0 | N113: =(J113-K113)+(L113-M113) -> 1395.57 | O113: =SUM(F113,G113,H113,N113) -> 13215.5
A114: Oct 13 - Oct 19 2025 | C114: 10158.93 | E114: 10020.64 | F114: 8901.79 | G114: 26.4 | H114: 218.37 | I114: 874.08 | J114: 870.6 | K114: 0 | L114: 141.77 | M114: 0 | N114: =(J114-K114)+(L114-M114) -> 1012.37 | O114: =SUM(F114,G114,H114,N114) -> 10158.93
A115: Oct 20 - Oct 26 2025 | C115: 9296.11 | E115: 9135.37 | F115: 8370.62 | G115: 18 | H115: 128.7 | I115: 618.05 | J115: 476.39 | K115: 0 | L115: 302.4 | M115: 0 | N115: =(J115-K115)+(L115-M115) -> 778.79 | O115: =SUM(F115,G115,H115,N115) -> 9296.11
A116: Oct 27 - Nov 02 2025 | C116: 11458.33 | D116: 232 | E116: 11249.53 | F116: 10368.76 | G116: 0 | H116: 356.86 | I116: 523.89 | J116: 638.65 | K116: 0 | L116: 94.06 | M116: 0 | N116: =(J116-K116)+(L116-M116) -> 732.71 | O116: =SUM(F116,G116,H116,N116) -> 11458.33
A117: Nov 03 - Nov 09 2025 | C117: 9556.88 | D117: 213 | E117: 9503.78 | F117: 8134.81 | G117: 0 | H117: 473.43 | I117: 895.54 | J117: 872.76 | K117: 0 | L117: 75.88 | M117: 0 | N117: =(J117-K117)+(L117-M117) -> 948.64 | O117: =SUM(F117,G117,H117,N117) -> 9556.88
A118: Nov 10 - Nov 16 2025 | C118: 11258.8 | D118: 231 | E118: 11177.8 | F118: 9729.76 | G118: 18 | H118: 298.58 | I118: 1131.46 | J118: 934.78 | K118: 0 | L118: 277.68 | M118: 0 | N118: =(J118-K118)+(L118-M118) -> 1212.46 | O118: =SUM(F118,G118,H118,N118) -> 11258.8
A119: Nov 17 - Nov 23 2025 | C119: 10628.84 | D119: 247 | E119: 10660.61 | F119: 8845.04 | G119: 0 | H119: 386.88 | I119: 1428.69 | J119: 1125.46 | K119: 31.77 | L119: 303.23 | M119: 0 | N119: =(J119-K119)+(L119-M119) -> 1396.92 | O119: =SUM(F119,G119,H119,N119) -> 10628.84
A120: Nov 24 - Nov 30 2025 | C120: 9557.27 | D120: 213 | E120: 9596.81 | F120: 7700.59 | G120: 32.86 | H120: 378.37 | I120: 1484.99 | J120: 1090.76 | K120: 48.54 | L120: 403.23 | M120: 0 | N120: =(J120-K120)+(L120-M120) -> 1445.45 | O120: =SUM(F120,G120,H120,N120) -> 9557.27
A121: Dec 01 - Dec 07 2025 | C121: 10839.45 | D121: 231 | E121: 10964.28 | F121: 9373.59 | G121: 0 | H121: 373.48 | I121: 1217.21 | J121: 1217.21 | K121: 144.63 | L121: 19.8 | M121: 0 | N121: =(J121-K121)+(L121-M121) -> 1092.38 | O121: =SUM(F121,G121,H121,N121) -> 10839.45
A122: Dec 08 - Dec 14 2025 | C122: 10098.84 | D122: 232 | E122: 10104.58 | F122: 8819.74 | G122: 0 | H122: 325.78 | I122: 959.06 | J122: 870.31 | K122: 116.46 | L122: 199.47 | M122: 0 | N122: =(J122-K122)+(L122-M122) -> 953.32 | O122: =SUM(F122,G122,H122,N122) -> 10098.84
A123: Dec 15 - Dec 21 2025 | C123: 9999.42 | D123: 231 | E123: 10081.53 | F123: 8234.32 | G123: 0 | H123: 233.99 | I123: 1613.22 | J123: 1617.42 | K123: 162.81 | L123: 76.5 | M123: 0 | N123: =(J123-K123)+(L123-M123) -> 1531.11 | O123: =SUM(F123,G123,H123,N123) -> 9999.42
A124: Dec 22 - Dec 28 2025 | C124: 12495.92 | D124: 256 | E124: 12583.24 | F124: 11296.1 | G124: 99.9 | H124: 370.57 | I124: 816.67 | J124: 761.11 | K124: 47.34 | L124: 15.58 | M124: 0 | N124: =(J124-K124)+(L124-M124) -> 729.35 | O124: =SUM(F124,G124,H124,N124) -> 12495.92
A125: Dec 29 - Jan 04 2026 | C125: 15834.44 | D125: 266 | E125: 15977.27 | F125: 14098 | G125: 26.4 | H125: 447.86 | I125: 1405.01 | J125: 1321.92 | K125: 145.83 | L125: 86.09 | M125: 0 | N125: =(J125-K125)+(L125-M125) -> 1262.18 | O125: =SUM(F125,G125,H125,N125) -> 15834.44
A126: Jan 05 - Jan 11 2026 | C126: 10791.09 | D126: 228 | E126: 10864.78 | F126: 8761 | G126: 36 | H126: 533.57 | I126: 1534.21 | J126: 1434.12 | K126: 110.67 | L126: 137.07 | M126: 0 | N126: =(J126-K126)+(L126-M126) -> 1460.52 | O126: =SUM(F126,G126,H126,N126) -> 10791.09
A127: Jan 12 - Jan 18 2026 | C127: 9148.82 | D127: 233 | E127: 9272.43 | F127: 7249.5 | G127: 148.63 | H127: 352.26 | I127: 1522.04 | J127: 1409.88 | K127: 176.41 | L127: 164.96 | M127: 0 | N127: =(J127-K127)+(L127-M127) -> 1398.43 | O127: =SUM(F127,G127,H127,N127) -> 9148.82
A128: Jan 19 - Jan 25 2026 | C128: 7484.15 | D128: 169 | E128: 7035.68 | F128: 5989.34 | G128: 71.99 | H128: 211.88 | I128: 762.47 | J128: 1221.28 | K128: 64.32 | L128: 53.98 | M128: 0 | N128: =(J128-K128)+(L128-M128) -> 1210.94 | O128: =SUM(F128,G128,H128,N128) -> 7484.15
A129: Jan 26 - Feb 01 2026 | C129: 12885.71 | D129: 258 | E129: 13040.8 | F129: 10587.8 | G129: 35.1 | H129: 598.34 | I129: 1819.56 | J129: 1613.28 | K129: 173.79 | L129: 224.98 | M129: 0 | N129: =(J129-K129)+(L129-M129) -> 1664.47 | O129: =SUM(F129,G129,H129,N129) -> 12885.71
A130: Feb 02 - Feb 08 2026 | C130: 9877.11 | D130: 228 | E130: 10029.91 | F130: 7893.33 | G130: 0 | H130: 780.31 | I130: 1356.27 | J130: 1237.97 | K130: 81.3 | L130: 46.8 | M130: 0 | N130: =(J130-K130)+(L130-M130) -> 1203.47 | O130: =SUM(F130,G130,H130,N130) -> 9877.11
A131: Feb 09 - Feb 15 2026 | C131: 11815.51 | D131: 254 | E131: 11900.88 | F131: 9667.07 | G131: 0 | H131: 586.24 | I131: 1647.57 | J131: 1436.5 | K131: 194.37 | L131: 320.07 | M131: 0 | N131: =(J131-K131)+(L131-M131) -> 1562.2 | O131: =SUM(F131,G131,H131,N131) -> 11815.51
A132: Feb 16 - Feb 22 2026 | C132: 11786.08 | D132: 243 | E132: 11926.06 | F132: 10361.85 | G132: 0 | H132: 344.39 | I132: 1219.82 | J132: 1081.55 | K132: 98.28 | L132: 96.57 | M132: 0 | N132: =(J132-K132)+(L132-M132) -> 1079.84 | O132: =SUM(F132,G132,H132,N132) -> 11786.08
A133: Feb 23 - Mar 1 2026 | C133: 12567.75 | D133: 227 | E133: 12574.59 | F133: 10807.66 | G133: 0 | H133: 407.99 | I133: 1358.94 | J133: 1270.15 | K133: 48.54 | L133: 130.49 | M133: 0 | N133: =(J133-K133)+(L133-M133) -> 1352.1 | O133: =SUM(F133,G133,H133,N133) -> 12567.75
A134: Mar 02 - Mar 08 2026 | C134: 17936.73 | D134: 281 | E134: 18019.79 | F134: 15784.69 | G134: 90 | H134: 578.51 | I134: 1566.59 | J134: 1265.65 | K134: 157.02 | L134: 374.9 | M134: 0 | N134: =(J134-K134)+(L134-M134) -> 1483.53 | O134: =SUM(F134,G134,H134,N134) -> 17936.73
A135: Mar 09 - Mar 15 2026 | C135: 21368.16 | D135: 306 | E135: 21494.82 | F135: 19213.18 | G135: 0 | H135: 696.74 | I135: 1584.9 | J135: 1321.58 | K135: 126.66 | L135: 263.32 | M135: 0 | N135: =(J135-K135)+(L135-M135) -> 1458.24 | O135: =SUM(F135,G135,H135,N135) -> 21368.16
A136: Mar 16 - Mar 22 2026 | C136: 24661.29 | D136: 357 | E136: 24820.5 | F136: 22041.38 | G136: 0 | H136: 531.52 | I136: 2247.6 | J136: 2039.85 | K136: 159.21 | L136: 207.75 | M136: 0 | N136: =(J136-K136)+(L136-M136) -> 2088.39 | O136: =SUM(F136,G136,H136,N136) -> 24661.29
... A139: Apr 06 - Apr 12 | C139: 11206.32 | D139: 240 | E139: 11284.56 | F139: 8914.17 | G139: 0 | H139: 417 | I139: 1953.39 | J139: 1824.77 | K139: 161.4 | L139: 211.78 | M139: 0 | N139: =(J139-K139)+(L139-M139) -> 1875.15 | O139: =SUM(F139,G139,H139,N139) -> 11206.32
A140: Apr 13 - Apr 19 | C140: 11891.16 | D140: 234 | E140: 11963.28 | F140: 9875.21 | G140: 105.99 | H140: 424.15 | I140: 1557.93 | J140: 1335.86 | K140: 142.23 | L140: 292.18 | M140: 0 | N140: 1485.81 | O140: 11891.16
A141: Apr 20 - Apr 26 | C141: 11986.83 | D141: 263 | E141: 12053.58 | F141: 9987.25 | G141: 57.8 | H141: 511.5 | I141: 1497.03 | J141: 1287.17 | K141: 105.75 | L141: 248.86 | M141: 0 | N141: =(J141-K141)+(L141-M141) -> 1430.28 | O141: =SUM(F141,G141,H141,N141) -> 11986.83
A142: Apr 27 - May 03 | C142: 11275.7 | D142: 242 | E142: 11409.86 | F142: 9045.72 | G142: 0 | H142: 495.73 | I142: 1868.41 | J142: $1,493.39 | K142: $134.16 | L142: 375.02 | M142: 0 | N142: =(J142-K142)+(L142-M142) -> 1734.25 | O142: =SUM(F142,G142,H142,N142) -> 11275.7
...

Sheet Kababwala
A1: Statement For Selected Period | C1: Total Revenue | H1: 2021 | K1: 2023
A2: August 28 2023 - September 3 2023 | C2: 18907.64 | H2: January | I2: 74079.49 | J2: 87281.23 | K2: January | N2: 69403.69
A3: September 4 2023 - September 10 2023 | C3: 16117.29 | H3: February | I3: 68100.95 | J3: 63034.51 | K3: February | N3: 62943.14 | O3: 384
A4: September 11 2023 - September 17 2023 | C4: 13973.31 | H4: March | I4: 77326.19 | J4: 64569.19 | K4: March | N4: 69917.17 | O4: 6412.27
A5: September 18 2023 - September 24 2023 | C5: 15058.21 | H5: April | I5: 74335 | J5: 66704.55 | K5: April | N5: 85521.5 | O5: 3821.88
A6: September 25 2023 - October 1 2023 | C6: 14752.34 | H6: May | I6: 101590.8 | J6: 86171.39 | K6: May | N6: 78013.1 | O6: 4152
A7: October 2 2023 - October 8 2023 | C7: 16461.74 | H7: June | I7: 77714.7 | J7: 78073.55 | K7: June | N7: 88939.31 | O7: 2856
A8: October 9 2023 - October 15 2023 | C8: 15751.3 | H8: July | I8: 91085.51 | J8: 98373.87 | K8: July | N8: 95569.19 | O8: 2237.6
A9: October 16 2023 - October 22 2023 | C9: 14944.6 | H9: August | I9: 80633.19 | J9: 77958.51 | K9: August | N9: 83798.18 | O9: 4480
A10: October 23 2023 - October 29 2023 | C10: 15238.49 | H10: September | I10: 75143.44 | J10: 76305.52 | K10: September | N10: 68745.39 | O10: 3384
A11: October 30 2023 - November 5 2023 | C11: 16537.96 | H11: October | I11: 83713.46 | J11: 82557.77 | K11: October | N11: 67822.85 | O11: 3832
A12: November 6 2023 - November 12 2023 | C12: 16254.22 | H12: November | I12: 70757.44 | J12: 76685.89 | K12: November
A13: November 13 2023 - November 19 2023 | C13: 16419.73 | H13: December | I13: 92026.07 | J13: 84136.76 | K13: December
A14: November 20 2023 - November 26 2023 | C14: 16688.44
A15: November 27 2023 - December 03 2024 | C15: 14806.91
A17: December 04 2023 - December 10 2024 | C17: 14923.3
A18: December 11 2023 - December 17 2024 | C18: 14084.19
A19: December 18 2023 - December 24 2024 | C19: 17814.62
A20: December 25 2023 - December 31 2024 | C20: 19192.27
A21: Jan 1 - Jan 07 2024 | C21: 14988.73
A22: Jan 8 - Jan 14 2024 | C22: 10837.15
A23: Jan 15 - Jan 21 2024 | C23: 13313.4
A24: Jan 22 - Jan 28 2025 | C24: 12023.55
A25: Jan 29 - Feb 04 2026 | C25: 11182.05
A26: Feb 05 - Feb 11 2026 | C26: 10837.15
... A40: May 13 - May 19 2024 | C40: 14598.85
A41: May 20 - May 26 2024 | C41: $13,235.24 + $2,003.04 = 15,238.28
A42: May 27 - Jun 02 2024 | C42: 15801.56
A43: Jun 03 - Jun 09 2024 | C43: 13718.57
A44: Jun 10 - Jun 16 2024 | C44: 16076.79
A45: Jun 17 - Jun 23 2024 | C45: 16021.38
A46: Jun 24 - Jun 30 2024 | C46: 16792.57
A47: Jul 1 - Jul 7 2024 | C47: 17314.17
A48: Jul 8 - Jul 14 2024 | C48: 15062.86
A49: Jul 15 - Jul 21 2024 | C49: =14363.75+1000 -> 15363.75
A50: Jul 22 - Jul 28 2024 | C50: 15367.46
A51: Jul 29 - Aug 04 2024 | C51: 16876.78
A52: Aug 05 - Aug 11 2024 | C52: 16542.52
A53: Aug 12 - Aug 18 2024 | C53: 15998.15
A54: Aug 19 - Aug 25 2024 | C54: 14843.19
A55: Aug 26 - Sep 01 2024 | C55: 16321.93
A56: Sep 02 - Sep 08 2024 | C56: 14169.96
A57: Sep 09 - Sep 15 2024 | C57: 15887.78
A58: Sep 16 - Sep 22 2024 | C58: 13026.28
A59: Sep 23 - Sep 29 2024 | C59: 14420.09
A60: Sep 30 - Oct 06 2024 | C60: 14926.92
A61: Oct 07 - Oct 13 2024 | C61: 14709.53
... A69: Dec 02 - Dec 08 2024 | C69: 13708.62
A70: Dec 09 - Dec 15 2024 | C70: 16310.34 | D70: Bill Count | E70: TB Total | F70: In-Store | G70: Skip | H70: DD | I70: Uber (TB) | J70: KKW Earnings | K70: KKW Marketing | L70: Smash Earnings | M70: Smash Marketing | N70: Uber Total
A71: Dec 16 - Dec 22 2024 | C71: 17615.42
A72: Dec 23 - Dec 29 2024 | C72: 21769.94 | G72: 396.9 | H72: 339.49 | I72: 2630.08
A73: Dec 30 - Jan 05 2025 | C73: 17723.83 | G73: 71.96 | H73: 468.65 | I73: 1724.06
A74: Jan 06 - Jan 12 2025 | C74: 13819.59
A75: Jan 13 - Jan 19 2025 | C75: =SUM(F75,G75,H75,N75) -> 17437.22 | F75: 14797.45 | G75: 138.55 | H75: 549.91 | I75: 2238.24 | J75: 2246.27 | K75: 294.96 | N75: =(J75-K75) -> 1951.31
A76: Jan 20 - Jan 26 2025 | C76: =SUM(F76,G76,H76,N76) -> 13915.09 | F76: 11263.85 | G76: 35 | H76: 480.57 | I76: 2568.55 | J76: 2568.55 | K76: 432.88 | N76: =(J76-K76) -> 2135.67
A77: Jan 27 - Feb 02 2025 | C77: =SUM(F77,G77,H77,N77) -> 14768.12 | F77: 12102.9 | G77: 89.28 | H77: 454.7 | I77: 2514.6 | J77: 2539.78 | K77: 418.54 | N77: =(J77-K77) -> 2121.24
A78: Feb 03 - Feb 09 2025 | C78: =SUM(F78,G78,H78,N78) -> 13793.78 | F78: 10274.77 | G78: 195.67 | H78: 599.59 | I78: 3203.38 | J78: 3150.61 | K78: 426.86 | N78: =(J78-K78) -> 2723.75
A79: Feb 10 - Feb 16 2025 | C79: =SUM(F79,G79,H79,N79) -> 12803.8 | F79: 10539.78 | G79: 234.24 | H79: 187.04 | I79: 2082.29 | J79: 2170.1 | K79: 327.36 | N79: =(J79-K79) -> 1842.74
A80: Feb 17 - Feb 23 2025 | C80: =SUM(F80,G80,H80,N80) -> 17889.5 | F80: 15612.65 | G80: 126.49 | H80: 204.9 | I80: 2375.33 | J80: 2375.33 | K80: 429.87 | N80: =(J80-K80) -> 1945.46
A81: Feb 24 - Mar 02 2025 | C81: =SUM(F81,G81,H81,N81) -> 11635.75 | F81: 9357.28 | G81: 156.53 | H81: 255.33 | I81: 2145.99 | J81: 2145.99 | K81: 279.38 | N81: =(J81-K81) -> 1866.61
A82: Mar 03 - Mar 09 2025 | C82: =SUM(F82,G82,H82,N82) -> 13056.51 | F82: 11083.03 | G82: 92.94 | H82: 242.7 | I82: 2140.3 | J82: 2140.3 | K82: 502.46 | N82: =(J82-K82) -> 1637.84
A83: Mar 10 - Mar 16 2025 | C83: =SUM(F83,G83,H83,N83) -> 14539.48 | F83: 12203.82 | G83: 403.24 | H83: 572.37 | I83: 1726.85 | J83: 1726.85 | K83: 366.8 | N83: =(J83-K83) -> 1360.05
A84: Mar 17 - Mar 23 2025 | C84: =SUM(F84,G84,H84,N84) -> 14351.51 | F84: 11772.36 | G84: 307.37 | H84: 229.5 | I84: 3043.9 | J84: 3043.9 | K84: 1001.62 | N84: =(J84-K84) -> 2042.28
A85: Mar 24 - Mar 30 2025 | C85: =SUM(F85,G85,H85,N85) -> 21036.12 | F85: 17239.64 | G85: 75.97 | H85: 329.42 | I85: 3407.34 | J85: 3802.37 | K85: 411.28 | N85: =(J85-K85) -> 3391.09
A86: Mar 31 - Apr 6 2025 | C86: =SUM(F86,G86,H86,N86) -> 19061.44 | F86: 15982.93 | G86: 99.57 | H86: 325.63 | I86: 2164.85 | J86: 2918.88 | K86: 265.57 | N86: =(J86-K86) -> 2653.31
... A90: Apr 28 - May 04 2025 | C90: =SUM(F90,G90,H90,N90) -> 17619.91 | F90: 15402.32 | G90: 63.37 | H90: 188.26 | I90: 1723.69 | J90: 2141.96 | K90: 176 | N90: =(J90-K90) -> 1965.96
A91: May 05 - May 11 2025 | C91: =SUM(F91,G91,H91,N91) -> 16280.44 | E91: 16181.36 | F91: 14028.63 | G91: 91.55 | H91: 91.14 | I91: 1970.04 | J91: 2491.78 | K91: 422.66 | N91: =(J91-K91) -> 2069.12
A92: May 12 - May 18 2025 | C92: =SUM(F92,G92,H92,N92) -> 17731.8 | E92: 17390.45 | F92: 15192.66 | G92: 30.08 | H92: 136.91 | I92: 2030.8 | J92: 2580.15 | K92: 208 | N92: =(J92-K92) -> 2372.15
A93: May 19 - May 25 2025 | C93: =SUM(F93,G93,H93,N93) -> 17165.91 | E93: 16865.13 | F93: 14131.51 | G93: 98.46 | H93: 148.87 | I93: 2486.29 | J93: 3107.07 | K93: 320 | N93: =(J93-K93) -> 2787.07
A94: May 26 - June 01 2025 | C94: =SUM(F94,G94,H94,N94) -> 19276.9 | E94: 19146.4 | F94: 16228.53 | G94: 21.8 | H94: 251.15 | I94: 2644.92 | J94: 3015.42 | K94: 240 | N94: =(J94-K94) -> 2775.42
A95: June 02 - June 08 2025 | C95: =SUM(F95,G95,H95,N95) -> 22000.12 | E95: 21760.9 | F95: 18673.66 | G95: 58.35 | H95: 67.93 | I95: 2960.96 | J95: 3616.18 | K95: 416 | N95: =(J95-K95) -> 3200.18
A96: June 09 - June 15 2025 | C96: =SUM(F96,G96,H96,N96) -> 17912.97 | E96: 17684.01 | F96: 14687.63 | G96: 19.62 | H96: 358.51 | I96: 2618.25 | J96: 3119.21 | K96: 272 | N96: =(J96-K96) -> 2847.21
A97: June 16 - June 22 2025 | C97: =SUM(F97,G97,H97,N97) -> 17516.68 | E97: 17394.72 | F97: 14622.01 | G97: 18.66 | H97: 268.59 | I97: 2485.46 | J97: 2895.42 | K97: 288 | N97: =(J97-K97) -> 2607.42
A98: June 23 - June 29 2025 | C98: =SUM(F98,G98,H98,N98) -> 17475.77 | E98: 17356.78 | F98: 14263.59 | G98: 190.74 | H98: 109.76 | I98: 2792.69 | J98: 3260.36 | K98: 348.68 | N98: =(J98-K98) -> 2911.68
A99: June 30 - July 06 2025 | C99: =SUM(F99,G99,H99,N99) -> 18753.5 | E99: 18326.25 | F99: 15286 | G99: 251.99 | H99: 238.03 | I99: 2550.23 | J99: 3041.18 | K99: 63.7 | N99: =(J99-K99) -> 2977.48
A100: July 07 - July 13 2025 | C100: =SUM(F100,G100,H100,N100) -> 17762.64 | E100: 17307.89 | F100: 15576.3 | G100: 74.21 | H100: 159.33 | I100: 1498.05 | J100: 1965.48 | K100: 12.68 | N100: =(J100-K100) -> 1952.8
A101: July 14 - July 20 2025 | C101: =SUM(F101,G101,H101,N101) -> 16579.27 | D101: 468 | E101: 16318.32 | F101: 14369.87 | G101: 121.34 | H101: 78.54 | I101: 1748.57 | J101: 2041.22 | K101: 31.7 | N101: =(J101-K101) -> 2009.52
A102: July 21 - July 27 2025 | C102: =SUM(F102,G102,H102,N102) -> 19588.48 | D102: 550 | E102: 19250.84 | F102: 16442.69 | G102: 52.11 | H102: 504.12 | I102: 2251.92 | J102: 2640.27 | K102: 50.71 | N102: =(J102-K102) -> 2589.56
A103: July 28 - Aug 03 2025 | C103: =SUM(F103,G103,H103,N103) -> 17781.54 | D103: 506 | E103: 17443.35 | F103: 15595.52 | G103: 96.27 | H103: 18.59 | I103: 1732.97 | J103: 2099.68 | K103: 28.52 | N103: =(J103-K103) -> 2071.16
A104: Aug 04 - Aug 10 2025 | C104: =SUM(F104,G104,H104,N104) -> 19284.33 | D104: 481 | E104: 19115.15 | F104: 17187.14 | G104: 48.28 | H104: 149.36 | I104: 1730.37 | J104: 1899.55 | K104: 0 | N104: =(J104-K104) -> 1899.55
A105: Aug 11 - Aug 17 2025 | C105: =SUM(F105,G105,H105,N105) -> 17665.55 | D105: 544 | E105: 17474.33 | F105: 16262.77 | G105: 73.77 | H105: 301.37 | I105: 836.42 | J105: 1027.64 | K105: 0 | N105: =(J105-K105) -> 1027.64
A106: Aug 18 - Aug 24 2025 | C106: =SUM(F106,G106,H106,N106) -> 16361.97 | D106: 471 | E106: 16199.2 | F106: 14382.84 | G106: 16.79 | H106: 176.02 | I106: 1623.55 | J106: 1786.32 | K106: 0 | L106: 0 | M106: 0 | N106: =(J106-K106) -> 1786.32
A107: Aug 25 - Aug 31 2025 | C107: =SUM(F107,G107,H107,N107) -> 19302.2 | D107: 506 | E107: 19083.93 | F107: 17664.64 | G107: 40.2 | H107: 284.79 | I107: 1094.3 | J107: 1312.57 | K107: 0 | L107: 0 | M107: 0 | N107: =(J107-K107) -> 1312.57
A108: Sep 01 - Sep 07 2025 | C108: =SUM(F108,G108,H108,N108) -> 15827.95 | D108: 422 | E108: 15524.34 | F108: 13926.86 | G108: 0 | H108: 101.18 | I108: 1496.3 | J108: 1799.91 | K108: 0 | L108: 35.97 | M108: 13.58 | N108: =(J108-K108) -> 1799.91
A109: Sep 08 - Sep 14 2025 | C109: =SUM(F109,G109,H109,N109) -> 15869.35 | D109: 424 | E109: 15558.56 | F109: 14364.77 | G109: 89.96 | H109: 90.51 | I109: 1013.32 | J109: 1324.11 | K109: 0 | L109: 71.95 | M109: 20.37 | N109: =(J109-K109) -> 1324.11
A110: Sep 15 - Sep 21 2025 | C110: =SUM(F110,G110,H110,N110) -> 16554.18 | D110: 448 | E110: 16173.27 | F110: 15074.13 | G110: 300.69 | H110: 50.8 | I110: 747.65 | J110: 1128.56 | K110: 0 | L110: 64.75 | M110: 20.97 | N110: =(J110-K110) -> 1128.56
A111: Sep 22 - Sep 28 2025 | C111: =SUM(F111,G111,H111,N111) -> 14618.26 | D111: 401 | E111: 14572.18 | F111: 12695.29 | G111: 206.01 | H111: 384.94 | J111: 1332.02 | K111: 0 | L111: 56.36 | M111: 20.37 | N111: =(J111-K111) -> 1332.02
A112: Sep 29 - Oct 05 2025 | C112: =SUM(F112,G112,H112,N112) -> 14396.65 | D112: 410 | E112: 14113 | F112: 13440.59 | G112: 105.57 | H112: 128.54 | J112: 721.95 | K112: 0 | L112: 0 | M112: 0 | N112: =(J112-K112) -> 721.95
A113: Oct 6 - Oct 12 2025 | C113: =SUM(F113,G113,H113,N113) -> 14525.36 | D113: 399 | E113: 14272.3 | F113: 12482.04 | G113: 216.85 | H113: 387.18 | I113: 1186.23 | J113: 1439.29 | K113: 0 | L113: 0 | M113: 0 | N113: =(J113-K113) -> 1439.29
A114: Oct 13 - Oct 19 2025 | C114: =SUM(F114,G114,H114,N114) -> 16654.76 | E114: 16467.97 | F114: 15056.75 | G114: 106.02 | H114: 265.57 | I114: 1039.63 | J114: 1226.42 | K114: 0 | L114: 0 | M114: 0 | N114: =(J114-K114) -> 1226.42
A115: Oct 20 - Oct 26 2025 | C115: =SUM(F115,G115,H115,N115) -> 13941.02 | D115: 402 | E115: 13914.64 | F115: 12581.93 | G115: 16.75 | H115: 105.62 | I115: 1210.34 | J115: 1218.73 | K115: 0 | L115: 17.99 | M115: 0 | N115: =(J115-K115)+(L115-M115) -> 1236.72
A116: Oct 27 - Nov 02 2025 | C116: =SUM(F116,G116,H116,N116) -> 15573.3 | D116: 419 | E116: 15460.77 | F116: 14139.67 | G116: 262.04 | H116: 274.76 | I116: 784.3 | J116: 896.83 | K116: 0 | L116: 0 | M116: 0 | N116: =(J116-K116)+(L116-M116) -> 896.83
A117: Nov 03 - Nov 09 2025 | C117: =SUM(F117,G117,H117,N117) -> 15102.74 | D117: 424 | E117: 14992.51 | F117: 12944.71 | G117: 166.23 | H117: 191.44 | I117: 1690.13 | J117: 1800.36 | K117: 0 | L117: 0 | M117: 0 | N117: =(J117-K117)+(L117-M117) -> 1800.36
A118: Nov 10 - Nov 16 2025 | C118: =SUM(F118,G118,H118,N118) -> 14148.97 | D118: 405 | E118: 14148.97 | F118: 12257.74 | G118: 319.62 | H118: 181.59 | I118: 1390.02 | J118: 1390.02 | K118: 0 | L118: 0 | M118: 0 | N118: =(J118-K118)+(L118-M118) -> 1390.02
A119: Nov 17 - Nov 23 2025 | C119: =SUM(F119,G119,H119,N119) -> 13645.93 | D119: 409 | E119: 13645.93 | F119: 12298.1 | G119: 200.82 | H119: 215.03 | I119: 931.98 | J119: 931.98 | K119: 0 | L119: 0 | M119: 0 | N119: =(J119-K119)+(L119-M119) -> 931.98
A120: Nov 24 - Nov 30 2025 | C120: =SUM(F120,G120,H120,N120) -> 16560.6 | D120: 426 | E120: 16367.82 | F120: 14586.76 | G120: 140.06 | H120: 209.52 | I120: 1431.48 | J120: 1452.53 | K120: 0 | L120: 247.02 | M120: 75.29 | N120: =(J120-K120)+(L120-M120) -> 1624.26
A121: Dec 01 - Dec 07 2025 | C121: =SUM(F121,G121,H121,N121) -> 12906.63 | D121: 345 | E121: 12906.63 | F121: 11121.57 | G121: 94.62 | H121: 226.27 | I121: 1464.17 | J121: 1431.79 | K121: 0 | L121: 32.38 | M121: 0 | N121: =(J121-K121)+(L121-M121) -> 1464.17
A122: Dec 08 - Dec 14 2025 | C122: =SUM(F122,G122,H122,N122) -> 14096.42 | D122: 381 | E122: 14096.42 | F122: 12319.92 | G122: 31.19 | H122: 408.04 | I122: 1337.27 | J122: 1304.94 | K122: 0 | L122: 32.33 | M122: 0 | N122: =(J122-K122)+(L122-M122) -> 1337.27
A123: Dec 15 - Dec 21 2025 | C123: =SUM(F123,G123,H123,N123) -> 14185.29 | D123: 412 | E123: 14227.25 | F123: 12411.62 | G123: 342.55 | H123: 284.56 | I123: 1188.52 | J123: 1188.52 | K123: 41.96 | L123: 0 | M123: 0 | N123: =(J123-K123)+(L123-M123) -> 1146.56
A124: Dec 22 - Dec 28 2025 | C124: =SUM(F124,G124,H124,N124) -> 18194.47 | D124: 493 | E124: 18278.39 | F124: 16380.94 | G124: 124.14 | H124: 177.73 | I124: 1595.58 | J124: 1595.58 | K124: 83.92 | L124: 0 | M124: 0 | N124: =(J124-K124)+(L124-M124) -> 1511.66
...

Sheet Pizza K Heartland
A1: Statement For Selected Period | C1: Total Revenue | I1: 2021 | K1: 2022 | O1: 2023
A2: August 28 2023 - September 3 2023 | C2: 26049.7 | I2: January | K2: January | O2: January
A3: September 4 2023 - September 10 2023 | C3: 22729.95 | I3: February | K3: February | O3: February
A4: September 11 2023 - September 17 2023 | C4: 19150.68 | I4: March | K4: March | O4: March
A5: September 18 2023 - September 24 2023 | C5: 20976.15 | I5: April | K5: April | O5: April
A6: September 25 2023 - October 1 2023 | C6: 19281.47 | I6: May | K6: May | O6: May
A7: October 2 2023 - October 8 2023 | C7: 21980.84 | I7: June | K7: June | O7: June
A8: October 9 2023 - October 15 2023 | C8: 22217.19 | I8: July | K8: July | O8: July
A9: October 16 2023 - October 22 2023 | C9: 20227.23 | I9: August | K9: August | O9: August
A10: October 23 2023 - October 29 2023 | C10: 21580.85 | I10: September | K10: September | O10: September
A11: October 30 2023 - November 5 2023 | C11: 21160.1 | I11: October | K11: October | O11: October
A12: November 6 2023 - November 12 2023 | C12: 21675.23 | I12: November | K12: November | O12: November
A13: November 13 2023 - November 19 2023 | C13: 21532.99 | I13: December | K13: December | O13: December
A14: November 20 2023 - November 26 2023 | C14: 21351.69
A15: November 27 2023 - December 03 2024 | C15: 18942.47
A16: December 04 2023 - December 10 2024 | C16: 18663.72
A17: December 11 2023 - December 17 2024 | C17: 17784.97
A18: December 18 2023 - December 24 2024 | C18: 20137.82
A19: December 25 2023 - December 31 2024 | C19: 29483.6
A20: Jan 1 - Jan 07 2024 | C20: 19057.18
A21: Jan 8 - Jan 14 2024 | C21: 16748.41
A22: Jan 15 - Jan 21 2024 | C22: 17827.58
A23: Jan 22 - Jan 28 2025 | C23: 15105.89
A24: Jan 29 - Feb 04 2026 | C24: 15592.57
A25: Feb 05 - Feb 11 2026 | C25: 15907.12
... A33: Apr 1 - Apr 07 2024 | C33: 16391.15
A34: Apr 8 - Apr 14 2024 | C34: 21,423.57
A35: Apr 15 - Apr 21 2024 | C35: 16814.71
A36: Apr 22 - Apr 28 2024 | C36: 14692.87
A37: Apr 29 - May 5 2024 | C37: 16252.68
A38: May 6 - May 12 2024 | C38: 14728.67
A39: May 13 - May 19 2024 | C39: 16675.46
A40: May 20 - May 26 2024 | C40: 15420.47
A41: May 27 - Jun 02 2024 | C41: 15964.98
A42: Jun 03 - Jun 09 2024 | C42: 16516.16
A43: Jun 10 - Jun 16 2024 | C43: 17167.97
A44: Jun 17 - Jun 23 2024 | C44: 17725.56
A45: Jun 24 - Jun 30 2024 | C45: 19207.7
A46: Jul 1 - Jul 7 2024 | C46: 18274.48
... A64: Nov 4 - Nov 10 2024 | C64: 15474.42
A65: Nov 11 - Nov 17 2024 | C65: =SUM(13899.62+1,994.45) -> 14895.07
A66: Nov 18 - Nov 24 2024 | C66: 16341.37
A67: Nov 25 - Dec 01 2024 | C67: 16532.36
A68: Dec 02 - Dec 08 2024 | C68: 15030.78
A69: Dec 09 - Dec 15 2024 | C69: 16764.57
A70: Dec 16 - Dec 22 2024 | C70: 16721.17
A71: Dec 23 - Dec 29 2024 | C71: 21254.87
A72: Dec 30 - Jan 05 2025 | C72: 20346.11
A73: Jan 06 - Jan 12 2025 | C73: 14240.06
A74: Jan 13 - Jan 19 2025 | C74: 16283.67
A75: Jan 20 - Jan 26 2025 | C75: 14767.44 | D75: Bill Count | E75: TB Total | F75: In Store | G75: Skip | H75: DD | I75: Uber TB | J75: PK Uber Rev | K75: PK Uber Disc | L75: Chick Uber Rev | M75: Chick Uber Disc | N75: Uber (After Discount) | O75: Total Revenue
A76: Jan 27 - Feb 02 2025 | C76: 14748.59
A77: Feb 03 - Feb 09 2025 | C77: 15602.64
A78: Feb 10 - Feb 16 2025 | C78: 15478.89
A79: Feb 17 - Feb 23 2025 | C79: 14771.2
A80: Feb 24 - Mar 02 2025 | C80: 15040.69 | F80: 8797.31 | G80: 0 | H80: 592.94 | I80: 6194.86 | J80: 6504.26 | K80: 853.82 | N80: =(J80-K80) -> 5650.44 | O80: =SUM(F80,G80,H80,N80) -> 15040.69
A81: Mar 03 - Mar 09 2025 | C81: 14005.79 | F81: 8498.44 | G81: 18 | H81: 618.26 | I81: 5654.05 | J81: 5545.45 | K81: 674.36 | N81: =(J81-K81) -> 4871.09 | O81: =SUM(F81,G81,H81,N81) -> 14005.79
A82: Mar 10 - Mar 16 2025 | C82: 17960.77 | F82: 11737.05 | G82: 18 | H82: 836.45 | I82: 6107.47 | J82: 6192.2 | K82: 822.93 | N82: =(J82-K82) -> 5369.27 | O82: =SUM(F82,G82,H82,N82) -> 17960.77
A83: Mar 17 - Mar 23 2025 | C83: 16952.08 | F83: 10632.6 | G83: 0 | H83: 752.41 | I83: 6265.03 | J83: 6315.3 | K83: 748.23 | N83: =(J83-K83) -> 5567.07 | O83: =SUM(F83,G83,H83,N83) -> 16952.08
A84: Mar 24 - Mar 30 2025 | C84: 22509.7 | F84: 13752.97 | G84: 33.6 | H84: 766.22 | I84: 9114.38 | J84: 8843.04 | K84: 886.13 | N84: =(J84-K84) -> 7956.91 | O84: =SUM(F84,G84,H84,N84) -> 22509.7
A85: Mar 31 - Apr 6 2025 | C85: 18697.92 | F85: 11613.99 | G85: 16.8 | H85: 618.55 | I85: 6317.19 | J85: 6540.64 | K85: 92.06 | N85: =(J85-K85) -> 6448.58 | O85: =SUM(F85,G85,H85,N85) -> 18697.92
A86: Apr 7 - Apr 13 2025 | C86: 18346.93 | F86: 11330.03 | G86: 0 | H86: 795.99 | I86: 6615.11 | J86: 6659.11 | K86: 438.2 | N86: =(J86-K86) -> 6220.91 | O86: =SUM(F86,G86,H86,N86) -> 18346.93
A87: Apr 14 - Apr 20 2025 | C87: 22019.12 | F87: 15405.08 | G87: 0 | H87: 766.89 | I87: 6185.37 | J87: 6199.77 | K87: 352.62 | N87: =(J87-K87) -> 5847.15 | O87: =SUM(F87,G87,H87,N87) -> 22019.12
A88: Apr 21 - Apr 27 2025 | C88: 19924.78 | F88: 13208.43 | G88: 0 | H88: 760.95 | I88: 6037.59 | J88: 6273.42 | K88: 318.02 | N88: =(J88-K88) -> 5955.4 | O88: =SUM(F88,G88,H88,N88) -> 19924.78
A89: Apr 28 - May 04 2025 | C89: 18624.93 | F89: 12668.7 | G89: 0 | H89: 761.11 | I89: 5482.23 | J89: 5433.03 | K89: 237.91 | N89: =(J89-K89) -> 5195.12 | O89: =SUM(F89,G89,H89,N89) -> 18624.93
A90: May 05 - May 11 2025 | C90: 19498.52 | E90: 19737.83 | F90: 12744.63 | G90: 0 | H90: 654.27 | I90: 6338.93 | J90: 6414.53 | K90: 314.91 | N90: =(J90-K90) -> 6099.62 | O90: =SUM(F90,G90,H90,N90) -> 19498.52
A91: May 12 - May 18 2025 | C91: 20394.58 | E91: 20649.48 | F91: 14025.42 | G91: 0 | H91: 592.17 | I91: 6031.89 | J91: 6045.59 | K91: 268.6 | L91: 0 | M91: 0 | N91: =(J91-K91)+(L91-M91) -> 5776.99 | O91: =SUM(F91,G91,H91,N91) -> 20394.58
A92: May 19 - May 25 2025 | C92: 20875.25 | E92: 21289.71 | F92: 14091.25 | G92: 0 | H92: 788.06 | I92: 6410.4 | J92: 6403.2 | K92: 407.26 | L92: 0 | M92: 0 | N92: =(J92-K92)+(L92-M92) -> 5995.94 | O92: =SUM(F92,G92,H92,N92) -> 20875.25
A93: May 26 - June 01 2025 | C93: 17203.22 | E93: 17476.95 | F93: 12195.79 | G93: 0 | H93: 191.68 | I93: 5089.48 | J93: 5056.95 | K93: 241.2 | L93: 0 | M93: 0 | N93: =(J93-K93)+(L93-M93) -> 4815.75 | O93: =SUM(F93,G93,H93,N93) -> 17203.22
A94: June 02 - June 08 2025 | C94: 20126.24 | E94: 20551.17 | F94: 14724.33 | G94: 0 | H94: 0 | I94: 5826.84 | J94: 5722.64 | K94: 337.51 | L94: 16.78 | M94: 0 | N94: =(J94-K94)+(L94-M94) -> 5401.91 | O94: =SUM(F94,G94,H94,N94) -> 20126.24
A95: June 09 - June 15 2025 | C95: 18988.3 | E95: 19206.44 | F95: 13152.36 | G95: 0 | H95: 0 | I95: 6054.08 | J95: 6194.41 | K95: 358.47 | L95: 0 | M95: 0 | N95: =(J95-K95)+(L95-M95) -> 5835.94 | O95: =SUM(F95,G95,H95,N95) -> 18988.3
A96: June 16 - June 22 2025 | C96: 19779.16 | F96: 13642.9 | G96: 0 | H96: 0 | I96: 6320.19 | J96: 6420.25 | K96: 283.99 | L96: 0 | M96: 0 | N96: =(J96-K96)+(L96-M96) -> 6136.26 | O96: =SUM(F96,G96,H96,N96) -> 19779.16
A97: June 23 - June 29 2025 | C97: 19888.39 | E97: 20181.46 | F97: 13603.1 | G97: 0 | H97: 0 | I97: 6578.36 | J97: 6623.24 | K97: 337.95 | L97: 0 | M97: 0 | N97: =(J97-K97)+(L97-M97) -> 6285.29 | O97: =SUM(F97,G97,H97,N97) -> 19888.39
A98: June 30 - July 06 2025 | C98: 20241.86 | E98: 20244.38 | F98: 15069.42 | G98: 0 | H98: 0 | I98: 5174.96 | J98: 5205.26 | K98: 32.82 | L98: 0 | M98: 0 | N98: =(J98-K98)+(L98-M98) -> 5172.44 | O98: =SUM(F98,G98,H98,N98) -> 20241.86
A99: July 07 - July 13 2025 | C99: 21032.52 | E99: 21199.52 | F99: 15061.68 | G99: 0 | H99: 0 | I99: 6137.84 | J99: 6190.04 | K99: 251.59 | L99: 32.39 | M99: 0 | N99: =(J99-K99)+(L99-M99) -> 5970.84 | O99: =SUM(F99,G99,H99,N99) -> 21032.52
A100: July 14 - July 20 2025 | C100: 19977.28 | D100: 658 | E100: 20083.65 | F100: 14254.69 | G100: 0 | H100: 0 | I100: 5828.96 | J100: 5950.15 | K100: 227.56 | L100: 0 | M100: 0 | N100: =(J100-K100)+(L100-M100) -> 5722.59 | O100: =SUM(F100,G100,H100,N100) -> 19977.28
A101: July 21 - July 27 2025 | C101: 19420.83 | D101: 656 | E101: 19855.69 | F101: 13933.81 | G101: 0 | H101: 0 | I101: 5921.88 | J101: 5744.43 | K101: 270.6 | L101: 13.19 | M101: 0 | N101: =(J101-K101)+(L101-M101) -> 5487.02 | O101: =SUM(F101,G101,H101,N101) -> 19420.83
A102: July 28 - Aug 03 2025 | C102: 22466.31 | D102: 727 | E102: 22680.53 | F102: 16293.58 | G102: 0 | H102: 0 | I102: 6386.95 | J102: 6463.45 | K102: 290.72 | L102: 0 | M102: 0 | N102: =(J102-K102)+(L102-M102) -> 6172.73 | O102: =SUM(F102,G102,H102,N102) -> 22466.31
A103: Aug 04 - Aug 10 2025 | C103: 19727.34 | D103: 656 | E103: 20015.35 | F103: 14186.27 | G103: 0 | H103: 0 | I103: 5829.08 | J103: 5842.38 | K103: 301.31 | L103: 0 | M103: 0 | N103: =(J103-K103)+(L103-M103) -> 5541.07 | O103: =SUM(F103,G103,H103,N103) -> 19727.34
A104: Aug 11 - Aug 17 2025 | C104: 19328.44 | D104: 644 | E104: 19465.94 | F104: 14629.82 | G104: 26.4 | H104: 0 | I104: 4809.72 | J104: 4889.08 | K104: 216.86 | L104: 0 | M104: 0 | N104: =(J104-K104)+(L104-M104) -> 4672.22 | O104: =SUM(F104,G104,H104,N104) -> 19328.44
A105: Aug 18 - Aug 24 2025 | C105: 16117.06 | D105: 464 | E105: 14428.94 | F105: 10294.77 | G105: 49.2 | H105: 0 | I105: 4084.97 | J105: 5994.63 | K105: 286.9 | L105: 65.36 | M105: 0 | N105: =(J105-K105)+(L105-M105) -> 5773.09 | O105: =SUM(F105,G105,H105,N105) -> 16117.06
A106: Aug 25 - Aug 31 2025 | C106: 20858.45 | D106: 719 | E106: 21168.34 | F106: 14667.93 | G106: 112.8 | H106: 0 | I106: 6387.61 | J106: 6384.76 | K106: 307.04 | L106: 0 | M106: 0 | N106: =(J106-K106)+(L106-M106) -> 6077.72 | O106: =SUM(F106,G106,H106,N106) -> 20858.45
A107: Sep 01 - Sep 07 2025 | C107: 19794.6 | D107: 646 | E107: 20016.5 | F107: 13212.82 | G107: 139.2 | H107: 0 | I107: 6664.48 | J107: 6730.37 | K107: 334.57 | L107: 46.78 | M107: 0 | N107: =(J107-K107)+(L107-M107) -> 6442.58 | O107: =SUM(F107,G107,H107,N107) -> 19794.6
A108: Sep 08 - Sep 14 2025 | C108: 18399.97 | D108: 629 | E108: 18653.2 | F108: 12159.6 | G108: 68.4 | H108: 0 | I108: 6425.2 | J108: 6427.92 | K108: 298.82 | L108: 42.87 | M108: 0 | N108: =(J108-K108)+(L108-M108) -> 6171.97 | O108: =SUM(F108,G108,H108,N108) -> 18399.97
A109: Sep 15 - Sep 21 2025 | C109: 17783.03 | D109: 583 | E109: 17957.97 | F109: 12433.88 | G109: 147.22 | H109: 0 | I109: 5376.87 | J109: 5421.27 | K109: 219.34 | L109: 0 | M109: 0 | N109: =(J109-K109)+(L109-M109) -> 5201.93 | O109: =SUM(F109,G109,H109,N109) -> 17783.03
A110: Sep 22 - Sep 28 2025 | C110: 16305.69 | D110: 581 | E110: 16525.32 | F110: 11080.55 | G110: 283.21 | H110: 0 | I110: 5161.56 | J110: 5209.26 | K110: 267.33 | L110: 0 | M110: 0 | N110: =(J110-K110)+(L110-M110) -> 4941.93 | O110: =SUM(F110,G110,H110,N110) -> 16305.69
A111: Sep 29 - Oct 05 2025 | C111: 16431.85 | D111: 546 | E111: 16536.19 | F111: 12265.58 | G111: 187.19 | H111: 0 | I111: 4083.42 | J111: 4096.91 | K111: 117.83 | L111: 0 | M111: 0 | N111: =(J111-K111)+(L111-M111) -> 3979.08 | O111: =SUM(F111,G111,H111,N111) -> 16431.85
A112: Oct 6 - Oct 12 2025 | C112: 17769.13 | D112: 570 | E112: 17821.14 | F112: 13504.86 | G112: 254.57 | H112: 0 | I112: 4061.71 | J112: 4009.7 | K112: 0 | L112: 0 | M112: 0 | N112: =(J112-K112)+(L112-M112) -> 4009.7 | O112: =SUM(F112,G112,H112,N112) -> 17769.13
A113: Oct 13 - Oct 19 2025 | C113: 17376.31 | E113: 17252.3 | F113: 13234.44 | G113: 200.1 | H113: 0 | I113: 3817.76 | J113: 3941.77 | K113: 0 | L113: 0 | M113: 0 | N113: =(J113-K113)+(L113-M113) -> 3941.77 | O113: =SUM(F113,G113,H113,N113) -> 17376.31
A114: Oct 20 - Oct 26 2025 | C114: 18726.79 | D114: 575 | E114: 18506.6 | F114: 13467.13 | G114: 255.15 | H114: 0 | I114: 4784.32 | J114: 5004.51 | K114: 0 | L114: 0 | M114: 0 | N114: =(J114-K114)+(L114-M114) -> 5004.51 | O114: =SUM(F114,G114,H114,N114) -> 18726.79
A115: Oct 27 - Nov 02 2025 | C115: 17425.06 | D115: 535 | E115: 17425.06 | F115: 12637.58 | G115: 367.19 | H115: 0 | I115: 4420.29 | J115: 4420.29 | K115: 0 | L115: 0 | M115: 0 | N115: =(J115-K115)+(L115-M115) -> 4420.29 | O115: =SUM(F115,G115,H115,N115) -> 17425.06
A116: Nov 03 - Nov 09 2025 | C116: 16256.28 | D116: 539 | E116: 16264.56 | F116: 11402.71 | G116: 192.68 | H116: 0 | I116: 4669.17 | J116: 4660.89 | K116: 0 | L116: 0 | M116: 0 | N116: =(J116-K116)+(L116-M116) -> 4660.89 | O116: =SUM(F116,G116,H116,N116) -> 16256.28
A117: Nov 10 - Nov 16 2025 | C117: 17706.84 | D117: 566 | E117: 17748.23 | F117: 12929.35 | G117: 337.96 | H117: 0 | I117: 4480.92 | J117: 4402.36 | K117: 0 | L117: 37.17 | M117: 0 | N117: =(J117-K117)+(L117-M117) -> 4439.53 | O117: =SUM(F117,G117,H117,N117) -> 17706.84
A118: Nov 17 - Nov 23 2025 | C118: 18888.52 | D118: 589 | E118: 19214.09 | F118: 12834.55 | G118: 171.69 | H118: 0 | I118: 6207.85 | J118: 6249.24 | K118: 366.96 | L118: 0 | M118: 0 | N118: =(J118-K118)+(L118-M118) -> 5882.28 | O118: =SUM(F118,G118,H118,N118) -> 18888.52
A119: Nov 24 - Nov 30 2025 | C119: 18917.61 | D119: 584 | E119: 19246.06 | F119: 12768.97 | G119: 102.93 | H119: 0 | I119: 6374.16 | J119: 6429.86 | K119: 384.15 | L119: 0 | M119: 0 | N119: =(J119-K119)+(L119-M119) -> 6045.71 | O119: =SUM(F119,G119,H119,N119) -> 18917.61
A120: Dec 01 - Dec 07 2025 | C120: 19147.39 | D120: 617 | E120: 19778.6 | F120: 11560.99 | G120: 137.74 | H120: 0 | I120: 8079.87 | J120: 8124.05 | K120: 675.39 | L120: 0 | M120: 0 | N120: =(J120-K120)+(L120-M120) -> 7448.66 | O120: =SUM(F120,G120,H120,N120) -> 19147.39
A121: Dec 08 - Dec 14 2025 | C121: 18451.81 | D121: 598 | E121: 18690.72 | F121: 12819.93 | G121: 140.78 | H121: 0 | I121: 5730.01 | J121: 5842.18 | K121: 370.57 | L121: 19.49 | M121: 0 | N121: =(J121-K121)+(L121-M121) -> 5491.1 | O121: =SUM(F121,G121,H121,N121) -> 18451.81
A122: Dec 15 - Dec 21 2025 | C122: 20513.53 | D122: 641 | E122: 21375.78 | F122: 12928.07 | G122: 239.59 | H122: 0 | I122: 8208.12 | J122: 8254.59 | K122: 908.72 | L122: 0 | M122: 0 | N122: =(J122-K122)+(L122-M122) -> 7345.87 | O122: =SUM(F122,G122,H122,N122) -> 20513.53
A123: Dec 22 - Dec 28 2025 | C123: 25775.68 | D123: 737 | E123: 26184.32 | F123: 17344.72 | G123: 135.59 | H123: 0 | I123: 8704.01 | J123: 8807.21 | K123: 511.84 | L123: 0 | M123: 0 | N123: =(J123-K123)+(L123-M123) -> 8295.37 | O123: =SUM(F123,G123,H123,N123) -> 25775.68
A124: Dec 29 - Jan 04 2026 | C124: 25820.83 | D124: 780 | E124: 26413.46 | F124: 17208.56 | G124: 307.47 | H124: 0 | I124: 8897.43 | J124: 8973.85 | K124: 669.05 | L124: 0 | M124: 0 | N124: =(J124-K124)+(L124-M124) -> 8304.8 | O124: =SUM(F124,G124,H124,N124) -> 25820.83
...

Sheet Pizza K Eglinton
A1: Statement For Selected Period | C1: Total Revenue | G1: 2021 | I1: 2022 | K1: 2023
A6: July 3 2023 - Jul 9 2023
A7: July 10 2023 - Jul 16 2023
A8: July 17 2023 - Jul 23 2023
A9: July 24 2023 - Jul 30 2023
A10: July 31 2023 - Aug 6 2023
A11: Aug 7 2023 - Aug 13 2023
A12: Aug 14 2023 - Aug 20 2023
A13: Aug 21 2023 - Aug 27 2023
A14: August 28 2023 - September 3 2023 | G14: January | I14: January | K14: January
A15: September 4 2023 - September 10 2023 | C15: 35828.04 | G15: February | I15: February | K15: February
A16: September 11 2023 - September 17 2023 | C16: 32800.14 | G16: March | I16: March | K16: March
A17: September 18 2023 - September 24 2023 | C17: 32570.58 | G17: April | I17: April | K17: April
A18: September 25 2023 - October 1 2023 | C18: 31003.05 | G18: May | I18: May | K18: May
A19: October 2 2023 - October 8 2023 | C19: 33502.67 | G19: June | I19: June | K19: June
A20: October 9 2023 - October 15 2023 | C20: 33884.25 | G20: July | I20: July | K20: July
A21: October 16 2023 - October 22 2023 | C21: 32268.41 | G21: August | I21: August | K21: August
A22: October 23 2023 - October 29 2023 | C22: 30896.17 | G22: September | I22: September | K22: September
A23: October 30 2023 - November 5 2023 | C23: 32576.91 | G23: October | I23: October | K23: October
A24: November 6 2023 - November 12 2023 | C24: 33068.93 | G24: November | I24: November | K24: November
A25: November 13 2023 - November 19 2023 | C25: 31608.72 | G25: December | I25: December | K25: December
A26: November 20 2023 - November 26 2023 | C26: 33190.03
A27: November 27 2023 - December 03 2024 | C27: 28202.06
A28: December 04 2023 - December 10 2024 | C28: 27415.28
A29: December 11 2023 - December 17 2024 | C29: 27243.43
A30: December 18 2023 - December 24 2024 | C30: 32192.08
A31: December 25 2023 - December 31 2024 | C31: 49259.55
A32: Jan 1 - Jan 07 2024 | C32: 34128.44
A33: Jan 8 - Jan 14 2024 | C33: 24621.42
A34: Jan 15 - Jan 21 2024 | C34: 26885.29
A35: Jan 8 - Jan 14 2024 | C35: 24621.42
A36: Jan 15 - Jan 21 2024 | C36: 26885.29
A37: Jan 22 - Jan 28 2025 | C37: 26012.71
A38: Jan 29 - Feb 04 2026 | C38: 28448.32 | J38: Food ordering review
A39: Feb 05 - Feb 11 2026 | C39: 27376.4 | J39: scheduling
A40: Feb 12 - Feb 18 2024 | C40: 29073.36 | J40: store 1 hr both stores
A41: Feb 19 - Feb 25 2024 | C41: 30876.28
A42: Feb 26 - Mar 03, 2024 | C42: 26034.34
A43: Mar 04 - Mar 10, 2024 | C43: 28154.72
A44: Mar 11 - Mar 17, 2024 | C44: 22169.44
A45: Mar 18 - Mar 25, 2024 | C45: 24820.86
A46: Mar 25 - Mar 31, 2024 | C46: 32002.13
A47: Apr 1 - Apr 07 2024 | C47: 32249.46
A48: Apr 8 - Apr 14 2024 | C48: 45132.97
A49: Apr 15 - Apr 21 2024 | C49: 32389.88
A50: Apr 22 - Apr 28 2024 | C50: 34518.73
A51: Apr 29 - May 5 2024 | C51: 31821.27
A52: May 6 - May 12 2024 | C52: 32125.16
... A78: Nov 4 - Nov 10 2024 | C78: 27240.48
A79: Nov 11 - Nov 17 2024 | C79: =SUM(29641.7+983.71) -> 30625.41
A80: Nov 18 - Nov 24 2024 | C80: 28602.95
A81: Nov 25 - Dec 01 2024 | C81: 31488.13
A82: Dec 02 - Dec 08 2024 | C82: 24652.04
A83: Dec 09 - Dec 15 2024 | C83: 28003.83
A84: Dec 16 - Dec 22 2024 | C84: 30991.28
A85: Dec 23 - Dec 29 2024 | C85: 46216.71
A86: Dec 30 - Jan 05 2025 | C86: 46848.4
A87: Jan 06 - Jan 12 2025 | C87: 27109.43
A88: Jan 13 - Jan 19 2025 | C88: 27238.48
A89: Jan 20 - Jan 26 2025 | C89: 27692.41 | D89: Bill Count | E89: TB Total | F89: In Store | G89: Skip | H89: DD | I89: Uber TB | J89: Uber Website | K89: Marketing/Discount | L89: Uber (After Discount) | M89: Total Revenue
A90: Jan 27 - Feb 02 2025 | C90: 26853.6
A91: Feb 03 - Feb 09 2025 | C91: 25785.18
A92: Feb 10 - Feb 16 2025 | C92: 26342.05
A93: Feb 17 - Feb 23 2025 | C93: 29300.91
A94: Feb 24 - Mar 02 2025 | C94: 23753.32 | F94: 17339.25 | G94: 0 | H94: 499.96 | I94: 5720.58 | J94: 5914.11 | K94: 0 | L94: =(J94-K94) -> 5914.11 | M94: =SUM(F94,G94,H94,L94) -> 23753.32
A95: Mar 03 - Mar 09 2025 | C95: 26279.44 | F95: 19061.44 | G95: 898.78 | H95: 169.2 | I95: 6231.1 | J95: 6150.02 | K95: 0 | L95: =(J95-K95) -> 6150.02 | M95: =SUM(F95,G95,H95,L95) -> 26279.44
A96: Mar 10 - Mar 16 2025 | C96: 30584.32 | F96: 21596.66 | G96: 1187.71 | H96: 198.6 | I96: 7509.6 | J96: 7766.53 | K96: 165.18 | L96: =(J96-K96) -> 7601.35 | M96: =SUM(F96,G96,H96,L96) -> 30584.32
A97: Mar 17 - Mar 23 2025 | C97: 31363.26 | F97: 22681.9 | G97: 613.34 | H97: 299.19 | I97: 8067.91 | J97: 8146.03 | K97: 377.2 | L97: =(J97-K97) -> 7768.83 | M97: =SUM(F97,G97,H97,L97) -> 31363.26
A98: Mar 24 - Mar 30 2025 | C98: 38562.15 | F98: 26202.62 | G98: 850.61 | H98: 604.78 | I98: 10894.53 | J98: 10904.14 | K98: 0 | L98: =(J98-K98) -> 10904.14 | M98: =SUM(F98,G98,H98,L98) -> 38562.15
A99: Mar 31 - Apr 6 2025 | C99: 35042.73 | F99: 24641.64 | G99: 999.38 | H99: 205.2 | I99: 8983.4 | J99: 9196.51 | K99: 0 | L99: =(J99-K99) -> 9196.51 | M99: =SUM(F99,G99,H99,L99) -> 35042.73
A100: Apr 7 - Apr 13 2025 | C100: 33346.08 | F100: 25093.37 | G100: 527.6 | H100: 306.57 | I100: 7431.35 | J100: 7418.54 | K100: 0 | L100: =(J100-K100) -> 7418.54 | M100: =SUM(F100,G100,H100,L100) -> 33346.08
A101: Apr 14 - Apr 20 2025 | C101: 37670.5 | F101: 29230.44 | G101: 771.35 | H101: 597.72 | I101: 7120.34 | J101: 7070.99 | K101: 0 | L101: =(J101-K101) -> 7070.99 | M101: =SUM(F101,G101,H101,L101) -> 37670.5
A102: Apr 21 - Apr 27 2025 | C102: 32791.42 | F102: 24557.66 | G102: 762.23 | H102: 358.83 | I102: 7018.15 | J102: 7112.7 | K102: 0 | L102: =(J102-K102) -> 7112.7 | M102: =SUM(F102,G102,H102,L102) -> 32791.42
A103: Apr 28 - May 04 2025 | C103: 32100.69 | F103: 25692.62 | G103: 766.37 | H103: 371.6 | I103: 5347.99 | J103: 5270.1 | K103: 0 | L103: =(J103-K103) -> 5270.1 | M103: =SUM(F103,G103,H103,L103) -> 32100.69
A104: May 05 - May 11 2025 | C104: 35369.53 | E104: 35456.79 | F104: 27199.04 | G104: 936.81 | H104: 212.99 | I104: 7107.95 | J104: 7020.69 | K104: 0 | L104: =(J104-K104) -> 7020.69 | M104: =SUM(F104,G104,H104,L104) -> 35369.53
A105: May 12 - May 18 2025 | C105: 33440.47 | E105: 33561.9 | F105: 26057.63 | G105: 547.72 | H105: 446.95 | I105: 6509.6 | J105: 6388.17 | K105: 0 | L105: =(J105-K105) -> 6388.17 | M105: =SUM(F105,G105,H105,L105) -> 33440.47
A106: May 19 - May 25 2025 | C106: 34789.7 | E106: 34569.42 | F106: 27029.09 | G106: 827.39 | H106: 362.08 | I106: 6350.86 | J106: 6571.14 | K106: 0 | L106: =(J106-K106) -> 6571.14 | M106: =SUM(F106,G106,H106,L106) -> 34789.7
A107: May 26 - June 01 2025 | C107: 33662.75 | E107: 33583.35 | F107: 26050.21 | G107: 508.94 | H107: 158.38 | I107: 6865.82 | J107: 6945.22 | K107: 0 | L107: =(J107-K107) -> 6945.22 | M107: =SUM(F107,G107,H107,L107) -> 33662.75
A108: June 02 - June 08 2025 | C108: 38939.84 | E108: 39076.66 | F108: 30285.8 | G108: 584.15 | H108: 555.57 | I108: 7651.14 | J108: 7514.32 | K108: 0 | L108: =(J108-K108) -> 7514.32 | M108: =SUM(F108,G108,H108,L108) -> 38939.84
A109: June 09 - June 15 2025 | C109: 35437.2 | E109: 35369.66 | F109: 27482.76 | G109: 1139 | H109: 266.87 | I109: 6481.03 | J109: 6548.57 | K109: 0 | L109: =(J109-K109) -> 6548.57 | M109: =SUM(F109,G109,H109,L109) -> 35437.2
A110: June 16 - June 22 2025 | C110: 36428.95 | E110: 36493.44 | F110: 27702.72 | G110: 1131.29 | H110: 424.56 | I110: 7234.87 | J110: 7170.38 | K110: 0 | L110: =(J110-K110) -> 7170.38 | M110: =SUM(F110,G110,H110,L110) -> 36428.95
A111: June 23 - June 29 2025 | C111: 43356.27 | E111: 43298.28 | F111: 33615.84 | G111: 872.82 | H111: 587.17 | I111: 8222.45 | J111: 8299.06 | K111: 18.62 | L111: =(J111-K111) -> 8280.44 | M111: =SUM(F111,G111,H111,L111) -> 43356.27
A112: June 30 - July 06 2025 | C112: 43420.07 | E112: 43696.36 | F112: 35061.14 | G112: 599.72 | H112: 601.62 | I112: 7433.88 | J112: 7214.59 | K112: 57 | L112: =(J112-K112) -> 7157.59 | M112: =SUM(F112,G112,H112,L112) -> 43420.07
A113: July 07 - July 13 2025 | C113: 40279.54 | E113: 39228.65 | F113: 31189.46 | G113: 549.67 | H113: 705.86 | I113: 6783.66 | J113: 8071.73 | K113: 237.18 | L113: =(J113-K113) -> 7834.55 | M113: =SUM(F113,G113,H113,L113) -> 40279.54
A114: July 14 - July 20 2025 | C114: 38629.01 | D114: 1206 | E114: 38732.85 | F114: 30147.56 | G114: 602.82 | H114: 386.79 | I114: 7595.68 | J114: 7751.86 | K114: 260.02 | L114: =(J114-K114) -> 7491.84 | M114: =SUM(F114,G114,H114,L114) -> 38629.01
A115: July 21 - July 27 2025 | C115: 36415.5 | D115: 1207 | E115: 36867.49 | F115: 28377.6 | G115: 16 | H115: 544.08 | I115: 7929.81 | J115: 7852.22 | K115: 374.4 | L115: =(J115-K115) -> 7477.82 | M115: =SUM(F115,G115,H115,L115) -> 36415.5
A116: July 28 - Aug 03 2025 | C116: 39914.14 | D116: 1274 | E116: 40255.51 | F116: 32046.2 | G116: 0 | H116: 353.86 | I116: 7855.45 | J116: 7852.76 | K116: 338.68 | L116: =(J116-K116) -> 7514.08 | M116: =SUM(F116,G116,H116,L116) -> 39914.14
A117: Aug 04 - Aug 10 2025 | C117: 40064.95 | D117: 1275 | E117: 40155.96 | F117: 31825.22 | G117: 0 | H117: 350.98 | I117: 7979.76 | J117: 8235.93 | K117: 347.18 | L117: =(J117-K117) -> 7888.75 | M117: =SUM(F117,G117,H117,L117) -> 40064.95
A118: Aug 11 - Aug 17 2025 | C118: 38385.47 | D118: 1192 | E118: 38585.09 | F118: 30009.4 | G118: 287.41 | H118: 330.19 | I118: 7958.09 | J118: 8143.83 | K118: 385.36 | L118: =(J118-K118) -> 7758.47 | M118: =SUM(F118,G118,H118,L118) -> 38385.47
A119: Aug 18 - Aug 24 2025 | C119: 36744.56 | D119: 1199 | E119: 37014.63 | F119: 28232.31 | G119: 665.37 | H119: 537.49 | I119: 7579.46 | J119: 7594.75 | K119: 285.36 | L119: =(J119-K119) -> 7309.39 | M119: =SUM(F119,G119,H119,L119) -> 36744.56
A120: Aug 25 - Aug 31 2025 | C120: 39699.53 | D120: 1273 | E120: 40064.39 | F120: 31575.61 | G120: 718.43 | H120: 558.46 | I120: 7211.89 | J120: 7087.29 | K120: 240.26 | L120: =(J120-K120) -> 6847.03 | M120: =SUM(F120,G120,H120,L120) -> 39699.53
A121: Sep 01 - Sep 07 2025 | C121: 35562.03 | D121: 1156 | E121: 35816.39 | F121: 26737.67 | G121: 649.89 | H121: 338.8 | I121: 8090.03 | J121: 8183.94 | K121: 348.27 | L121: =(J121-K121) -> 7835.67 | M121: =SUM(F121,G121,H121,L121) -> 35562.03
A122: Sep 08 - Sep 14 2025 | C122: 27289.98 | D122: 914 | E122: 27543.12 | F122: 20393.43 | G122: 546.38 | H122: 76.4 | I122: 6526.91 | J122: 6564.14 | K122: 290.37 | L122: =(J122-K122) -> 6273.77 | M122: =SUM(F122,G122,H122,L122) -> 27289.98
A123: Sep 15 - Sep 21 2025 | C123: 30595.78 | D123: 960 | E123: 30728.46 | F123: 23127.68 | G123: 510.56 | H123: 477.48 | I123: 6612.74 | J123: 6753.33 | K123: 273.27 | L123: =(J123-K123) -> 6480.06 | M123: =SUM(F123,G123,H123,L123) -> 30595.78
A124: Sep 22 - Sep 28 2025 | C124: 30893.03 | D124: 1021 | E124: 31380.25 | F124: 23910.13 | G124: 481.8 | H124: 438.09 | I124: 6550.23 | J124: 6333.43 | K124: 270.42 | L124: =(J124-K124) -> 6063.01 | M124: =SUM(F124,G124,H124,L124) -> 30893.03
A125: Sep 29 - Oct 05 2025 | C125: 28750.13 | D125: 941 | E125: 28550.11 | F125: 21696.6 | G125: 426.9 | H125: 593.1 | I125: 5833.51 | J125: 6150.61 | K125: 117.08 | L125: =(J125-K125) -> 6033.53 | M125: =SUM(F125,G125,H125,L125) -> 28750.13
A126: Oct 6 - Oct 12 2025 | C126: 34108.24 | D126: 1096 | E126: 34253.01 | F126: 27003.35 | G126: 714.85 | H126: 592.86 | I126: 5941.95 | J126: 5797.18 | K126: 0 | L126: =(J126-K126) -> 5797.18 | M126: =SUM(F126,G126,H126,L126) -> 34108.24
A127: Oct 13 - Oct 19 2025 | C127: 35256.14 | E127: 35085.54 | F127: 26170.65 | G127: 665.77 | H127: 625.99 | I127: 7623.13 | J127: 7793.73 | K127: 0 | L127: =(J127-K127) -> 7793.73 | M127: =SUM(F127,G127,H127,L127) -> 35256.14
A128: Oct 20 - Oct 26 2025 | C128: 33913.24 | E128: 33616.29 | F128: 25602.63 | G128: 834.67 | H128: 337.75 | I128: 6841.24 | J128: 7138.19 | K128: 0 | L128: =(J128-K128) -> 7138.19 | M128: =SUM(F128,G128,H128,L128) -> 33913.24
A129: Oct 27 - Nov 02 2025 | C129: 33332.12 | D129: 979 | E129: 33277.95 | F129: 23552.91 | G129: 775.33 | H129: 557.08 | I129: 8392.63 | J129: 8446.8 | K129: 0 | L129: =(J129-K129) -> 8446.8 | M129: =SUM(F129,G129,H129,L129) -> 33332.12
...

Sheet Karachi Food Court
A1: Statement For Selected Period | C1: Total Revenue | H1: 2023
A2: August 28 2023 - September 3 2023 | H2: January
A3: September 4 2023 - September 10 2023 | H3: February
A4: September 11 2023 - September 17 2023 | C4: 19936.98 | H4: March
A5: September 18 2023 - September 24 2023 | C5: 26303.86 | H5: April
A6: September 25 2023 - October 1 2023 | C6: 26748.71 | H6: May
A7: October 2 2023 - October 8 2023 | C7: 27040.61 | H7: June
A8: October 9 2023 - October 15 2023 | C8: 23879.31 | H8: July
A9: October 16 2023 - October 22 2023 | C9: 22117.11 | H9: August
A10: October 23 2023 - October 29 2023 | C10: 23843.55 | H10: September
A11: October 30 2023 - November 5 2023 | C11: 21104.57 | H11: October
A12: November 6 2023 - November 12 2023 | C12: 24501.77 | H12: November
A13: November 13 2023 - November 19 2023 | C13: 24352.37 | H13: December
A14: November 20 2023 - November 26 2023 | C14: 26183.71
A15: November 27 2023 - December 03 2024 | C15: 22082.62
A16: December 04 2023 - December 10 2024 | C16: 25238.83
A17: December 11 2023 - December 17 2024 | C17: 20086.32
A18: December 18 2023 - December 24 2024 | C18: 23791.89
A19: December 25 2023 - December 31 2024 | C19: 44516.8
A20: Jan 1 - Jan 07 2024 | C20: 21563.55
A21: Jan 8 - Jan 14 2024 | C21: 17092.53
A22: Jan 15 - Jan 21 2024 | C22: 9587.8
A23: Jan 22 - Jan 28 2025 | C23: 20279.16
A24: Jan 29 - Feb 04 2026 | C24: 19566.21
A25: Feb 05 - Feb 11 2026 | C25: 19072.64
... A69: Dec 09 - Dec 15 2024 | C69: 37559.1
A70: Dec 16 - Dec 22 2024 | C70: 43475.56 | D70: Bill Count | E70: TB Total | F70: In Store | G70: Skip | H70: DD | I70: Uber TB | J70: FC Rev | K70: FC Marketing | L70: Chickentarian Rev | M70: Chickentarian Marketing | N70: Smash Rev | O70: Smash Marketing | P70: Uber (After Discount) | Q70: Total Revenue
A71: Dec 23 - Dec 29 2024 | C71: 89842.47 | F71: =C71-(I71+G71+H71) -> 85670.25 | G71: 174.68 | H71: 971.89 | I71: 3025.65
A72: Dec 30 - Jan 05 2025 | C72: 77438.75 | F72: =C72-(I72+G72+H72) -> 74012.65 | G72: 421.45 | H72: 171.72 | I72: 2832.93
A73: Jan 06 - Jan 12 2025 | C73: 39667.86
A74: Jan 13 - Jan 19 2025 | C74: 44859.21 | F74: 41435.41 | G74: 210.42 | H74: 346.95 | I74: 2866.43 | J74: 2750.28
A75: Jan 20 - Jan 26 2025 | C75: 44159.58 | F75: 41486.14 | G75: 380.65 | H75: 43.38 | I75: 2249.41
A76: Jan 27 - Feb 02 2025 | C76: 41432.64 | F76: 38186.99 | G76: 362.55 | H76: 433.19 | I76: 2449.91
A77: Feb 03 - Feb 09 2025 | C77: 42408.88 | F77: 39376.72 | G77: 240.13 | H77: 186.2 | I77: 2605.83
A78: Feb 10 - Feb 16 2025 | C78: 38328.99 | F78: 36670.19 | G78: 169.34 | H78: 37.47 | I78: 1451.99
A79: Feb 17 - Feb 23 2025 | C79: 55100.66 | F79: 51373.3 | G79: 344.81 | H79: 76.09 | I79: 3306.46
A80: Feb 24 - Mar 02 2025 | C80: 38257.93 | F80: 35952.52 | G80: 274.03 | H80: 23.38 | I80: 2008
A81: Mar 03 - Mar 09 2025 | C81: 43531.99 | F81: 39887.7 | G81: 219.35 | H81: 234.34 | I81: 3190.6
A82: Mar 10 - Mar 16 2025 | C82: 59192.5 | F82: 56306.62 | G82: 306.77 | H82: 110.65 | I82: 2509.93 | J82: 2617.51 | K82: 149.05 | P82: =(J82-K82) -> 2468.46 | Q82: =SUM(F82,G82,H82,P82) -> 59192.5
A83: Mar 17 - Mar 23 2025 | C83: 56656.53 | F83: 52209.01 | G83: 254.79 | H83: 80.97 | I83: 4481.31 | J83: 4427.92 | K83: 316.16 | P83: =(J83-K83) -> 4111.76 | Q83: =SUM(F83,G83,H83,P83) -> 56656.53
A84: Mar 24 - Mar 30 2025 | C84: 70466.62 | F84: 65804.91 | G84: 260.59 | H84: 116.93 | I84: 3929.61 | J84: 4284.19 | K84: 0 | P84: =(J84-K84) -> 4284.19 | Q84: =SUM(F84,G84,H84,P84) -> 70466.62
A85: Mar 31 - Apr 6 2025 | C85: 65442.42 | F85: 61646.29 | G85: 89.75 | H85: 283.22 | I85: 3465.36 | J85: 3423.16 | K85: 0 | P85: =(J85-K85) -> 3423.16 | Q85: =SUM(F85,G85,H85,P85) -> 65442.42
A86: Apr 7 - Apr 13 2025 | C86: 56383.64 | F86: 52694.01 | G86: 329.73 | H86: 251.06 | I86: 3494.58 | J86: 3380.84 | K86: 272 | P86: =(J86-K86) -> 3108.84 | Q86: =SUM(F86,G86,H86,P86) -> 56383.64
A87: Apr 14 - Apr 20 2025 | C87: 72066.4 | F87: 67953.78 | G87: 287.06 | H87: 521.5 | I87: 3469.83 | J87: 3484.22 | K87: 180.16 | P87: =(J87-K87) -> 3304.06 | Q87: =SUM(F87,G87,H87,P87) -> 72066.4
A88: Apr 21 - Apr 27 2025 | C88: 55031.27 | F88: 51573.96 | G88: 189.97 | H88: 277.59 | I88: 2967.88 | J88: 3105.9 | K88: 116.15 | P88: =(J88-K88) -> 2989.75 | Q88: =SUM(F88,G88,H88,P88) -> 55031.27
A89: Apr 28 - May 04 2025 | C89: 54863.13 | F89: 51416.75 | G89: 107.43 | H89: 341.33 | I89: 3043.92 | J89: 3050.42 | K89: 52.8 | P89: =(J89-K89) -> 2997.62 | Q89: =SUM(F89,G89,H89,P89) -> 54863.13
A90: May 05 - May 11 2025 | C90: 58615.74 | E90: 58655.27 | F90: 55827.69 | G90: 317.86 | H90: 130.13 | I90: 2379.59 | J90: 2340.06 | K90: 0 | P90: =(J90-K90) -> 2340.06 | Q90: =SUM(F90,G90,H90,P90) -> 58615.74
A91: May 12 - May 18 2025 | C91: 64103.37 | E91: 64319.69 | F91: 61079.04 | G91: 296.9 | H91: 15.7 | I91: 2928.05 | J91: 2711.73 | K91: 0 | P91: =(J91-K91) -> 2711.73 | Q91: =SUM(F91,G91,H91,P91) -> 64103.37
A92: May 19 - May 25 2025 | C92: 66835.93 | E92: 66620.85 | F92: 63351.22 | G92: 509.1 | H92: 149.31 | I92: 2611.22 | J92: 2826.3 | K92: 0 | P92: =(J92-K92) -> 2826.3 | Q92: =SUM(F92,G92,H92,P92) -> 66835.93
A93: May 26 - June 01 2025 | C93: 63466.7 | E93: 63478.08 | F93: 60452.9 | G93: 279.82 | H93: 252.03 | I93: 2493.33 | J93: 2465.75 | K93: 0 | L93: 16.2 | M93: 0 | N93: 0 | O93: 0 | P93: =(J93-K93)+(L93-M93) -> 2481.95 | Q93: =SUM(F93,G93,H93,P93) -> 63466.7
A94: June 02 - June 08 2025 | C94: 74504.6 | E94: 74512.66 | F94: 70969.24 | G94: 655.6 | H94: 0 | I94: 2887.82 | J94: 2829.42 | K94: 0 | L94: 50.34 | M94: 0 | N94: 0 | O94: 0 | P94: =(J94-K94)+(L94-M94) -> 2879.76 | Q94: =SUM(F94,G94,H94,P94) -> 74504.6
A95: June 09 - June 15 2025 | C95: 68465.64 | E95: 68484.61 | F95: 64870.47 | G95: 295.88 | H95: 0 | I95: 3318.26 | J95: 3299.29 | K95: 0 | L95: 0 | M95: 0 | N95: 0 | O95: 0 | P95: =(J95-K95)+(L95-M95) -> 3299.29 | Q95: =SUM(F95,G95,H95,P95) -> 68465.64
A96: June 16 - June 22 2025 | C96: 64651.96 | E96: 64628.14 | F96: 62071.43 | G96: 308.12 | H96: 0 | I96: 2248.59 | J96: 2256.82 | K96: 0 | L96: 0 | M96: 0 | N96: 15.59 | O96: 0 | P96: =(J96-K96)+(L96-M96)+(N96-O96) -> 2272.41 | Q96: =SUM(F96,G96,H96,P96) -> 64651.96
A97: June 23 - June 29 2025 | C97: 64214.65 | E97: 64145.69 | F97: 61398.03 | G97: 206.83 | H97: 0 | I97: 2540.83 | J97: 2544.13 | K97: 0 | L97: 65.66 | M97: 0 | N97: 0 | O97: 0 | P97: =(J97-K97)+(L97-M97)+(N97-O97) -> 2609.79 | Q97: =SUM(F97,G97,H97,P97) -> 64214.65
A98: June 30 - July 06 2025 | C98: 85251.13 | E98: 85140.47 | F98: 81944.22 | G98: 486.19 | H98: 33.58 | I98: 2676.48 | J98: 2787.14 | K98: 0 | L98: 0 | M98: 0 | N98: 0 | O98: 0 | P98: =(J98-K98)+(L98-M98)+(N98-O98) -> 2787.14 | Q98: =SUM(F98,G98,H98,P98) -> 85251.13
A99: July 07 - July 13 2025 | C99: 71226.33 | E99: 71205.29 | F99: 67920.92 | G99: 392.79 | H99: 187.36 | I99: 2704.22 | J99: 2725.26 | K99: 0 | L99: 0 | M99: 0 | N99: 0 | O99: 0 | P99: =(J99-K99)+(L99-M99)+(N99-O99) -> 2725.26 | Q99: =SUM(F99,G99,H99,P99) -> 71226.33
A100: July 14 - July 20 2025 | C100: 73279.98 | D100: 2035 | E100: 72922.74 | F100: 70067.34 | G100: 244.37 | H100: 171.17 | I100: 2439.86 | J100: 2797.1 | K100: 0 | L100: 0 | M100: 0 | N100: 0 | O100: 0 | P100: =(J100-K100)+(L100-M100)+(N100-O100) -> 2797.1 | Q100: =SUM(F100,G100,H100,P100) -> 73279.98
A101: July 21 - July 27 2025 | C101: 69592.61 | D101: 1955 | E101: 70061.5 | F101: 65896.94 | G101: 423.69 | H101: 224.76 | I101: 3516.11 | J101: 3031.33 | K101: 0 | L101: 15.89 | M101: 0 | N101: 0 | O101: 0 | P101: =(J101-K101)+(L101-M101)+(N101-O101) -> 3047.22 | Q101: =SUM(F101,G101,H101,P101) -> 69592.61
A102: July 28 - Aug 03 2025 | C102: 76659.06 | D102: 2014 | E102: 76082.34 | F102: 74236.59 | G102: 40.5 | H102: 181.83 | I102: 1623.42 | J102: 2200.14 | K102: 0 | L102: 0 | M102: 0 | N102: 0 | O102: 0 | P102: =(J102-K102)+(L102-M102)+(N102-O102) -> 2200.14 | Q102: =SUM(F102,G102,H102,P102) -> 76659.06
A103: Aug 04 - Aug 10 2025 | C103: 69552.59 | D103: 1979 | E103: 69742.44 | F103: 66070.17 | G103: 110.54 | H103: 192.77 | I103: 3368.96 | J103: 3179.11 | K103: 0 | L103: 0 | M103: 0 | N103: 0 | O103: 0 | P103: =(J103-K103)+(L103-M103)+(N103-O103) -> 3179.11 | Q103: =SUM(F103,G103,H103,P103) -> 69552.59
A104: Aug 11 - Aug 17 2025 | C104: 70303.49 | D104: 2181 | E104: 70565.18 | F104: 66906.03 | G104: 294.62 | H104: 363.03 | I104: 3001.5 | J104: 2739.81 | K104: 0 | L104: 0 | M104: 0 | N104: 0 | O104: 0 | P104: =(J104-K104)+(L104-M104)+(N104-O104) -> 2739.81 | Q104: =SUM(F104,G104,H104,P104) -> 70303.49
A105: Aug 18 - Aug 24 2025 | C105: 67644.62 | D105: 2225 | E105: 67396.76 | F105: 64676.56 | G105: 142.2 | H105: 215.16 | I105: 2362.84 | J105: 2593.35 | K105: 0 | L105: 0 | M105: 0 | N105: 22.78 | O105: 5.43 | P105: =(J105-K105)+(L105-M105)+(N105-O105) -> 2610.7 | Q105: =SUM(F105,G105,H105,P105) -> 67644.62
A106: Aug 25 - Aug 31 2025 | C106: 75626.59 | D106: 2024 | E106: 75977.24 | F106: 71910.28 | G106: 33.58 | H106: 343.55 | I106: 3689.83 | J106: 3304.7 | K106: 0 | L106: 34.48 | M106: 0 | N106: 0 | O106: 0 | P106: =(J106-K106)+(L106-M106)+(N106-O106) -> 3339.18 | Q106: =SUM(F106,G106,H106,P106) -> 75626.59
A107: Sep 01 - Sep 07 2025 | C107: 63118.01 | D107: 1809 | E107: 62792.45 | F107: 60151.61 | G107: 16.8 | H107: 161.69 | I107: 2462.35 | J107: 2727.4 | K107: 0 | L107: 35.08 | M107: 0 | N107: 43.17 | O107: 17.74 | P107: =(J107-K107)+(L107-M107)+(N107-O107) -> 2787.91 | Q107: =SUM(F107,G107,H107,P107) -> 63118.01
A108: Sep 08 - Sep 14 2025 | C108: 51481.48 | D108: 1521 | E108: 51120.24 | F108: 48208.76 | G108: 45.57 | H108: 266.63 | I108: 2599.28 | J108: 2883.52 | K108: 0 | L108: 0 | M108: 0 | N108: 123.8 | O108: 46.8 | P108: =(J108-K108)+(L108-M108)+(N108-O108) -> 2960.52 | Q108: =SUM(F108,G108,H108,P108) -> 51481.48
A109: Sep 15 - Sep 21 2025 | C109: 58889.9 | D109: 1712 | E109: 59019.05 | F109: 56012.74 | G109: 85.15 | H109: 390.12 | I109: 2531.04 | J109: 2348.13 | K109: 0 | L109: 0 | M109: 0 | N109: 88.74 | O109: 34.98 | P109: =(J109-K109)+(L109-M109)+(N109-O109) -> 2401.89 | Q109: =SUM(F109,G109,H109,P109) -> 58889.9
A110: Sep 22 - Sep 28 2025 | C110: 56173.31 | D110: 1639 | E110: 56118.34 | F110: 53314.93 | G110: 42.06 | H110: 421.98 | I110: 2339.37 | J110: 2329.57 | K110: 0 | L110: 0 | M110: 0 | N110: 81.54 | O110: 16.77 | P110: =(J110-K110)+(L110-M110)+(N110-O110) -> 2394.34 | Q110: =SUM(F110,G110,H110,P110) -> 56173.31
A111: Sep 29 - Oct 05 2025 | C111: 58371.86 | D111: 1688 | E111: 58305.05 | F111: 55248.7 | G111: 43.09 | H111: 347.69 | I111: 2665.57 | J111: 2716.8 | K111: 0 | L111: 15.58 | M111: 0 | N111: 0 | O111: 0 | P111: =(J111-K111)+(L111-M111)+(N111-O111) -> 2732.38 | Q111: =SUM(F111,G111,H111,P111) -> 58371.86
A112: Oct 6 - Oct 12 2025 | C112: 63649.29 | D112: 1787 | E112: 63735.45 | F112: 61307.37 | G112: 52.49 | H112: 271.09 | I112: 2104.5 | J112: 2018.34 | K112: 0 | L112: 0 | M112: 0 | N112: 0 | O112: 0 | P112: =(J112-K112)+(L112-M112)+(N112-O112) -> 2018.34 | Q112: =SUM(F112,G112,H112,P112) -> 63649.29
A113: Oct 13 - Oct 19 2025 | C113: 60398.42 | E113: 60191.27 | F113: 57178.93 | G113: 0 | H113: 432.17 | I113: 2580.17 | J113: 2787.32 | K113: 0 | L113: 0 | M113: 0 | N113: 0 | O113: 0 | P113: =(J113-K113)+(L113-M113)+(N113-O113) -> 2787.32 | Q113: =SUM(F113,G113,H113,P113) -> 60398.42
A114: Oct 20 - Oct 26 2025 | C114: 56964.52 | E114: 56942.15 | F114: 54420.33 | G114: 61.78 | H114: 299.88 | I114: 2160.16 | J114: 2166.34 | K114: 0 | L114: 16.19 | M114: 0 | N114: 0 | O114: 0 | P114: =(J114-K114)+(L114-M114)+(N114-O114) -> 2182.53 | Q114: =SUM(F114,G114,H114,P114) -> 56964.52
A115: Oct 27 - Nov 02 2025 | C115: 54356.75 | D115: 1637 | E115: 54239.89 | F115: 50919.68 | G115: 46.77 | H115: 283.04 | I115: 2990.4 | J115: 3083.28 | K115: 0 | L115: 0 | M115: 0 | N115: 23.98 | O115: 0 | P115: =(J115-K115)+(L115-M115)+(N115-O115) -> 3107.26 | Q115: =SUM(F115,G115,H115,P115) -> 54356.75
A116: Nov 03 - Nov 09 2025 | C116: 49653.3 | D116: 1,519 | E116: 49748.58 | F116: 46128.03 | G116: 102.36 | H116: 289.88 | I116: 3228.31 | J116: 3133.03 | K116: 0 | L116: 0 | M116: 0 | N116: 0 | O116: 0 | P116: =(J116-K116)+(L116-M116)+(N116-O116) -> 3133.03 | Q116: =SUM(F116,G116,H116,P116) -> 49653.3
A117: Nov 10 - Nov 16 2025 | C117: 50527.75 | D117: 1,488 | E117: 50407.18 | F117: 47850.75 | G117: 25.18 | H117: 188.22 | I117: 2343.03 | J117: 2357.33 | K117: 0 | L117: 87.07 | M117: 0 | N117: 19.2 | O117: 0 | P117: =(J117-K117)+(L117-M117)+(N117-O117) -> 2463.6 | Q117: =SUM(F117,G117,H117,P117) -> 50527.75
A118: Nov 17 - Nov 23 2025 | C118: 47385.9 | D118: 1,448 | E118: 46870.52 | F118: 44573.78 | G118: 64.16 | H118: 87.67 | I118: 2144.91 | J118: 2634.51 | K118: 0 | L118: 25.78 | M118: 0 | N118: 0 | O118: 0 | P118: =(J118-K118)+(L118-M118)+(N118-O118) -> 2660.29 | Q118: =SUM(F118,G118,H118,P118) -> 47385.9
A119: Nov 24 - Nov 30 2025 | C119: 48813.65 | D119: 1407 | E119: 49452.29 | F119: 45726.39 | G119: 32.38 | H119: 46.17 | I119: 3647.35 | J119: 2957.33 | K119: 0 | L119: 24.99 | M119: 0 | N119: 26.39 | O119: 0 | P119: =(J119-K119)+(L119-M119)+(N119-O119) -> 3008.71 | Q119: =SUM(F119,G119,H119,P119) -> 48813.65
A120: Dec 01 - Dec 07 2025 | C120: 42687.83 | D120: 1281 | E120: 42457.23 | F120: 38758.09 | G120: 0 | H120: 144.72 | I120: 3554.42 | J120: 3737.35 | K120: 0 | L120: 47.67 | M120: 0 | N120: 0 | O120: 0 | P120: =(J120-K120)+(L120-M120)+(N120-O120) -> 3785.02 | Q120: =SUM(F120,G120,H120,P120) -> 42687.83
A121: Dec 08 - Dec 14 2025 | C121: 37865.16 | D121: 1,138 | E121: 37599.25 | F121: 34426.32 | G121: 16.79 | H121: 163.09 | I121: 2993.05 | J121: 3180.41 | K121: 0 | L121: 67.16 | M121: 0 | N121: 11.39 | O121: 0 | P121: =(J121-K121)+(L121-M121)+(N121-O121) -> 3258.96 | Q121: =SUM(F121,G121,H121,P121) -> 37865.16
A122: Dec 15 - Dec 21 2025 | C122: 47376.36 | D122: 1,603 | E122: 47606.93 | F122: 43702.94 | G122: 125.92 | H122: 64.35 | I122: 3713.72 | J122: 3409.1 | K122: 0 | L122: 32.68 | M122: 0 | N122: 41.37 | O122: 0 | P122: =(J122-K122)+(L122-M122)+(N122-O122) -> 3483.15 | Q122: =SUM(F122,G122,H122,P122) -> 47376.36
A123: Dec 22 - Dec 28 2025 | C123: 66636.7 | D123: 1806 | E123: 66529.91 | F123: 62433.53 | G123: 35.39 | H123: 383.46 | I123: 3677.53 | J123: 3702.67 | K123: 0 | L123: 81.65 | M123: 0 | N123: 0 | O123: 0 | P123: =(J123-K123)+(L123-M123)+(N123-O123) -> 3784.32 | Q123: =SUM(F123,G123,H123,P123) -> 66636.7
A124: Dec 29 - Jan 04 2026 | C124: 75840.28 | D124: 2,080 | E124: 75867.23 | F124: 72085.37 | G124: 137.95 | H124: 0 | I124: 3643.91 | J124: 3528.71 | K124: 0 | L124: 90.05 | M124: 20.98 | N124: 19.18 | O124: 0 | P124: =(J124-K124)+(L124-M124)+(N124-O124) -> 3616.96 | Q124: =SUM(F124,G124,H124,P124) -> 75840.28
A125: Jan 05 - Jan 11 2026 | C125: 42077.29 | D125: 1,228 | E125: 41725.22 | F125: 39246.19 | G125: 93.46 | H125: 58.44 | I125: 2327.13 | J125: 2608.43 | K125: 0 | L125: 70.77 | M125: 0 | N125: 0 | O125: 0 | P125: =(J125-K125)+(L125-M125)+(N125-O125) -> 2679.2 | Q125: =SUM(F125,G125,H125,P125) -> 42077.29
A126: Jan 12 - Jan 18 2026 | C126: 42198.97 | D126: 1,494 | E126: 42393.06 | F126: 38683.62 | G126: 100.2 | H126: 53 | I126: 3556.24 | J126: 3362.15 | K126: 0 | L126: 0 | M126: 0 | N126: 0 | O126: 0 | P126: =(J126-K126)+(L126-M126)+(N126-O126) -> 3362.15 | Q126: =SUM(F126,G126,H126,P126) -> 42198.97
A127: Jan 19 - Jan 25 2026 | C127: 31282.94 | D127: 943 | E127: 31294.9 | F127: 28030.97 | G127: 97.24 | H127: 117.8 | I127: 3048.89 | J127: 3191.35 | K127: 166.71 | L127: 12.29 | M127: 0 | N127: 0 | O127: 0 | P127: =(J127-K127)+(L127-M127)+(N127-O127) -> 3036.93 | Q127: =SUM(F127,G127,H127,P127) -> 31282.94
A128: Jan 26 - Feb 01 2026 | C128: 45129.9 | D128: 1,362 | E128: 45575.27 | F128: 40263.6 | G128: 385.4 | H128: 73.18 | I128: 4853.09 | J128: 4847.02 | K128: 439.3 | L128: 0 | M128: 0 | N128: 0 | O128: 0 | P128: =(J128-K128)+(L128-M128)+(N128-O128) -> 4407.72 | Q128: =SUM(F128,G128,H128,P128) -> 45129.9
A129: Feb 02 - Feb 08 2026 | C129: 40752.28 | D129: 1,269 | E129: 40826.02 | F129: 36789.72 | G129: 154.55 | H129: 206.1 | I129: 3675.65 | J129: 3585.12 | K129: 0 | L129: 16.79 | M129: 0 | N129: 0 | O129: 0 | P129: =(J129-K129)+(L129-M129)+(N129-O129) -> 3601.91 | Q129: =SUM(F129,G129,H129,P129) -> 40752.28
A130: Feb 09 - Feb 15 2026 | C130: 55904.41 | D130: 1,646 | E130: 55395.55 | F130: 51724.97 | G130: 135.53 | H130: 153.17 | I130: 3381.88 | J130: 3819.17 | K130: 0 | L130: 49.77 | M130: 0 | N130: 35.58 | O130: 13.78 | P130: =(J130-K130)+(L130-M130)+(N130-O130) -> 3890.74 | Q130: =SUM(F130,G130,H130,P130) -> 55904.41
A131: Feb 16 - Feb 22 2026 | C131: 46088.54 | D131: 1,402 | E131: 46369.31 | F131: 42333.83 | G131: 110.51 | H131: 771.72 | I131: 3153.25 | J131: 2812.5 | K131: 0 | L131: 41.78 | M131: 0 | N131: 31.98 | O131: 13.78 | P131: =(J131-K131)+(L131-M131)+(N131-O131) -> 2872.48 | Q131: =SUM(F131,G131,H131,P131) -> 46088.54
A132: Feb 23 - Mar 1 2026 | C132: 40600.81 | D132: 1,303 | E132: 40559.22 | F132: 36265.92 | G132: 201.29 | H132: 846.64 | I132: 3245.37 | J132: 3222.18 | K132: 0 | L132: 24.99 | M132: 0 | N132: 67.96 | O132: 28.17 | P132: =(J132-K132)+(L132-M132)+(N132-O132) -> 3286.96 | Q132: =SUM(F132,G132,H132,P132) -> 40600.81
A133: Mar 02 - Mar 08 2026 | C133: 47921.57 | D133: 1,572 | E133: 47892.34 | F133: 44305.3 | G133: 109.52 | H133: 443.09 | I133: 3034.43 | J133: 3000.87 | K133: 0 | L133: 0 | M133: 0 | N133: 107.94 | O133: 45.15 | P133: =(J133-K133)+(L133-M133)+(N133-O133) -> 3063.66 | Q133: =SUM(F133,G133,H133,P133) -> 47921.57
A134: Mar 09 - Mar 15 2026 | C134: 52613.88 | D134: 1,577 | E134: 52248.71 | F134: 48605.05 | G134: 95.26 | H134: 764.8 | I134: 2783.6 | J134: 3056.29 | K134: 0 | L134: 18.89 | M134: 0 | N134: 119.54 | O134: 45.95 | P134: =(J134-K134)+(L134-M134)+(N134-O134) -> 3148.77 | Q134: =SUM(F134,G134,H134,P134) -> 52613.88
A135: Mar 16 - Mar 22 2026 | C135: 88000.02 | D135: 2,170 | E135: 86996.77 | F135: 82950.35 | G135: 62.5 | H135: 177.98 | I135: 3805.94 | J135: 4760.79 | K135: 0 | L135: 0 | M135: 0 | N135: 80.76 | O135: 32.36 | P135: =(J135-K135)+(L135-M135)+(N135-O135) -> 4809.19 | Q135: =SUM(F135,G135,H135,P135) -> 88000.02
... A138: Apr 06 - Apr 12 | C138: 56910.23 | D138: 1,724 | E138: 57120.37 | F138: 53661.92 | G138: 190.83 | H138: 159.8 | I138: 3107.82 | J138: 2865.11 | K138: 0 | L138: 0 | M138: 0 | N138: 48.75 | O138: 16.18 | P138: =(J138-K138)+(L138-M138)+(N138-O138) -> 2897.68 | Q138: =SUM(F138,G138,H138,P138) -> 56910.23
A139: Apr 13 - Apr 19 | C139: 58051.89 | D139: 1,854 | E139: 58012.78 | F139: 54171.54 | G139: 26.38 | H139: 238.43 | I139: 3576.43 | J139: $3,491.18 | K139: 0 | L139: 13.19 | M139: 0 | N139: $172.69 | O139: $61.52 | P139: =(J139-K139)+(L139-M139)+(N139-O139) -> 3615.54 | Q139: =SUM(F139,G139,H139,P139) -> 58051.89
A140: Apr 20 - Apr 26 | C140: 56750.23 | D140: 1,690 | E140: 56679.69 | F140: 53681.34 | G140: 119.93 | H140: 325.46 | I140: 2552.96 | J140: 2574.13 | K140: 0 | L140: 0 | M140: 0 | N140: 80.74 | O140: 31.37 | P140: =(J140-K140)+(L140-M140)+(N140-O140) -> 2623.5 | Q140: =SUM(F140,G140,H140,P140) -> 56750.23
A141: Apr 27 - May 03 | C141: 57253.16 | D141: 1,703 | E141: 56994.48 | F141: 54225.09 | G141: 81.54 | H141: 39.92 | I141: 2647.93 | J141: $2,786.66 | K141: 0 | L141: 24.99 | M141: 0 | N141: $140.30 | O141: $45.34 | P141: =(J141-K141)+(L141-M141)+(N141-O141) -> 2906.61 | Q141: =SUM(F141,G141,H141,P141) -> 57253.16
A142: May 4 - May 10 | C142: 60756.22 | D142: 1700 | E142: 60358.29 | F142: 56042.58 | G142: 86.13 | H142: 131.93 | I142: 4097.65 | J142: 4419.32 | K142: 0 | L142: 76.26 | M142: 0 | N142: 0 | O142: 0 | P142: =(J142-K142)+(L142-M142)+(N142-O142) -> 4495.58 | Q142: =SUM(F142,G142,H142,P142) -> 60756.22
A143: May 11 - May 17 | C143: 54781.81 | D143: 1679 | E143: 54962.39 | F143: 51430.74 | G143: 52.16 | H143: 110.92 | I143: 3368.57 | J143: 3187.99 | K143: 0 | L143: 0 | M143: 0 | N143: 0 | O143: 0 | P143: =(J143-K143)+(L143-M143)+(N143-O143) -> 3187.99 | Q143: =SUM(F143,G143,H143,P143) -> 54781.81
A144: May 18 - May 24 | C144: 63431.41 | D144: 1796 | E144: 63689.3 | F144: 59630.24 | G144: 66.86 | H144: 156.09 | I144: 3836.11 | J144: 3562.33 | K144: 0 | L144: 15.89 | M144: 0 | N144: 0 | O144: 0 | P144: =(J144-K144)+(L144-M144)+(N144-O144) -> 3578.22 | Q144: =SUM(F144,G144,H144,P144) -> 63431.41
A145: May 25 - May 31 | C145: 74821.97 | D145: 1857 | E145: 74782.62 | F145: 69197.6 | G145: 112.28 | H145: 907.77 | I145: 4564.97 | J145: 4550.95 | K145: 0 | L145: 36.77 | M145: 10.98 | N145: 27.58 | O145: 0 | P145: =(J145-K145)+(L145-M145)+(N145-O145) -> 4604.32 | Q145: =SUM(F145,G145,H145,P145) -> 74821.97
...

Sheet Markham
A1: Markham
A2: Statement For Selected Period | B2: Total Revenue (Net Sales) | C2: Royalties (6%) | D2: Marketing (2%)
A3: December 18 2023 - December 24 2024 | B3: 4640.56 | C3: =B3*0.06 -> 278.4336 | D3: =B3*0.02 -> 92.8112
A4: December 25 2023 - December 31 2024 | B4: 12060.9 | C4: =B4*0.06 -> 723.654 | D4: =B4*0.02 -> 241.218
A5: Jan 1 - Jan 07 2024 | B5: 11251.81 | C5: =B5*0.06 -> 675.1086 | D5: =B5*0.02 -> 225.0362
A6: Jan 8 - Jan 14 2024 | B6: 8547.71 | C6: =B6*0.06 -> 512.8626 | D6: =B6*0.02 -> 170.9542
A7: Jan 15 - Jan 21 2024 | B7: 10272.1 | C7: =B7*0.06 -> 616.326 | D7: =B7*0.02 -> 205.442
A8: Jan 22 - Jan 28 2024 | B8: 11991.64 | C8: =B8*0.06 -> 719.4984 | D8: =B8*0.02 -> 239.8328
A9: Jan 29 - Feb 04 2024 | B9: 10169.08 | C9: =B9*0.06 -> 610.1448 | D9: =B9*0.02 -> 203.3816
A10: Feb 05 - Feb 11 2024 | B10: 10185.83 | C10: =B10*0.06 -> 611.1498 | D10: =B10*0.02 -> 203.7166
A11: Feb 12 - Feb 18 2024 | B11: 9415.22 | C11: =B11*0.06 -> 564.9132 | D11: =B11*0.02 -> 188.3044
A12: Feb 19 - Feb 25 2024 | B12: 10664.05 | C12: =B12*0.06 -> 639.843 | D12: =B12*0.02 -> 213.281
A13: Feb 26 - Mar 03, 2024 | B13: 10643.55 | C13: =B13*0.06 -> 638.613 | D13: =B13*0.02 -> 212.871
A14: Mar 04 - Mar 10, 2024 | B14: 8627.64 | C14: =B14*0.06 -> 517.6584 | D14: =B14*0.02 -> 172.5528
... A20: Apr 15 - Apr 21 2024 | B20: 9134.63 | C20: =B20*0.06 -> 548.0778 | D20: =B20*0.02 -> 182.6926
A21: Apr 22 - Apr 28 2024 | B21: 9378.85 | C21: =(B21*0.06)*1.13 -> 635.88603 | D21: =(B21*0.02)*1.13 -> 211.96201
A22: Apr 29 - May 5 2024 | B22: 8840.32 | C22: =(B22*0.06)*1.13 -> 599.3737 | D22: =(B22*0.02)*1.13 -> 199.79123
A23: May 6 - May 12 2024 | B23: 9831.2 | C23: =(B23*0.06)*1.13 -> 666.55536 | D23: =(B23*0.02)*1.13 -> 222.18512
A24: May 13 - May 19 2024 | B24: 10206.77 | C24: =(B24*0.06)*1.13 -> 692.01901 | D24: =(B24*0.02)*1.13 -> 230.673
A25: May 20 - May 26 2024 | B25: 12184.27 | C25: =(B25*0.06)*1.13 -> 826.09351 | D25: =(B25*0.02)*1.13 -> 275.3645
A26: May 27 - Jun 02 2024 | B26: 11920.02 | C26: =(B26*0.06)*1.13 -> 808.17736 | D26: =(B26*0.02)*1.13 -> 269.39245
A27: Jun 03 - Jun 09 2024 | B27: 13116.63 | C27: =(B27*0.06)*1.13 -> 889.30751 | D27: =(B27*0.02)*1.13 -> 296.43584
A28: Jun 10 - Jun 16 2024 | B28: 12257.18 | C28: =(B28*0.06)*1.13 -> 831.0368 | D28: =(B28*0.02)*1.13 -> 277.01227
A29: Jun 17 - Jun 23 2024 | B29: 13754.28 | C29: =(B29*0.06)*1.13 -> 932.54018 | D29: =(B29*0.02)*1.13 -> 310.84673
A30: Jun 24 - Jun 30 2024 | B30: 12247.99 | C30: =(B30*0.06)*1.13 -> 830.41372 | D30: =(B30*0.02)*1.13 -> 276.80457
A31: Jul 1 - Jul 7 2024 | B31: =13152.46-1164.26 -> 11988.2 | C31: =(B31*0.06)*1.13 -> 812.79996 | D31: =(B31*0.02)*1.13 -> 270.93332
A32: Jul 8 - Jul 14 2024 | B32: 11665.99 | C32: =(B32*0.06)*1.13 -> 790.95412 | D32: =(B32*0.02)*1.13 -> 263.65137
A33: Jul 15 - Jul 21 2024 | B33: 11814.15 | C33: =(B33*0.06)*1.13 -> 800.99937 | D33: =(B33*0.02)*1.13 -> 266.99979
A34: Jul 22 - Jul 28 2024 | B34: 11963.75 | C34: =(B34*0.06)*1.13 -> 811.14225 | D34: =(B34*0.02)*1.13 -> 270.38075
A35: Jul 29 - Aug 04 2024 | B35: 12977.57 | C35: =(B35*0.06)*1.13 -> 879.87925 | D35: =(B35*0.02)*1.13 -> 293.29308
A36: Aug 05 - Aug 11 2024 | B36: 13094.69 | C36: =(B36*0.06)*1.13 -> 887.81998 | D36: =(B36*0.02)*1.13 -> 295.93999
A37: Aug 12 - Aug 18 2024 | B37: 13216.82 | C37: =(B37*0.06)*1.13 -> 896.1004 | D37: =(B37*0.02)*1.13 -> 298.70013
A38: Aug 19 - Aug 25 2024 | B38: 12088.66 | C38: =(B38*0.06)*1.13 -> 819.61115 | D38: =(B38*0.02)*1.13 -> 273.20372
A39: Aug 26 - Sep 01 2024 | B39: 13164.76 | C39: =(B39*0.06)*1.13 -> 892.57073 | D39: =(B39*0.02)*1.13 -> 297.52358
A40: Sep 02 - Sep 08 2024 | B40: 13465.82 | C40: =(B40*0.06)*1.13 -> 912.9826 | D40: =(B40*0.02)*1.13 -> 304.32753
A41: Sep 09 - Sep 15 2024 | B41: 12064.43 | C41: =(B41*0.06)*1.13 -> 817.96835 | D41: =(B41*0.02)*1.13 -> 272.65612
A42: Sep 16 - Sep 22 2024 | B42: 13132.43 | C42: =(B42*0.06)*1.13 -> 890.37875 | D42: =(B42*0.02)*1.13 -> 296.79292
A43: Sep 23 - Sep 29 2024 | B43: 12136.79 | C43: =(B43*0.06)*1.13 -> 822.87436 | D43: =(B43*0.02)*1.13 -> 274.29145
... A53: Dec 02 - Dec 08 2024 | B53: 10374.78 | C53: =(B53*0.06)*1.13 -> 703.41008 | D53: =(B53*0.02)*1.13 -> 234.47003
A54: Dec 09 - Dec 15 2024 | B54: 10277.44 | C54: =(B54*0.06)*1.13 -> 696.81043 | D54: =(B54*0.02)*1.13 -> 232.27014 | E54: Bill Count | F54: TB Total | G54: In Store | H54: Skip | I54: DD | J54: Uber TB | K54: Uber Website | L54: Marketing | M54: Uber Total | N54: Total
A55: Dec 16 - Dec 22 2024 | B55: 12541.61 | C55: =(B55*0.06)*1.13 -> 850.32116 | D55: =(B55*0.02)*1.13 -> 283.44039 | G55: 7702.17 | H55: 229.04 | I55: 38.14 | J55: 6571.23 | K55: 7237 | L55: =SUM(2566.94,97.8) -> 2664.74 | M55: =K55-L55 -> 4572.26 | N55: =SUM(G55,H55,I55,M55) -> 12541.61
J56: 155 | K56: 172
A57: Dec 23 - Dec 29 2024 | B57: 13228.19 | C57: =(B57*0.06)*1.13 -> 896.87128 | D57: =(B57*0.02)*1.13 -> 298.95709 | G57: 8691.45 | H57: 32.39 | I57: 29.1 | J57: 7099.41 | K57: 7358 | L57: =SUM(2803.87,78.88) -> 2882.75 | M57: =K57-L57 -> 4475.25 | N57: =SUM(G57,H57,I57,M57) -> 13228.19
J58: 165 | K58: 172
A59: Dec 30 - Jan 05 2025 | B59: 13802.12 | C59: =(B59*0.06)*1.13 -> 935.78374 | D59: =(B59*0.02)*1.13 -> 311.92791 | G59: 9725.69 | H59: 151.96 | I59: 18 | J59: 6053.43 | K59: 6230 | L59: =SUM(2272.53,51) -> 2323.53 | M59: =K59-L59 -> 3906.47 | N59: =SUM(G59,H59,I59,M59) -> 13802.12
J60: 135 | K60: 139
A61: Jan 06 - Jan 12 2025 | B61: 10844.2 | C61: =(B61*0.06)*1.13 -> 735.23676 | D61: =(B61*0.02)*1.13 -> 245.07892 | G61: 6303.1 | H61: 98.09 | I61: 54 | J61: 6494.2 | K61: 6548 | L61: =(2145.19+13.8) -> 2158.99 | M61: =K61-L61 -> 4389.01 | N61: =SUM(G61,H61,I61,M61) -> 10844.2
J62: 148 | K62: 149
A63: Jan 13 - Jan 19 2025 | B63: 9015.41 | C63: =(B63*0.06)*1.13 -> 611.2448 | D63: =(B63*0.02)*1.13 -> 203.74827 | G63: 5532.54 | H63: 94.8 | I63: 121.37 | J63: 5019.12 | K63: 5091 | L63: 1824.3 | M63: =K63-L63 -> 3266.7 | N63: =SUM(G63,H63,I63,M63) -> 9015.41
J64: 113
A65: Jan 20 - Jan 26 2025 | B65: 12517.81 | C65: =(B65*0.06)*1.13 -> 848.70752 | D65: =(B65*0.02)*1.13 -> 282.90251 | G65: 7684.17 | H65: 104.8 | J65: 6709.14 | K65: 6803.34 | L65: 2074.5 | M65: =K65-L65 -> 4728.84 | N65: =SUM(G65,H65,I65,M65) -> 12517.81
A67: Jan 27 - Feb 02 2025 | B67: 10197.33 | C67: =(B67*0.06)*1.13 -> 691.37897 | D67: =(B67*0.02)*1.13 -> 230.45966 | G67: 7203.42 | H67: 310.57 | I67: 100.67 | J67: 2312.3 | K67: 2621.37 | L67: 38.7 | M67: =K67-L67 -> 2582.67 | N67: =SUM(G67,H67,I67,M67) -> 10197.33
A69: Feb 03 - Feb 09 2025 | B69: 10844.59 | C69: =(B69*0.06)*1.13 -> 735.2632 | D69: =(B69*0.02)*1.13 -> 245.08773 | G69: 7217.26 | H69: 33.6 | I69: 135.6 | J69: 3083.24 | K69: 3458.13 | L69: 0 | M69: =K69-L69 -> 3458.13 | N69: =SUM(G69,H69,I69,M69) -> 10844.59
A71: Feb 10 - Feb 16 2025 | B71: 10302.97 | C71: =(B71*0.06)*1.13 -> 698.54137 | D71: =(B71*0.02)*1.13 -> 232.84712 | G71: 7636.66 | H71: 78.8 | I71: 189.63 | J71: 2166.71 | K71: 2397.88 | L71: 0 | M71: =K71-L71 -> 2397.88 | N71: =SUM(G71,H71,I71,M71) -> 10302.97
A73: Feb 17 - Feb 23 2025 | B73: 9839.6 | C73: =(B73*0.06)*1.13 -> 667.12488 | D73: =(B73*0.02)*1.13 -> 222.37496 | G73: 7549.74 | H73: 207.31 | I73: 76.8 | J73: 2365.55 | K73: 2484.95 | L73: 479.2 | M73: =K73-L73 -> 2005.75 | N73: =SUM(G73,H73,I73,M73) -> 9839.6
A75: Feb 24 - Mar 02 2025 | B75: 8737.69 | C75: =(B75*0.06)*1.13 -> 592.41538 | D75: =(B75*0.02)*1.13 -> 197.47179 | G75: 6043.18 | H75: 244.19 | I75: 26.39 | J75: 2282.52 | K75: 2423.93 | L75: 0 | M75: =K75-L75 -> 2423.93 | N75: =SUM(G75,H75,I75,M75) -> 8737.69
C76: =(B76*0.06)*1.13 -> 0 | D76: =(B76*0.02)*1.13 -> 0
A77: Mar 03 - Mar 09 2025 | B77: 7902.35 | C77: =(B77*0.06)*1.13 -> 535.77933 | D77: =(B77*0.02)*1.13 -> 178.59311 | G77: 5145.19 | H77: 235.99 | I77: 0 | J77: 2409.61 | K77: 2521.17 | L77: 0 | M77: =K77-L77 -> 2521.17 | N77: =SUM(G77,H77,I77,M77) -> 7902.35
A79: Mar 10 - Mar 16 2025 | B79: 7985.93 | C79: =(B79*0.06)*1.13 -> 541.44605 | D79: =(B79*0.02)*1.13 -> 180.48202 | G79: 5239.66 | H79: 110.87 | I79: 46.58 | J79: 2542.02 | K79: 2588.82 | L79: 0 | M79: =K79-L79 -> 2588.82 | N79: =SUM(G79,H79,I79,M79) -> 7985.93
A81: Mar 17 - Mar 23 2025 | B81: 10543.86 | C81: =(B81*0.06)*1.13 -> 714.87371 | D81: =(B81*0.02)*1.13 -> 238.29124 | G81: 7606.4 | H81: 259.41 | I81: 128.17 | J81: 2491.39 | K81: 2549.88 | L81: 0 | M81: =K81-L81 -> 2549.88 | N81: =SUM(G81,H81,I81,M81) -> 10543.86
A83: Mar 24 - Mar 30 2025 | B83: 12962.6 | C83: =(B83*0.06)*1.13 -> 878.86428 | D83: =(B83*0.02)*1.13 -> 292.95476 | G83: 9038.83 | H83: 286.27 | I83: 68.4 | J83: 3590.88 | K83: 3569.1 | L83: 0 | M83: =K83-L83 -> 3569.1 | N83: =SUM(G83,H83,I83,M83) -> 12962.6
A85: Mar 31 - Apr 6 2025 | B85: 10719.71 | C85: =(B85*0.06)*1.13 -> 726.79634 | D85: =(B85*0.02)*1.13 -> 242.26545 | G85: 7764.31 | H85: 78.3 | I85: 103.66 | J85: 2623.92 | K85: 2773.44 | L85: 0 | M85: =K85-L85 -> 2773.44 | N85: =SUM(G85,H85,I85,M85) -> 10719.71
A87: Apr 7 - Apr 13 2025 | B87: 9281.84 | C87: =(B87*0.06)*1.13 -> 629.30875 | D87: =(B87*0.02)*1.13 -> 209.76958 | G87: 6736.8 | H87: 108.3 | I87: 136.29 | J87: 2252.98 | K87: 2300.45 | L87: 0 | M87: =K87-L87 -> 2300.45 | N87: =SUM(G87,H87,I87,M87) -> 9281.84
A88: Apr 14 - Apr 20 2025 | B88: 10311.72 | C88: =(B88*0.06)*1.13 -> 699.13462 | D88: =(B88*0.02)*1.13 -> 233.04487 | G88: 7841.25 | H88: 101.2 | I88: 146.7 | J88: 2103.19 | K88: 2336.79 | L88: 114.22 | M88: =K88-L88 -> 2222.57 | N88: =SUM(G88,H88,I88,M88) -> 10311.72
A89: Apr 21 - Apr 27 2025 | B89: 9208 | C89: =(B89*0.06)*1.13 -> 624.3024 | D89: =(B89*0.02)*1.13 -> 208.1008 | G89: 6993.59 | H89: 300.65 | I89: 58.17 | J89: 2034.67 | K89: 1992.27 | L89: 136.68 | M89: =K89-L89 -> 1855.59 | N89: =SUM(G89,H89,I89,M89) -> 9208
A90: Apr 28 - May 04 2025 | B90: 9146.91 | C90: =(B90*0.06)*1.13 -> 620.1605 | D90: =(B90*0.02)*1.13 -> 206.72017 | G90: 6974.01 | H90: 200.86 | I90: 135.69 | J90: 1855.67 | K90: 1871.67 | L90: 35.32 | M90: =K90-L90 -> 1836.35 | N90: =SUM(G90,H90,I90,M90) -> 9146.91
A91: May 05 - May 11 2025 | B91: 9126.32 | C91: =(B91*0.06)*1.13 -> 618.7645 | D91: =(B91*0.02)*1.13 -> 206.25483 | F91: 9132.71 | G91: 7153.39 | H91: 144.26 | I91: 26.4 | J91: 1808.66 | K91: 1802.27 | L91: 0 | M91: =K91-L91 -> 1802.27 | N91: =SUM(G91,H91,I91,M91) -> 9126.32
A92: May 12 - May 18 2025 | B92: 8593.31 | C92: =(B92*0.06)*1.13 -> 582.62642 | D92: =(B92*0.02)*1.13 -> 194.20881 | F92: 8603.71 | G92: 6540.78 | H92: 156.38 | I92: 67.2 | J92: 1839.35 | K92: 1828.95 | L92: 0 | M92: =K92-L92 -> 1828.95 | N92: =SUM(G92,H92,I92,M92) -> 8593.31
A93: May 19 - May 25 2025 | B93: 10236.01 | C93: =(B93*0.06)*1.13 -> 694.00148 | D93: =(B93*0.02)*1.13 -> 231.33383 | F93: 10220.41 | G93: 8098.96 | H93: 128.97 | I93: 62.4 | J93: 1930.08 | K93: 1945.68 | L93: 0 | M93: =K93-L93 -> 1945.68 | N93: =SUM(G93,H93,I93,M93) -> 10236.01
A94: May 26 - June 01 2025 | B94: 9515.03 | C94: =(B94*0.06)*1.13 -> 645.11903 | D94: =(B94*0.02)*1.13 -> 215.03968 | F94: 9491.82 | G94: 7625.22 | H94: 116.17 | I94: 68.27 | J94: 1682.16 | K94: 1705.37 | L94: 0 | M94: =K94-L94 -> 1705.37 | N94: =SUM(G94,H94,I94,M94) -> 9515.03
A95: June 02 - June 08 2025 | B95: 8933.1 | C95: =(B95*0.06)*1.13 -> 605.66418 | D95: =(B95*0.02)*1.13 -> 201.88806 | F95: 8933.1 | G95: 7339.26 | H95: 0 | I95: 77.39 | J95: 1516.45 | K95: 1516.45 | L95: 0 | M95: =K95-L95 -> 1516.45 | N95: =SUM(G95,H95,I95,M95) -> 8933.1
A96: June 09 - June 15 2025 | B96: 9723.83 | C96: =(B96*0.06)*1.13 -> 659.27567 | D96: =(B96*0.02)*1.13 -> 219.75856 | F96: 9697.43 | G96: 7344.08 | H96: 207.6 | I96: 75 | J96: 2070.75 | K96: 2097.15 | L96: 0 | M96: =K96-L96 -> 2097.15 | N96: =SUM(G96,H96,I96,M96) -> 9723.83
A97: June 16 - June 22 2025 | B97: 7801.29 | C97: =(B97*0.06)*1.13 -> 528.92746 | D97: =(B97*0.02)*1.13 -> 176.30915 | F97: 7896.68 | G97: 5657.82 | H97: 201.86 | I97: 212.4 | J97: 1824.6 | K97: 1729.21 | L97: 0 | M97: =K97-L97 -> 1729.21 | N97: =SUM(G97,H97,I97,M97) -> 7801.29
A98: June 23 - June 29 2025 | B98: 9699.92 | C98: =(B98*0.06)*1.13 -> 657.65458 | D98: =(B98*0.02)*1.13 -> 219.21819 | F98: 9722.12 | G98: 7494.14 | H98: 136 | I98: 66.33 | J98: 2025.65 | K98: 2003.45 | L98: 0 | M98: =K98-L98 -> 2003.45 | N98: =SUM(G98,H98,I98,M98) -> 9699.92
A99: June 30 - July 06 2025 | B99: 10751.68 | C99: =(B99*0.06)*1.13 -> 728.9639 | D99: =(B99*0.02)*1.13 -> 242.98797 | F99: 11285.55 | G99: 8390.21 | H99: 109.4 | I99: 71.4 | J99: 2714.54 | K99: 2629.35 | L99: 448.68 | M99: =K99-L99 -> 2180.67 | N99: =SUM(G99,H99,I99,M99) -> 10751.68
A100: July 07 - July 13 2025 | B100: 9122.01 | C100: =(B100*0.06)*1.13 -> 618.47228 | D100: =(B100*0.02)*1.13 -> 206.15743 | F100: 9757.67 | G100: 5892.12 | H100: 172.76 | I100: 166.8 | J100: 3525.99 | K100: 3564.39 | L100: 674.06 | M100: =K100-L100 -> 2890.33 | N100: =SUM(G100,H100,I100,M100) -> 9122.01
A101: July 14 - July 20 2025 | B101: 9419.27 | C101: =(B101*0.06)*1.13 -> 638.62651 | D101: =(B101*0.02)*1.13 -> 212.8755 | E101: 285 | F101: 9832.73 | G101: 7088.72 | H101: 131.12 | I101: 211.73 | J101: 2401.16 | K101: 2450.35 | L101: 462.65 | M101: =K101-L101 -> 1987.7 | N101: =SUM(G101,H101,I101,M101) -> 9419.27
A102: July 21 - July 27 2025 | B102: 10415.91 | C102: =(B102*0.06)*1.13 -> 706.1987 | D102: =(B102*0.02)*1.13 -> 235.39957 | E102: 378 | F102: 11175.11 | G102: 7756.08 | H102: 48 | I102: 58.8 | J102: 3312.23 | K102: 3326.64 | L102: 773.61 | M102: =K102-L102 -> 2553.03 | N102: =SUM(G102,H102,I102,M102) -> 10415.91
A103: July 28 - Aug 03 2025 | B103: 9101.52 | C103: =(B103*0.06)*1.13 -> 617.08306 | D103: =(B103*0.02)*1.13 -> 205.69435 | E103: 311 | F103: 9721.12 | G103: 6488.6 | H103: 0 | I103: 209.74 | J103: 3022.78 | K103: 3077.98 | L103: 674.8 | M103: =K103-L103 -> 2403.18 | N103: =SUM(G103,H103,I103,M103) -> 9101.52
A104: Aug 04 - Aug 10 2025 | B104: 9528.04 | C104: =(B104*0.06)*1.13 -> 646.00111 | D104: =(B104*0.02)*1.13 -> 215.3337 | E104: 307 | F104: 10132.29 | G104: 6846.95 | H104: 213.87 | I104: 197.19 | J104: 2874.28 | K104: 2919.88 | L104: 649.85 | M104: =K104-L104 -> 2270.03 | N104: =SUM(G104,H104,I104,M104) -> 9528.04
A105: Aug 11 - Aug 17 2025 | B105: 10371.73 | C105: =(B105*0.06)*1.13 -> 703.20329 | D105: =(B105*0.02)*1.13 -> 234.4011 | E105: 294 | F105: 10689.38 | G105: 7505.28 | H105: 157.47 | I105: 80.4 | J105: 2946.23 | K105: 3143.13 | L105: 514.55 | M105: =K105-L105 -> 2628.58 | N105: =SUM(G105,H105,I105,M105) -> 10371.73
A106: Aug 18 - Aug 24 2025 | B106: 9854.62 | C106: =(B106*0.06)*1.13 -> 668.14324 | D106: =(B106*0.02)*1.13 -> 222.71441 | E106: 300 | F106: 10355.62 | G106: 7294.81 | H106: 147.5 | I106: 54 | J106: 2859.31 | K106: 2939.01 | L106: 580.7 | M106: =K106-L106 -> 2358.31 | N106: =SUM(G106,H106,I106,M106) -> 9854.62
A107: Aug 25 - Aug 31 2025 | B107: 9335.72 | C107: =(B107*0.06)*1.13 -> 632.96182 | D107: =(B107*0.02)*1.13 -> 210.98727 | E107: 324 | F107: 9950.75 | G107: 6940.95 | H107: 38.8 | I107: 96.46 | J107: 2874.54 | K107: 2866.16 | L107: 606.65 | M107: =K107-L107 -> 2259.51 | N107: =SUM(G107,H107,I107,M107) -> 9335.72
A108: Sep 01 - Sep 07 2025 | B108: 8355.39 | C108: =(B108*0.06)*1.13 -> 566.49544 | D108: =(B108*0.02)*1.13 -> 188.83181 | E108: 264 | F108: 8307.99 | G108: 6073.96 | H108: 121 | I108: 157.35 | J108: 1955.68 | K108: 2003.08 | L108: 0 | M108: =K108-L108 -> 2003.08 | N108: =SUM(G108,H108,I108,M108) -> 8355.39
A109: Sep 08 - Sep 14 2025 | B109: 7442.94 | C109: =(B109*0.06)*1.13 -> 504.63133 | D109: =(B109*0.02)*1.13 -> 168.21044 | E109: 241 | F109: 7321.46 | G109: 5435.7 | H109: 134.44 | I109: 121.78 | J109: 1629.54 | K109: 1751.02 | L109: 0 | M109: =K109-L109 -> 1751.02 | N109: =SUM(G109,H109,I109,M109) -> 7442.94
A110: Sep 15 - Sep 21 2025 | B110: 7721.95 | C110: =(B110*0.06)*1.13 -> 523.54821 | D110: =(B110*0.02)*1.13 -> 174.51607 | E110: 249 | F110: 7634.65 | G110: 6041.33 | H110: 161.07 | I110: 0 | J110: 1432.25 | K110: 1519.55 | L110: 0 | M110: =K110-L110 -> 1519.55 | N110: =SUM(G110,H110,I110,M110) -> 7721.95
A111: Sep 22 - Sep 28 2025 | B111: 7747.38 | C111: =(B111*0.06)*1.13 -> 525.27236 | D111: =(B111*0.02)*1.13 -> 175.09079 | E111: 250 | F111: 7738.98 | G111: 6213 | H111: 18 | I111: 132.89 | J111: 1375.09 | K111: 1383.49 | L111: 0 | M111: =K111-L111 -> 1383.49 | N111: =SUM(G111,H111,I111,M111) -> 7747.38
A112: Sep 29 - Oct 05 2025 | B112: 7630.92 | C112: =(B112*0.06)*1.13 -> 517.37638 | D112: =(B112*0.02)*1.13 -> 172.45879 | E112: 248 | F112: 7685.27 | G112: 6256.78 | H112: 115.07 | I112: 112.28 | J112: 1201.14 | K112: 1205.95 | L112: 59.16 | M112: =K112-L112 -> 1146.79 | N112: =SUM(G112,H112,I112,M112) -> 7630.92
A113: Oct 6 - Oct 12 2025 | B113: 9383.4 | C113: =(B113*0.06)*1.13 -> 636.19452 | D113: =(B113*0.02)*1.13 -> 212.06484 | E113: 287 | F113: 9383.4 | G113: 7417.86 | H113: 176.96 | I113: 87.18 | J113: 1701.4 | K113: 1701.4 | L113: 0 | M113: =K113-L113 -> 1701.4 | N113: =SUM(G113,H113,I113,M113) -> 9383.4
A114: Oct 13 - Oct 19 2025 | B114: 8292.72 | C114: =(B114*0.06)*1.13 -> 562.24642 | D114: =(B114*0.02)*1.13 -> 187.41547 | F114: 8292.72 | G114: 6642.43 | H114: 88 | I114: 286.49 | J114: 1275.8 | K114: 1275.8 | L114: 0 | M114: =K114-L114 -> 1275.8 | N114: =SUM(G114,H114,I114,M114) -> 8292.72
A115: Oct 20 - Oct 26 2025 | B115: 8898.09 | C115: =(B115*0.06)*1.13 -> 603.2905 | D115: =(B115*0.02)*1.13 -> 201.09683 | E115: 261 | F115: 8755.45 | G115: 7054.66 | H115: 290.91 | I115: 132.46 | J115: 1277.42 | K115: 1420.06 | L115: 0 | M115: =K115-L115 -> 1420.06 | N115: =SUM(G115,H115,I115,M115) -> 8898.09
A116: Oct 27 - Nov 02 2025 | B116: 7239.21 | C116: =(B116*0.06)*1.13 -> 490.81844 | D116: =(B116*0.02)*1.13 -> 163.60615 | E116: 231 | F116: 7172.12 | G116: 5412.3 | H116: 62.4 | I116: 29.99 | J116: 1667.43 | K116: 1734.52 | L116: 0 | M116: =K116-L116 -> 1734.52 | N116: =SUM(G116,H116,I116,M116) -> 7239.21
A117: Nov 03 - Nov 09 2025 | B117: 8001.94 | C117: =(B117*0.06)*1.13 -> 542.53153 | D117: =(B117*0.02)*1.13 -> 180.84384 | E117: 244 | F117: 7961.01 | G117: 5823.18 | H117: 34 | I117: 144.48 | J117: 1959.35 | K117: 2000.28 | L117: 0 | M117: =K117-L117 -> 2000.28 | N117: =SUM(G117,H117,I117,M117) -> 8001.94
A118: Nov 10 - Nov 16 2025 | B118: 7600.81 | C118: =(B118*0.06)*1.13 -> 515.33492 | D118: =(B118*0.02)*1.13 -> 171.77831 | E118: 257 | F118: 7559.07 | G118: 6084.54 | H118: 26.4 | I118: 0 | J118: 1448.13 | K118: 1489.87 | L118: 0 | M118: =K118-L118 -> 1489.87 | N118: =SUM(G118,H118,I118,M118) -> 7600.81
A119: Nov 17 - Nov 23 2025 | B119: 8038.43 | C119: =(B119*0.06)*1.13 -> 545.00555 | D119: =(B119*0.02)*1.13 -> 181.66852 | E119: 258 | F119: 8134.63 | G119: 5658 | H119: 151.06 | I119: 94.89 | J119: 2230.68 | K119: 2200.21 | L119: 65.73 | M119: =K119-L119 -> 2134.48 | N119: =SUM(G119,H119,I119,M119) -> 8038.43
A120: Nov 24 - Nov 30 2025 | B120: 8358.95 | C120: =(B120*0.06)*1.13 -> 566.73681 | D120: =(B120*0.02)*1.13 -> 188.91227 | E120: 271 | F120: 8499.65 | G120: 6178.94 | H120: 20.14 | I120: 79.35 | J120: 2221.22 | K120: 2261.3 | L120: 180.78 | M120: =K120-L120 -> 2080.52 | N120: =SUM(G120,H120,I120,M120) -> 8358.95
A121: Dec 01 - Dec 07 2025 | B121: 8898.77 | C121: =(B121*0.06)*1.13 -> 603.33661 | D121: =(B121*0.02)*1.13 -> 201.1122 | E121: 341 | F121: 9145.69 | G121: 5879.82 | H121: 67.34 | I121: 43.49 | J121: 3155.04 | K121: 3121.66 | L121: 213.54 | M121: =K121-L121 -> 2908.12 | N121: =SUM(G121,H121,I121,M121) -> 8898.77
A122: Dec 08 - Dec 14 2025 | B122: 8495.72 | C122: =(B122*0.06)*1.13 -> 576.00982 | D122: =(B122*0.02)*1.13 -> 192.00327 | E122: 266 | F122: 8532.7 | G122: 5405.2 | H122: 49.2 | I122: 181.29 | J122: 2897.01 | K122: 3075.97 | L122: 215.94 | M122: =K122-L122 -> 2860.03 | N122: =SUM(G122,H122,I122,M122) -> 8495.72
A123: Dec 15 - Dec 21 2025 | B123: 8747.05 | C123: =(B123*0.06)*1.13 -> 593.04999 | D123: =(B123*0.02)*1.13 -> 197.68333 | E123: 294 | F123: 9053.23 | G123: 6354.74 | H123: 106.19 | I123: 112.18 | J123: 2480.12 | K123: 2447.42 | L123: 273.48 | M123: =K123-L123 -> 2173.94 | N123: =SUM(G123,H123,I123,M123) -> 8747.05
A124: Dec 22 - Dec 28 2025 | B124: 11628.19 | C124: =(B124*0.06)*1.13 -> 788.39128 | D124: =(B124*0.02)*1.13 -> 262.79709 | E124: 343 | F124: 11883.39 | G124: 7749.16 | H124: 132.27 | I124: 88.79 | J124: 3913.17 | K124: 3970.21 | L124: 312.24 | M124: =K124-L124 -> 3657.97 | N124: =SUM(G124,H124,I124,M124) -> 11628.19
...

Sheet Jane
A1: Wonderland
A2: Statement For Selected Period | B2: Total Revenue (Net Sales) | C2: Royalties (6%) | D2: Marketing (2%)
A3: Aug 12 - Aug 18 2024 | B3: 2155.81 | C3: =(B3*0.06)*1.13 -> 146.16392 | D3: =(B3*0.02)*1.13 -> 48.721306
A4: Aug 19 - Aug 25 2024 | B4: 8077.84 | C4: =(B4*0.06)*1.13 -> 547.67755 | D4: =(B4*0.02)*1.13 -> 182.55918
A5: Aug 26 - Sep 01 2024 | B5: 11929.59 | C5: =(B5*0.06)*1.13 -> 808.8262 | D5: =(B5*0.02)*1.13 -> 269.60873
A6: Sep 02 - Sep 08 2024 | B6: 8374.32 | C6: =(B6*0.06)*1.13 -> 567.7789 | D6: =(B6*0.02)*1.13 -> 189.25963
A7: Sep 09 - Sep 15 2024 | B7: 8953.43 | C7: =(B7*0.06)*1.13 -> 607.04255 | D7: =(B7*0.02)*1.13 -> 202.34752
A8: Sep 16 - Sep 22 2024 | B8: 9370.37 | C8: =(B8*0.06)*1.13 -> 635.31109 | D8: =(B8*0.02)*1.13 -> 211.77036
A9: Sep 23 - Sep 29 2024 | B9: 11456.84 | C9: =(B9*0.06)*1.13 -> 776.77375 | D9: =(B9*0.02)*1.13 -> 258.92458
A10: Sep 30 - Oct 06 2024 | B10: 11124.69 | C10: =(B10*0.06)*1.13 -> 754.25398 | D10: =(B10*0.02)*1.13 -> 251.41799
A11: Oct 07 - Oct 13 2024 | B11: 9620.03 | C11: =(B11*0.06)*1.13 -> 652.23803 | D11: =(B11*0.02)*1.13 -> 217.41268
A12: Oct 14 - Oct 20 2024 | B12: 11409.59 | C12: =(B12*0.06)*1.13 -> 773.5702 | D12: =(B12*0.02)*1.13 -> 257.85673
A13: Oct 21 - Oct 27 2024 | B13: 11377.48 | C13: =(B13*0.06)*1.13 -> 771.39314 | D13: =(B13*0.02)*1.13 -> 257.13105
A14: Oct 28 - Nov 03 2024 | B14: 9556.77 | C14: =(B14*0.06)*1.13 -> 647.94901 | D14: =(B14*0.02)*1.13 -> 215.983
... A19: Dec 02 - Dec 08 2024 | B19: 6573.21 | C19: =(B19*0.06)*1.13 -> 445.66364 | D19: =(B19*0.02)*1.13 -> 148.55455
A20: Dec 09 - Dec 15 2024 | B20: 7432.33 | C20: =(B20*0.06)*1.13 -> 503.91197 | D20: =(B20*0.02)*1.13 -> 167.97066 | E20: Bill Count | F20: TB Total | G20: In Store | H20: Skip | I20: DD | J20: Uber TB | K20: Uber Website | L20: Marketing/Discount | M20: Smash Ox Rev | N20: Smash Ox Marketing | O20: Uber (After Discount) | P20: Total Revenue
A21: Dec 16 - Dec 22 2024 | B21: 7909.19 | C21: =(B21*0.06)*1.13 -> 536.24308 | D21: =(B21*0.02)*1.13 -> 178.74769 | G21: 5772.68 | H21: 98.74 | I21: 163.2 | J21: 2815.1 | K21: 2815.1 | L21: 940.53 | O21: =K21-L21 -> 1874.57 | P21: =SUM(O21,I21,H21,G21) -> 7909.19
C22: =(B22*0.06)*1.13 -> 0 | D22: =(B22*0.02)*1.13 -> 0 | J22: 65 orders | K22: 65 orders
A23: Dec 23 - Dec 29 2024 | B23: 11818.28 | C23: =(B23*0.06)*1.13 -> 801.27938 | D23: =(B23*0.02)*1.13 -> 267.09313 | G23: 8559.6 | H23: 22.8 | I23: 111.89 | J23: 4752.48 | K23: 4752.48 | L23: =1625.79+2.7 -> 1628.49 | O23: =K23-L23 -> 3123.99 | P23: =SUM(O23,I23,H23,G23) -> 11818.28
C24: =(B24*0.06)*1.13 -> 0 | D24: =(B24*0.02)*1.13 -> 0 | J24: 98 orders | K24: 98 orders
A25: Dec 30 - Jan 05 2025 | B25: 11433.7 | C25: =(B25*0.06)*1.13 -> 775.20486 | D25: =(B25*0.02)*1.13 -> 258.40162 | G25: 8336.8 | H25: 133.19 | I25: 185.69 | J25: 4093.06 | K25: 4131.06 | L25: =1323.94+29.1 -> 1353.04 | O25: =K25-L25 -> 2778.02 | P25: =SUM(G25,H25,I25,O25) -> 11433.7
C26: =(B26*0.06)*1.13 -> 0 | D26: =(B26*0.02)*1.13 -> 0 | J26: 91 orders | K26: 92 orders
A27: Jan 06 - Jan 12 2025 | B27: 7060.74 | C27: =(B27*0.06)*1.13 -> 478.71817 | D27: =(B27*0.02)*1.13 -> 159.57272 | G27: 4933.67 | H27: 22.8 | I27: 125.37 | J27: 2770.9 | K27: 2770.9 | L27: 792 | O27: =K27-L27 -> 1978.9 | P27: =SUM(G27,H27,I27,O27) -> 7060.74
C28: =(B28*0.06)*1.13 -> 0 | D28: =(B28*0.02)*1.13 -> 0 | J28: 58 | K28: 58
A29: Jan 13 - Jan 19 2025 | B29: 9149.74 | C29: =(B29*0.06)*1.13 -> 620.35237 | D29: =(B29*0.02)*1.13 -> 206.78412 | G29: 6642.75 | H29: 78.4 | I29: 31.59 | J29: 2887.05 | K29: 3459 | L29: 1062 | O29: =K29-L29 -> 2397 | P29: =SUM(G29,H29,I29,O29) -> 9149.74
C30: =(B30*0.06)*1.13 -> 0 | D30: =(B30*0.02)*1.13 -> 0
A31: Jan 20 - Jan 26 2025 | B31: 7637.81 | C31: =(B31*0.06)*1.13 -> 517.84352 | D31: =(B31*0.02)*1.13 -> 172.61451 | G31: 5102.85 | H31: 76.67 | I31: 40.8 | J31: 3425.49 | K31: 3461.49 | L31: 1044 | O31: =K31-L31 -> 2417.49 | P31: =SUM(G31,H31,I31,O31) -> 7637.81
C32: =(B32*0.06)*1.13 -> 0 | D32: =(B32*0.02)*1.13 -> 0 | P32: =SUM(G32,H32,I32,O32) -> 0
A33: Jan 27 - Feb 02 2025 | B33: 8956.04 | C33: =(B33*0.06)*1.13 -> 607.21951 | D33: =(B33*0.02)*1.13 -> 202.4065 | G33: 6202.67 | H33: 70.92 | I33: 80.4 | J33: 3824.05 | K33: 3826.05 | L33: 1224 | O33: =K33-L33 -> 2602.05 | P33: =SUM(G33,H33,I33,O33) -> 8956.04
C34: =(B34*0.06)*1.13 -> 0 | D34: =(B34*0.02)*1.13 -> 0
A35: Feb 03 - Feb 09 2025 | B35: 8608.3 | C35: =(B35*0.06)*1.13 -> 583.64274 | D35: =(B35*0.02)*1.13 -> 194.54758 | G35: 6327.3 | H35: 39.87 | I35: 366.28 | J35: 2016.85 | K35: 2018.85 | L35: 144 | O35: =K35-L35 -> 1874.85 | P35: =SUM(G35,H35,I35,O35) -> 8608.3
C36: =(B36*0.06)*1.13 -> 0 | D36: =(B36*0.02)*1.13 -> 0
A37: Feb 10 - Feb 16 2025 | B37: 8833.99 | C37: =(B37*0.06)*1.13 -> 598.94452 | D37: =(B37*0.02)*1.13 -> 199.64817 | G37: 6502.12 | H37: 47.13 | I37: 332.33 | J37: 2035.3 | K37: 2008.9 | L37: 56.49 | O37: =K37-L37 -> 1952.41 | P37: =SUM(G37,H37,I37,O37) -> 8833.99
C38: =(B38*0.06)*1.13 -> 0 | D38: =(B38*0.02)*1.13 -> 0
A39: Feb 17 - Feb 23 2025 | B39: 8500.48 | C39: =(B39*0.06)*1.13 -> 576.33254 | D39: =(B39*0.02)*1.13 -> 192.11085 | G39: 5630.35 | H39: 50.39 | I39: 354.55 | J39: 2530.36 | K39: 2601.02 | L39: 135.83 | O39: =K39-L39 -> 2465.19 | P39: =SUM(G39,H39,I39,O39) -> 8500.48
C40: =(B40*0.06)*1.13 -> 0 | D40: =(B40*0.02)*1.13 -> 0
A41: Feb 24 - Mar 02 2025 | B41: 7690.28 | C41: =(B41*0.06)*1.13 -> 521.40098 | D41: =(B41*0.02)*1.13 -> 173.80033 | G41: 5726.56 | H41: 77.05 | I41: 202.77 | J41: 1745.82 | K41: 1759.01 | L41: 75.11 | O41: =K41-L41 -> 1683.9 | P41: =SUM(G41,H41,I41,O41) -> 7690.28
C42: =(B42*0.06)*1.13 -> 0 | D42: =(B42*0.02)*1.13 -> 0
A43: Mar 03 - Mar 09 2025 | B43: 6502.39 | C43: =(B43*0.06)*1.13 -> 440.86204 | D43: =(B43*0.02)*1.13 -> 146.95401 | G43: 4634.61 | H43: 131.39 | I43: 94.8 | J43: 1659.44 | K43: 1659.44 | L43: 17.85 | O43: =K43-L43 -> 1641.59 | P43: =SUM(G43,H43,I43,O43) -> 6502.39
C44: =(B44*0.06)*1.13 -> 0 | D44: =(B44*0.02)*1.13 -> 0
A45: Mar 10 - Mar 16 2025 | B45: 7944.11 | C45: =(B45*0.06)*1.13 -> 538.61066 | D45: =(B45*0.02)*1.13 -> 179.53689 | G45: 5586.64 | H45: 31.79 | I45: 128.38 | J45: 2405.6 | K45: 2405.6 | L45: 208.3 | O45: =K45-L45 -> 2197.3 | P45: =SUM(G45,H45,I45,O45) -> 7944.11
C46: =(B46*0.06)*1.13 -> 0 | D46: =(B46*0.02)*1.13 -> 0
A47: Mar 17 - Mar 23 2025 | B47: 8203.64 | C47: =(B47*0.06)*1.13 -> 556.20679 | D47: =(B47*0.02)*1.13 -> 185.40226 | G47: 5741.22 | H47: 120.33 | I47: 129.38 | J47: 2535.95 | K47: 2535.95 | L47: 323.24 | O47: =K47-L47 -> 2212.71 | P47: =SUM(G47,H47,I47,O47) -> 8203.64
C48: =(B48*0.06)*1.13 -> 0 | D48: =(B48*0.02)*1.13 -> 0 | O48: =K48-L48 -> 0 | P48: =SUM(G48,H48,I48,O48) -> 0
A49: Mar 24 - Mar 30 2025 | B49: 9113.96 | C49: =(B49*0.06)*1.13 -> 617.92649 | D49: =(B49*0.02)*1.13 -> 205.9755 | G49: 6392.4 | H49: 26.4 | I49: 172.78 | J49: 2532 | K49: 2563.19 | L49: 40.81 | O49: =K49-L49 -> 2522.38 | P49: =SUM(G49,H49,I49,O49) -> 9113.96
C50: =(B50*0.06)*1.13 -> 0 | D50: =(B50*0.02)*1.13 -> 0
A51: Mar 31 - Apr 6 2025 | B51: 9443.84 | C51: =(B51*0.06)*1.13 -> 640.29235 | D51: =(B51*0.02)*1.13 -> 213.43078 | G51: 6536.04 | H51: 54.59 | I51: 400.75 | J51: 2453.01 | K51: 2455.01 | L51: 2.55 | O51: =K51-L51 -> 2452.46 | P51: =SUM(G51,H51,I51,O51) -> 9443.84
C52: =(B52*0.06)*1.13 -> 0 | D52: =(B52*0.02)*1.13 -> 0
A53: Apr 7 - Apr 13 2025 | B53: 9090.54 | C53: =(B53*0.06)*1.13 -> 616.33861 | D53: =(B53*0.02)*1.13 -> 205.4462 | G53: 6480.88 | H53: 34 | I53: 101.16 | J53: 2580.72 | K53: 2580.72 | L53: 106.22 | O53: =K53-L53 -> 2474.5 | P53: =SUM(G53,H53,I53,O53) -> 9090.54
A54: Apr 14 - Apr 20 2025 | B54: 9797.4 | C54: =(B54*0.06)*1.13 -> 664.26372 | D54: =(B54*0.02)*1.13 -> 221.42124 | G54: 7019.51 | H54: 270.47 | I54: 173.39 | J54: 2434.5 | K54: 2434.5 | L54: 100.47 | O54: =K54-L54 -> 2334.03 | P54: =SUM(G54,H54,I54,O54) -> 9797.4
A55: Apr 21 - Apr 27 2025 | B55: 10090.21 | C55: =(B55*0.06)*1.13 -> 684.11624 | D55: =(B55*0.02)*1.13 -> 228.03875 | G55: 6476.07 | H55: 172.47 | I55: 219.56 | J55: 3381.99 | K55: 3381.99 | L55: 159.88 | O55: =K55-L55 -> 3222.11 | P55: =SUM(G55,H55,I55,O55) -> 10090.21
A56: Apr 28 - May 04 2025 | B56: 8677.22 | C56: =(B56*0.06)*1.13 -> 588.31552 | D56: =(B56*0.02)*1.13 -> 196.10517 | G56: 6534.2 | H56: 52 | I56: 77.97 | J56: 2112.82 | K56: 2114.82 | L56: 101.77 | O56: =K56-L56 -> 2013.05 | P56: =SUM(G56,H56,I56,O56) -> 8677.22
A57: May 05 - May 11 2025 | B57: 10193.15 | C57: =(B57*0.06)*1.13 -> 691.09557 | D57: =(B57*0.02)*1.13 -> 230.36519 | F57: 10315.41 | G57: 7879.77 | H57: 194.38 | I57: 151.79 | J57: 2089.47 | K57: 2089.47 | L57: 122.26 | O57: =K57-L57 -> 1967.21 | P57: =SUM(G57,H57,I57,O57) -> 10193.15
A58: May 12 - May 18 2025 | B58: 12954.94 | C58: =(B58*0.06)*1.13 -> 878.34493 | D58: =(B58*0.02)*1.13 -> 292.78164 | F58: 13019.07 | G58: 10604.2 | H58: 18 | I58: 122.79 | J58: 2274.08 | K58: 2298.08 | L58: 88.13 | O58: =K58-L58 -> 2209.95 | P58: =SUM(G58,H58,I58,O58) -> 12954.94
A59: May 19 - May 25 2025 | B59: 12451.66 | C59: =(B59*0.06)*1.13 -> 844.22255 | D59: =(B59*0.02)*1.13 -> 281.40752 | F59: 12581.42 | G59: 9716.56 | H59: 31.6 | I59: 327.52 | J59: 2505.74 | K59: 2505.74 | L59: 129.76 | O59: =K59-L59 -> 2375.98 | P59: =SUM(G59,H59,I59,O59) -> 12451.66
A60: May 26 - June 01 2025 | B60: 12820.66 | C60: =(B60*0.06)*1.13 -> 869.24075 | D60: =(B60*0.02)*1.13 -> 289.74692 | F60: 12914.17 | G60: 10539.05 | H60: 63.9 | I60: 177.37 | J60: 2133.85 | K60: 2133.85 | L60: 93.51 | O60: =K60-L60 -> 2040.34 | P60: =SUM(G60,H60,I60,O60) -> 12820.66
A61: June 02 - June 08 2025 | B61: 12484.1 | C61: =(B61*0.06)*1.13 -> 846.42198 | D61: =(B61*0.02)*1.13 -> 282.14066 | F61: 12572.13 | G61: 10178.35 | H61: 0 | I61: 87.2 | J61: 2306.58 | K61: 2347.38 | L61: 128.83 | O61: =K61-L61 -> 2218.55 | P61: =SUM(G61,H61,I61,O61) -> 12484.1
A62: June 09 - June 15 2025 | B62: 13976.4 | C62: =(B62*0.06)*1.13 -> 947.59992 | D62: =(B62*0.02)*1.13 -> 315.86664 | F62: 14114.3 | G62: 10842.72 | H62: 0 | I62: 289.85 | J62: 2981.73 | K62: 2999.73 | L62: 155.9 | O62: =K62-L62 -> 2843.83 | P62: =SUM(G62,H62,I62,O62) -> 13976.4
A63: June 16 - June 22 2025 | B63: 14689.37 | C63: =(B63*0.06)*1.13 -> 995.93929 | D63: =(B63*0.02)*1.13 -> 331.97976 | F63: 14802.96 | G63: 11672.57 | H63: 125.2 | I63: 217.75 | J63: 2787.44 | K63: 2799.44 | L63: 125.59 | O63: =K63-L63 -> 2673.85 | P63: =SUM(G63,H63,I63,O63) -> 14689.37
A64: June 23 - June 29 2025 | B64: 16548.29 | C64: =(B64*0.06)*1.13 -> 1121.9741 | D64: =(B64*0.02)*1.13 -> 373.99135 | F64: 16665.19 | G64: 13989.28 | H64: 141.6 | I64: 308.72 | J64: 2225.59 | K64: 2225.59 | L64: 116.9 | O64: =K64-L64 -> 2108.69 | P64: =SUM(G64,H64,I64,O64) -> 16548.29
A65: June 30 - July 06 2025 | B65: 16616.67 | C65: =(B65*0.06)*1.13 -> 1126.6102 | D65: =(B65*0.02)*1.13 -> 375.53674 | F65: 16643.15 | G65: 14252.93 | H65: 0 | I65: 68.09 | J65: 2322.13 | K65: 2322.13 | L65: 26.48 | O65: =K65-L65 -> 2295.65 | P65: =SUM(G65,H65,I65,O65) -> 16616.67
A66: July 07 - July 13 2025 | B66: 18467.66 | C66: =(B66*0.06)*1.13 -> 1252.1073 | D66: =(B66*0.02)*1.13 -> 417.36912 | F66: 18505.62 | G66: 15414.09 | H66: 55.47 | I66: 117.4 | J66: 2918.66 | K66: 2971.46 | L66: 90.76 | O66: =K66-L66 -> 2880.7 | P66: =SUM(G66,H66,I66,O66) -> 18467.66
A67: July 14 - July 20 2025 | B67: 16637.82 | C67: =(B67*0.06)*1.13 -> 1128.0442 | D67: =(B67*0.02)*1.13 -> 376.01473 | E67: 664 | F67: 16730.49 | G67: 14210.58 | H67: 7.2 | I67: 269.71 | J67: 2243 | K67: 2243 | L67: 92.67 | O67: =K67-L67 -> 2150.33 | P67: =SUM(G67,H67,I67,O67) -> 16637.82
A68: July 21 - July 27 2025 | B68: 17623.37 | C68: =(B68*0.06)*1.13 -> 1194.8645 | D68: =(B68*0.02)*1.13 -> 398.28816 | E68: 743 | F68: 17702.63 | G68: 15508.86 | H68: 24 | I68: 0 | J68: 2169.77 | K68: 2169.77 | L68: 79.26 | O68: =K68-L68 -> 2090.51 | P68: =SUM(G68,H68,I68,O68) -> 17623.37
A69: July 28 - Aug 03 2025 | B69: 19107.22 | C69: =(B69*0.06)*1.13 -> 1295.4695 | D69: =(B69*0.02)*1.13 -> 431.82317 | E69: 778 | F69: 19220.35 | G69: 16285.36 | H69: 206.87 | I69: 130.04 | J69: 2598.08 | K69: 2572.08 | L69: 87.13 | O69: =K69-L69 -> 2484.95 | P69: =SUM(G69,H69,I69,O69) -> 19107.22
A70: Aug 04 - Aug 10 2025 | B70: 18962.14 | C70: =(B70*0.06)*1.13 -> 1285.6331 | D70: =(B70*0.02)*1.13 -> 428.54436 | E70: 773 | F70: 19164 | G70: 16060.62 | H70: 0 | I70: 77.99 | J70: 3025.39 | K70: 2945.04 | L70: 121.51 | O70: =K70-L70 -> 2823.53 | P70: =SUM(G70,H70,I70,O70) -> 18962.14
A71: Aug 11 - Aug 17 2025 | B71: 18130.69 | C71: =(B71*0.06)*1.13 -> 1229.2608 | D71: =(B71*0.02)*1.13 -> 409.75359 | E71: 753 | F71: 18248.85 | G71: 15537.57 | H71: 146.61 | I71: 0 | J71: 2564.67 | K71: 2430.37 | L71: 94.99 | M71: 134.3 | N71: 23.17 | O71: =(K71-L71)+(M71-N71) -> 2446.51 | P71: =SUM(G71,H71,I71,O71) -> 18130.69
A72: Aug 18 - Aug 24 2025 | B72: 19722.38 | C72: =(B72*0.06)*1.13 -> 1337.1774 | D72: =(B72*0.02)*1.13 -> 445.72579 | E72: 808 | F72: 19850.71 | G72: 17089.19 | H72: 22.8 | I72: 145.63 | J72: 2593.09 | K72: 2470.78 | L72: 87.91 | M72: 122.31 | N72: 40.42 | O72: =(K72-L72)+(M72-N72) -> 2464.76 | P72: =SUM(G72,H72,I72,O72) -> 19722.38
A73: Aug 25 - Aug 31 2025 | B73: 22023.84 | C73: =(B73*0.06)*1.13 -> 1493.2164 | D73: =(B73*0.02)*1.13 -> 497.73878 | E73: 862 | F73: 22176.92 | G73: 19647.22 | H73: 0 | I73: 52.8 | J73: 2476.9 | K73: 2387.77 | L73: 142.22 | M73: 89.13 | N73: 10.86 | O73: =(K73-L73)+(M73-N73) -> 2323.82 | P73: =SUM(G73,H73,I73,O73) -> 22023.84
A74: Sep 01 - Sep 07 2025 | B74: 11468.06 | C74: =(B74*0.06)*1.13 -> 777.53447 | D74: =(B74*0.02)*1.13 -> 259.17816 | E74: 391 | F74: 11550.05 | G74: 9266.1 | H74: 26.4 | I74: 229.45 | J74: 2028.1 | K74: 1917.76 | L74: 60.26 | M74: 110.34 | N74: 21.73 | O74: =(K74-L74)+(M74-N74) -> 1946.11 | P74: =SUM(G74,H74,I74,O74) -> 11468.06
A75: Sep 08 - Sep 14 2025 | B75: 12290.23 | C75: =(B75*0.06)*1.13 -> 833.27759 | D75: =(B75*0.02)*1.13 -> 277.7592 | E75: 452 | F75: 12373.21 | G75: 9454.77 | H75: 18 | I75: 259.01 | J75: 2641.43 | K75: 2641.43 | L75: 122.45 | M75: 55.77 | N75: 16.3 | O75: =(K75-L75)+(M75-N75) -> 2558.45 | P75: =SUM(G75,H75,I75,O75) -> 12290.23
A76: Sep 15 - Sep 21 2025 | B76: 8507.11 | C76: =(B76*0.06)*1.13 -> 576.78206 | D76: =(B76*0.02)*1.13 -> 192.26069 | E76: 335 | F76: 8512.53 | G76: 6620.89 | H76: 26.4 | I76: 106.06 | J76: 1759.18 | K76: 1810.78 | L76: 94.24 | M76: 48.56 | N76: 11.34 | O76: =(K76-L76)+(M76-N76) -> 1753.76 | P76: =SUM(G76,H76,I76,O76) -> 8507.11
A77: Sep 22 - Sep 28 2025 | B77: 10453.18 | C77: =(B77*0.06)*1.13 -> 708.7256 | D77: =(B77*0.02)*1.13 -> 236.24187 | E77: 390 | F77: 10566.69 | G77: 7952.51 | H77: 24.29 | I77: 96.69 | J77: 2493.2 | K77: 2430.84 | L77: 115.92 | M77: 81.54 | N77: 16.77 | O77: =(K77-L77)+(M77-N77) -> 2379.69 | P77: =SUM(G77,H77,I77,O77) -> 10453.18
A78: Sep 29 - Oct 05 2025 | B78: 9956.32 | C78: =(B78*0.06)*1.13 -> 675.0385 | D78: =(B78*0.02)*1.13 -> 225.01283 | E78: 404 | F78: 9897.83 | G78: 7642.19 | H78: 27.6 | I78: 320.86 | J78: 1907.18 | K78: 1983.32 | L78: 17.65 | M78: 0 | N78: 0 | O78: =(K78-L78)+(M78-N78) -> 1965.67 | P78: =SUM(G78,H78,I78,O78) -> 9956.32
A79: Oct 6 - Oct 12 2025 | B79: 11492.36 | C79: =(B79*0.06)*1.13 -> 779.18201 | D79: =(B79*0.02)*1.13 -> 259.72734 | E79: 448 | F79: 11396.56 | G79: 9153.5 | H79: 198.59 | I79: 151.37 | J79: 1893.1 | K79: 1988.9 | L79: 0 | M79: 0 | N79: 0 | O79: =(K79-L79)+(M79-N79) -> 1988.9 | P79: =SUM(G79,H79,I79,O79) -> 11492.36
A80: Oct 13 - Oct 19 2025 | B80: 12660.06 | C80: =(B80*0.06)*1.13 -> 858.35207 | D80: =(B80*0.02)*1.13 -> 286.11736 | F80: 12633.66 | G80: 10151.39 | H80: 58.8 | I80: 134.73 | J80: 2288.74 | K80: 2315.14 | L80: 0 | M80: 0 | N80: 0 | O80: =(K80-L80)+(M80-N80) -> 2315.14 | P80: =SUM(G80,H80,I80,O80) -> 12660.06
A81: Oct 20 - Oct 26 2025 | B81: 11775.34 | C81: =(B81*0.06)*1.13 -> 798.36805 | D81: =(B81*0.02)*1.13 -> 266.12268 | F81: 11741.34 | G81: 9570.55 | H81: 47.99 | I81: 176.47 | J81: 1946.33 | K81: 1980.33 | L81: 0 | M81: 0 | N81: 0 | O81: =(K81-L81)+(M81-N81) -> 1980.33 | P81: =SUM(G81,H81,I81,O81) -> 11775.34
A82: Oct 27 - Nov 02 2025 | B82: 12776.83 | C82: =(B82*0.06)*1.13 -> 866.26907 | D82: =(B82*0.02)*1.13 -> 288.75636 | E82: 441 | F82: 12727.63 | G82: 10607.79 | H82: 103.54 | I82: 45.58 | J82: 1970.72 | K82: 1971.36 | L82: 0 | M82: 48.56 | N82: 0 | O82: =(K82-L82)+(M82-N82) -> 2019.92 | P82: =SUM(G82,H82,I82,O82) -> 12776.83
A83: Nov 03 - Nov 09 2025 | B83: 10311.84 | C83: =(B83*0.06)*1.13 -> 699.14275 | D83: =(B83*0.02)*1.13 -> 233.04758 | E83: 336 | F83: 10336.24 | G83: 6799.22 | H83: 67.2 | I83: 81.64 | J83: 3388.18 | K83: 3363.78 | L83: 0 | M83: 0 | N83: 0 | O83: =(K83-L83)+(M83-N83) -> 3363.78 | P83: =SUM(G83,H83,I83,O83) -> 10311.84
A84: Nov 10 - Nov 16 2025 | B84: 9167.09 | C84: =(B84*0.06)*1.13 -> 621.5287 | D84: =(B84*0.02)*1.13 -> 207.17623 | E84: 306 | F84: 9167.09 | G84: 6595.57 | H84: 99.88 | I84: 122.38 | J84: 2349.26 | K84: 2325.28 | L84: 0 | M84: 23.98 | N84: 0 | O84: =(K84-L84)+(M84-N84) -> 2349.26 | P84: =SUM(G84,H84,I84,O84) -> 9167.09
A85: Nov 17 - Nov 23 2025 | B85: 10724.92 | C85: =(B85*0.06)*1.13 -> 727.14958 | D85: =(B85*0.02)*1.13 -> 242.38319 | E85: 368 | F85: 10820.8 | G85: 8469.63 | H85: 91.6 | I85: 125.39 | J85: 2134.18 | K85: 2134.18 | L85: 95.88 | M85: 0 | N85: 0 | O85: =(K85-L85)+(M85-N85) -> 2038.3 | P85: =SUM(G85,H85,I85,O85) -> 10724.92
A86: Nov 24 - Nov 30 2025 | B86: 10630.86 | C86: =(B86*0.06)*1.13 -> 720.77231 | D86: =(B86*0.02)*1.13 -> 240.25744 | E86: 382 | F86: 10725.94 | G86: 7644.15 | H86: 78.39 | I86: 185.93 | J86: 2817.47 | K86: 2819.47 | L86: 97.08 | M86: 0 | N86: 0 | O86: =(K86-L86)+(M86-N86) -> 2722.39 | P86: =SUM(G86,H86,I86,O86) -> 10630.86
A87: Dec 01 - Dec 07 2025 | B87: 10691.56 | C87: =(B87*0.06)*1.13 -> 724.88777 | D87: =(B87*0.02)*1.13 -> 241.62926 | E87: 361 | F87: 11000.2 | G87: 6631.19 | H87: 24.3 | I87: 259.04 | J87: 4085.67 | K87: 4085.67 | L87: 308.64 | M87: 0 | N87: 0 | O87: =(K87-L87)+(M87-N87) -> 3777.03 | P87: =SUM(G87,H87,I87,O87) -> 10691.56
A88: Dec 08 - Dec 14 2025 | B88: 9321.37 | C88: =(B88*0.06)*1.13 -> 631.98889 | D88: =(B88*0.02)*1.13 -> 210.66296 | E88: 338 | F88: 9581.05 | G88: 6152.9 | H88: 42.21 | I88: 159.43 | J88: 3226.51 | K88: 3194.13 | L88: 259.68 | M88: 32.38 | N88: 0 | O88: =(K88-L88)+(M88-N88) -> 2966.83 | P88: =SUM(G88,H88,I88,O88) -> 9321.37
A89: Dec 15 - Dec 21 2025 | B89: 11135.48 | C89: =(B89*0.06)*1.13 -> 754.98554 | D89: =(B89*0.02)*1.13 -> 251.66185 | E89: 385 | F89: 11518.17 | G89: 7247.33 | H89: 76 | I89: 171.26 | J89: 4023.58 | K89: 4012.21 | L89: 440.67 | M89: 69.35 | N89: 0 | O89: =(K89-L89)+(M89-N89) -> 3640.89 | P89: =SUM(G89,H89,I89,O89) -> 11135.48
A90: Dec 22 - Dec 28 2025 | B90: 12397.21 | C90: =(B90*0.06)*1.13 -> 840.53084 | D90: =(B90*0.02)*1.13 -> 280.17695 | E90: 376 | F90: 12664.69 | G90: 9057.71 | H90: 165.78 | I90: 145.17 | J90: 3296.03 | K90: 3296.03 | L90: 295.05 | M90: 27.57 | N90: 0 | O90: =(K90-L90)+(M90-N90) -> 3028.55 | P90: =SUM(G90,H90,I90,O90) -> 12397.21
A91: Dec 29 - Jan 04 2026 | B91: 13573.15 | C91: =(B91*0.06)*1.13 -> 920.25957 | D91: =(B91*0.02)*1.13 -> 306.75319 | E91: 400 | F91: 14098.07 | G91: 9346 | H91: 54.29 | I91: 498.75 | J91: 4199.03 | K91: 4181.5 | L91: 507.39 | M91: 0 | N91: 0 | O91: =(K91-L91)+(M91-N91) -> 3674.11 | P91: =SUM(G91,H91,I91,O91) -> 13573.15
A92: Jan 05 - Jan 11 2026 | B92: 8906.77 | C92: =(B92*0.06)*1.13 -> 603.87901 | D92: =(B92*0.02)*1.13 -> 201.293 | E92: 322 | F92: 9183.79 | G92: 5791.15 | H92: 52.8 | I92: 177.15 | J92: 3162.69 | K92: 3208.89 | L92: 323.22 | M92: 0 | N92: 0 | O92: =(K92-L92)+(M92-N92) -> 2885.67 | P92: =SUM(G92,H92,I92,O92) -> 8906.77
A93: Jan 12 - Jan 18 2026 | B93: 9483.84 | C93: =(B93*0.06)*1.13 -> 643.00435 | D93: =(B93*0.02)*1.13 -> 214.33478 | E93: 301 | F93: 9941.61 | G93: 5523.61 | H93: 26.4 | I93: 82.78 | J93: 4308.82 | K93: 4269.94 | L93: 483.64 | M93: 64.75 | N93: 0 | O93: =(K93-L93)+(M93-N93) -> 3851.05 | P93: =SUM(G93,H93,I93,O93) -> 9483.84
A94: Jan 19 - Jan 25 2026 | B94: 9469.42 | C94: =(B94*0.06)*1.13 -> 642.02668 | D94: =(B94*0.02)*1.13 -> 214.00889 | E94: 323 | F94: 9949.43 | G94: 5760.51 | H94: 84 | I94: 191.33 | J94: 3913.59 | K94: 3915.59 | L94: 482.01 | M94: 0 | N94: 0 | O94: =(K94-L94)+(M94-N94) -> 3433.58 | P94: =SUM(G94,H94,I94,O94) -> 9469.42
A95: Jan 26 - Feb 01 2026 | B95: 10309.22 | C95: =(B95*0.06)*1.13 -> 698.96512 | D95: =(B95*0.02)*1.13 -> 232.98837 | E95: 291 | F95: 10571.41 | G95: 6728.87 | H95: 186.48 | I95: 198.47 | J95: 3457.59 | K95: 3571.96 | L95: 376.56 | M95: 0 | N95: 0 | O95: =(K95-L95)+(M95-N95) -> 3195.4 | P95: =SUM(G95,H95,I95,O95) -> 10309.22
A96: Feb 02 - Feb 08 2026 | B96: 10151.82 | C96: =(B96*0.06)*1.13 -> 688.2934 | D96: =(B96*0.02)*1.13 -> 229.43113 | E96: 350 | F96: 10485.17 | G96: 6839.92 | H96: 16 | I96: 196.79 | J96: 3432.46 | K96: 3213.39 | L96: 302.4 | M96: 303.4 | N96: 115.28 | O96: =(K96-L96)+(M96-N96) -> 3099.11 | P96: =SUM(G96,H96,I96,O96) -> 10151.82
A97: Feb 09 - Feb 15 2026 | B97: 11865.48 | C97: =(B97*0.06)*1.13 -> 804.47954 | D97: =(B97*0.02)*1.13 -> 268.15985 | E97: 401 | F97: 12249.99 | G97: 8167.65 | H97: 64.9 | I97: 183.09 | J97: 3834.35 | K97: 3884.08 | L97: 501.82 | M97: 98.34 | N97: 30.76 | O97: =(K97-L97)+(M97-N97) -> 3449.84 | P97: =SUM(G97,H97,I97,O97) -> 11865.48
A98: Feb 16 - Feb 22 2026 | B98: 7301.7 | C98: =(B98*0.06)*1.13 -> 495.05526 | D98: =(B98*0.02)*1.13 -> 165.01842 | E98: 264 | F98: 7692.39 | G98: 4703.17 | H98: 26.4 | I98: 34.67 | J98: 2928.15 | K98: 2753.49 | L98: 355 | M98: 228.66 | N98: 89.69 | O98: =(K98-L98)+(M98-N98) -> 2537.46 | P98: =SUM(G98,H98,I98,O98) -> 7301.7
A99: Feb 23 - Mar 1 2026 | B99: 9621.79 | C99: =(B99*0.06)*1.13 -> 652.35736 | D99: =(B99*0.02)*1.13 -> 217.45245 | E99: 331 | F99: 9985.73 | G99: 6044.16 | H99: 151.16 | I99: 186.41 | J99: 3604 | K99: 3546.44 | L99: 371.55 | M99: 95.93 | N99: 30.76 | O99: =(K99-L99)+(M99-N99) -> 3240.06 | P99: =SUM(G99,H99,I99,O99) -> 9621.79
A100: Mar 02 - Mar 08 2026 | B100: 9564.93 | C100: =(B100*0.06)*1.13 -> 648.50225 | D100: =(B100*0.02)*1.13 -> 216.16742 | E100: 290 | F100: 9970.83 | G100: 6076.89 | H100: 99.47 | I100: 337.21 | J100: 3457.26 | K100: 3358.81 | L100: 451.44 | M100: 234.67 | N100: 90.68 | O100: =(K100-L100)+(M100-N100) -> 3051.36 | P100: =SUM(G100,H100,I100,O100) -> 9564.93
A101: Mar 09 - Mar 15 2026 | B101: 9468.79 | C101: =(B101*0.06)*1.13 -> 641.98396 | D101: =(B101*0.02)*1.13 -> 213.99465 | E101: 278 | F101: 9838.09 | G101: 5570.43 | H101: 55.79 | I101: 239.63 | J101: 3972.24 | K101: 3866.72 | L101: 366.97 | M101: 165.51 | N101: 62.32 | O101: =(K101-L101)+(M101-N101) -> 3602.94 | P101: =SUM(G101,H101,I101,O101) -> 9468.79
A102: Mar 16 - Mar 22 2026 | B102: 11279.79 | C102: =(B102*0.06)*1.13 -> 764.76976 | D102: =(B102*0.02)*1.13 -> 254.92325 | E102: 317 | F102: 11664.97 | G102: 7661.62 | H102: 116.44 | I102: 85.2 | J102: 3801.71 | K102: 3619.79 | L102: 292.65 | M102: 151.52 | N102: 62.13 | O102: =(K102-L102)+(M102-N102) -> 3416.53 | P102: =SUM(G102,H102,I102,O102) -> 11279.79
... A107: Apr 20 - Apr 26 | B107: 12617.9 | C107: =(B107*0.06)*1.13 -> 855.49362 | D107: =(B107*0.02)*1.13 -> 285.16454 | E107: 398 | F107: 13167.54 | G107: 8609.43 | H107: 84.1 | I107: 244.21 | J107: 4229.8 | K107: 3821.64 | L107: 408.6 | M107: 444.53 | N107: 177.41 | O107: =(K107-L107)+(M107-N107) -> 3680.16 | P107: =SUM(G107,H107,I107,O107) -> 12617.9
A108: Apr 27 - May 03 | B108: 12032.49 | C108: =(B108*0.06)*1.13 -> 815.80282 | D108: =(B108*0.02)*1.13 -> 271.93427 | E108: 417 | F108: 12216.61 | G108: 8287.74 | H108: 102.3 | I108: 155.88 | J108: 3670.69 | K108: $3,590.74 | L108: $191.13 | M108: $133.90 | N108: $46.94 | O108: =(K108-L108)+(M108-N108) -> 3486.57 | P108: =SUM(G108,H108,I108,O108) -> 12032.49
...

Sheet Ajax
A1: Ajax
A2: Statement For Selected Period | B2: Total Revenue (Net Sales) | C2: Royalties (6%) | D2: Marketing (2%)
A3: Sep 23 - Sep 29 2024 | B3: 4033.49 | C3: =(B3*0.06)*1.13 -> 273.47062 | D3: =(B3*0.02)*1.13 -> 91.156874
A4: Sep 30 - Oct 06 2024 | B4: 9597.76 | C4: =(B4*0.06)*1.13 -> 650.72813 | D4: =(B4*0.02)*1.13 -> 216.90938
A5: Oct 07 - Oct 13 2024 | B5: 11281.14 | C5: =(B5*0.06)*1.13 -> 764.86129 | D5: =(B5*0.02)*1.13 -> 254.95376
A6: Oct 14 - Oct 20 2024 | B6: 11483.19 | C6: =(B6*0.06)*1.13 -> 778.56028 | D6: =(B6*0.02)*1.13 -> 259.52009
A7: Oct 21 - Oct 27 2024 | B7: 11478.83 | C7: =(B7*0.06)*1.13 -> 778.26467 | D7: =(B7*0.02)*1.13 -> 259.42156
A8: Oct 28 - Nov 03 2024 | B8: 9937.88 | C8: =(B8*0.06)*1.13 -> 673.78826 | D8: =(B8*0.02)*1.13 -> 224.59609
A9: Nov 4 - Nov 10 2024 | B9: 10406.88 | C9: =(B9*0.06)*1.13 -> 705.58646 | D9: =(B9*0.02)*1.13 -> 235.19549
A10: Nov 11 - Nov 17 2024 | B10: 9061.93 | C10: =(B10*0.06)*1.13 -> 614.39885 | D10: =(B10*0.02)*1.13 -> 204.79962
A11: Nov 18 - Nov 24 2024 | B11: 9513.59 | C11: =(B11*0.06)*1.13 -> 645.0214 | D11: =(B11*0.02)*1.13 -> 215.00713
A12: Nov 25 - Dec 01 2024 | B12: 9365.94 | C12: =(B12*0.06)*1.13 -> 635.01073 | D12: =(B12*0.02)*1.13 -> 211.67024
A13: Dec 02 - Dec 08 2024 | B13: 9682.96 | C13: =(B13*0.06)*1.13 -> 656.50469 | D13: =(B13*0.02)*1.13 -> 218.8349
A14: Dec 09 - Dec 15 2024 | B14: 11096.12 | C14: =(B14*0.06)*1.13 -> 752.31694 | D14: =(B14*0.02)*1.13 -> 250.77231
A15: Dec 16 - Dec 22 2024 | B15: 10054.79 | C15: =(B15*0.06)*1.13 -> 681.71476 | D15: =(B15*0.02)*1.13 -> 227.23825 | E15: Bill Count | F15: TB Revenue | G15: In-Store | H15: Skip | I15: DD | J15: Uber | K15: Uber Earnings | L15: Uber Marketing | O15: Uber (Total) | P15: Total
A16: Dec 23 - Dec 29 2024 | B16: 15668 | C16: =(B16*0.06)*1.13 -> 1062.2904 | D16: =(B16*0.02)*1.13 -> 354.0968 | G16: 11263.41 | H16: 268.17 | I16: 521.25 | J16: 3615.17
A17: Dec 30 - Jan 05 2025 | B17: 13399.51 | C17: =(B17*0.06)*1.13 -> 908.48678 | D17: =(B17*0.02)*1.13 -> 302.82893 | G17: 9069.76 | H17: 330.15 | I17: 532.78 | J17: 3466.82
A18: Jan 06 - Jan 12 2025 | B18: 9836.76 | C18: =(B18*0.06)*1.13 -> 666.93233 | D18: =(B18*0.02)*1.13 -> 222.31078
A19: Jan 13 - Jan 19 2025 | B19: 9635.01 | C19: =(B19*0.06)*1.13 -> 653.25368 | D19: =(B19*0.02)*1.13 -> 217.75123 | G19: 6684.79 | H19: 284.67 | I19: 358.98 | J19: 2306.57 | O19: 2262 | P19: =SUM(G19:J19) -> 9635.01
A20: Jan 20 - Jan 26 2025 | B20: 10717.23 | C20: =(B20*0.06)*1.13 -> 726.62819 | D20: =(B20*0.02)*1.13 -> 242.2094 | G20: 7891.66 | H20: 394.28 | I20: 355.14 | J20: 2076.15 | O20: 2116.95 | P20: =SUM(G20:J20) -> 10717.23
A21: Jan 27 - Feb 02 2025 | B21: 10695.63 | C21: =(B21*0.06)*1.13 -> 725.16371 | D21: =(B21*0.02)*1.13 -> 241.72124
A22: Feb 03 - Feb 09 2025 | B22: 10607.6 | C22: =(B22*0.06)*1.13 -> 719.19528 | D22: =(B22*0.02)*1.13 -> 239.73176 | F22: 10609.82 | G22: 7389.99 | H22: 278.97 | I22: 407.38 | J22: 2533.48 | K22: 2535.48 | L22: 4.22 | O22: =(K22-L22) -> 2531.26 | P22: =SUM(G22,H22,I22,O22) -> 10607.6
A23: Feb 10 - Feb 16 2025 | B23: 9317.92 | C23: =(B23*0.06)*1.13 -> 631.75498 | D23: =(B23*0.02)*1.13 -> 210.58499 | F23: 9317.92 | G23: 7103.86 | H23: 226.8 | I23: 546.81 | J23: 1440.45 | K23: 1440.45 | L23: 0 | O23: =(K23-L23) -> 1440.45 | P23: =SUM(G23,H23,I23,O23) -> 9317.92
A24: Feb 17 - Feb 23 2025 | B24: 12389.36 | C24: =(B24*0.06)*1.13 -> 839.99861 | D24: =(B24*0.02)*1.13 -> 279.99954 | F24: 12885.05 | G24: 9549.8 | H24: 105.6 | I24: 590.81 | J24: 2638.84 | K24: 2638.84 | L24: 495.69 | O24: =(K24-L24) -> 2143.15 | P24: =SUM(G24,H24,I24,O24) -> 12389.36
A25: Feb 24 - Mar 02 2025 | B25: 9107.42 | C25: =(B25*0.06)*1.13 -> 617.48308 | D25: =(B25*0.02)*1.13 -> 205.82769 | F25: 9312.86 | G25: 6193.36 | H25: 184.66 | I25: 278.48 | J25: 2656.36 | K25: 2745.46 | L25: 294.54 | O25: =(K25-L25) -> 2450.92 | P25: =SUM(G25,H25,I25,O25) -> 9107.42
A26: Mar 03 - Mar 09 2025 | B26: 9346.16 | C26: =(B26*0.06)*1.13 -> 633.66965 | D26: =(B26*0.02)*1.13 -> 211.22322 | F26: 9676.14 | G26: 6082.76 | H26: 128.39 | I26: 259.05 | J26: 3205.94 | K26: 3205.94 | L26: 329.98 | O26: =(K26-L26) -> 2875.96 | P26: =SUM(G26,H26,I26,O26) -> 9346.16
A27: Mar 10 - Mar 16 2025 | B27: 9881.08 | C27: =(B27*0.06)*1.13 -> 669.93722 | D27: =(B27*0.02)*1.13 -> 223.31241 | F27: 10463.53 | G27: 6271.89 | H27: 187.23 | I27: 162.27 | J27: 3842.14 | K27: 3788.14 | L27: 528.45 | O27: =(K27-L27) -> 3259.69 | P27: =SUM(G27,H27,I27,O27) -> 9881.08
A28: Mar 17 - Mar 23 2025 | B28: 9422.94 | C28: =(B28*0.06)*1.13 -> 638.87533 | D28: =(B28*0.02)*1.13 -> 212.95844 | F28: 10033 | G28: 5689.23 | H28: 227.57 | I28: 240.99 | J28: 3875.21 | K28: 3875.21 | L28: 610.06 | O28: =(K28-L28) -> 3265.15 | P28: =SUM(G28,H28,I28,O28) -> 9422.94
A29: Mar 24 - Mar 30 2025 | B29: 12856.63 | C29: =(B29*0.06)*1.13 -> 871.67951 | D29: =(B29*0.02)*1.13 -> 290.55984 | F29: 13331.58 | G29: 8429.27 | H29: 233.38 | I29: 200.17 | J29: 4468.76 | K29: 4496.36 | L29: 502.55 | O29: =(K29-L29) -> 3993.81 | P29: =SUM(G29,H29,I29,O29) -> 12856.63
A30: Mar 31 - Apr 6 2025 | B30: 13777.58 | C30: =(B30*0.06)*1.13 -> 934.11992 | D30: =(B30*0.02)*1.13 -> 311.37331 | F30: 13817.12 | G30: 10277.94 | H30: 176.09 | I30: 345.17 | J30: 3017.92 | K30: 3047.92 | L30: 69.54 | O30: =(K30-L30) -> 2978.38 | P30: =SUM(G30,H30,I30,O30) -> 13777.58
A31: Apr 7 - Apr 13 2025 | B31: 11168.82 | C31: =(B31*0.06)*1.13 -> 757.246 | D31: =(B31*0.02)*1.13 -> 252.41533 | F31: 11390.74 | G31: 7525.76 | H31: 115.58 | I31: 402.91 | K31: 3346.49 | L31: 221.92 | O31: =(K31-L31) -> 3124.57 | P31: =SUM(G31,H31,I31,O31) -> 11168.82
A32: Apr 14 - Apr 20 2025 | B32: 15131.23 | C32: =(B32*0.06)*1.13 -> 1025.8974 | D32: =(B32*0.02)*1.13 -> 341.9658 | G32: 10454.27 | H32: 413.06 | I32: 446.92 | J32: 4077.93 | K32: 4041.93 | L32: 224.95 | O32: =(K32-L32) -> 3816.98 | P32: =SUM(G32,H32,I32,O32) -> 15131.23
A33: Apr 21 - Apr 27 2025 | B33: 12922.11 | C33: =(B33*0.06)*1.13 -> 876.11906 | D33: =(B33*0.02)*1.13 -> 292.03969 | F33: 13129.61 | G33: 8421.13 | H33: 399.99 | I33: 285.49 | J33: 4023 | K33: 4059 | L33: 243.5 | O33: =(K33-L33) -> 3815.5 | P33: =SUM(G33,H33,I33,O33) -> 12922.11
A34: Apr 28 - May 04 2025 | B34: 12067.53 | C34: =(B34*0.06)*1.13 -> 818.17853 | D34: =(B34*0.02)*1.13 -> 272.72618 | G34: 7781.83 | H34: 238.34 | I34: 235.35 | J34: 4046.66 | K34: 4046.66 | L34: 234.65 | O34: =(K34-L34) -> 3812.01 | P34: =SUM(G34,H34,I34,O34) -> 12067.53
A35: May 05 - May 11 2025 | B35: 11958.73 | C35: =(B35*0.06)*1.13 -> 810.80189 | D35: =(B35*0.02)*1.13 -> 270.2673 | F35: 12101.05 | G35: 7982.31 | H35: 198.57 | I35: 318.96 | J35: 3601.21 | K35: 3686.41 | L35: 227.52 | O35: =(K35-L35) -> 3458.89 | P35: =SUM(G35,H35,I35,O35) -> 11958.73
A36: May 12 - May 18 2025 | B36: 11178.71 | C36: =(B36*0.06)*1.13 -> 757.91654 | D36: =(B36*0.02)*1.13 -> 252.63885 | F36: 11438.46 | G36: 8405.86 | H36: 78.4 | I36: 136.06 | J36: 2818.14 | K36: 2746.14 | L36: 187.75 | O36: =(K36-L36) -> 2558.39 | P36: =SUM(G36,H36,I36,O36) -> 11178.71
A37: May 19 - May 25 2025 | B37: 12467.05 | C37: =(B37*0.06)*1.13 -> 845.26599 | D37: =(B37*0.02)*1.13 -> 281.75533 | F37: 12590.84 | G37: 8994.09 | H37: 184.39 | I37: 327.44 | J37: 3084.92 | K37: 3110.13 | L37: 149 | O37: =(K37-L37) -> 2961.13 | P37: =SUM(G37,H37,I37,O37) -> 12467.05
A38: May 26 - June 01 2025 | B38: 11331.89 | C38: =(B38*0.06)*1.13 -> 768.30214 | D38: =(B38*0.02)*1.13 -> 256.10071 | F38: 11570.02 | G38: 7507.73 | H38: 226.8 | I38: 244.58 | J38: 3590.91 | K38: 3592.91 | L38: 240.13 | O38: =(K38-L38) -> 3352.78 | P38: =SUM(G38,H38,I38,O38) -> 11331.89
A39: June 02 - June 08 2025 | B39: 13019.08 | C39: =(B39*0.06)*1.13 -> 882.69362 | D39: =(B39*0.02)*1.13 -> 294.23121 | F39: 13101.38 | G39: 9587.9 | H39: 96.4 | I39: 373.06 | J39: 3044.02 | K39: 3101.91 | L39: 140.19 | O39: =(K39-L39) -> 2961.72 | P39: =SUM(G39,H39,I39,O39) -> 13019.08
A40: June 09 - June 15 2025 | B40: 10681.11 | C40: =(B40*0.06)*1.13 -> 724.17926 | D40: =(B40*0.02)*1.13 -> 241.39309 | F40: 10858.39 | G40: 7482.18 | H40: 146.78 | I40: 419.77 | J40: 2809.66 | K40: 2809.66 | L40: 177.28 | O40: =(K40-L40) -> 2632.38 | P40: =SUM(G40,H40,I40,O40) -> 10681.11
A41: June 16 - June 22 2025 | B41: 11249.78 | C41: =(B41*0.06)*1.13 -> 762.73508 | D41: =(B41*0.02)*1.13 -> 254.24503 | F41: 11400.54 | G41: 7844.48 | H41: 110.19 | I41: 328.66 | J41: 3117.21 | K41: 3117.21 | L41: 150.76 | O41: =(K41-L41) -> 2966.45 | P41: =SUM(G41,H41,I41,O41) -> 11249.78
A42: June 23 - June 29 2025 | B42: 13709.57 | C42: =(B42*0.06)*1.13 -> 929.50885 | D42: =(B42*0.02)*1.13 -> 309.83628 | F42: 13915.71 | G42: 8994.12 | H42: 161.96 | I42: 317.34 | J42: 4442.29 | K42: 4479.49 | L42: 243.34 | O42: =(K42-L42) -> 4236.15 | P42: =SUM(G42,H42,I42,O42) -> 13709.57
A43: June 30 - July 06 2025 | B43: 13468.59 | C43: =(B43*0.06)*1.13 -> 913.1704 | D43: =(B43*0.02)*1.13 -> 304.39013 | F43: 13482.63 | G43: 9758.26 | H43: 268.72 | I43: 373.7 | J43: 3081.95 | K43: 3128.75 | L43: 60.84 | O43: =(K43-L43) -> 3067.91 | P43: =SUM(G43,H43,I43,O43) -> 13468.59
A44: July 07 - July 13 2025 | B44: 12349.7 | C44: =(B44*0.06)*1.13 -> 837.30966 | D44: =(B44*0.02)*1.13 -> 279.10322 | F44: 12487.84 | G44: 9345.85 | H44: 253.6 | I44: 215.56 | J44: 2672.83 | K44: 2649.24 | L44: 114.55 | O44: =(K44-L44) -> 2534.69 | P44: =SUM(G44,H44,I44,O44) -> 12349.7
A45: July 14 - July 20 2025 | B45: 11301.77 | C45: =(B45*0.06)*1.13 -> 766.26001 | D45: =(B45*0.02)*1.13 -> 255.42 | E45: 347 | F45: 11386.27 | G45: 8192.31 | H45: 82.79 | I45: 301.33 | J45: 2809.84 | K45: 2855.04 | L45: 129.7 | O45: =(K45-L45) -> 2725.34 | P45: =SUM(G45,H45,I45,O45) -> 11301.77
A46: July 21 - July 27 2025 | B46: 11360.85 | C46: =(B46*0.06)*1.13 -> 770.26563 | D46: =(B46*0.02)*1.13 -> 256.75521 | E46: 387 | F46: 11523.8 | G46: 7616.6 | H46: 111.6 | I46: 227.77 | J46: 3567.83 | K46: 3600.23 | L46: 195.35 | O46: =(K46-L46) -> 3404.88 | P46: =SUM(G46,H46,I46,O46) -> 11360.85
A47: July 28 - Aug 03 2025 | B47: 12208.62 | C47: =(B47*0.06)*1.13 -> 827.74444 | D47: =(B47*0.02)*1.13 -> 275.91481 | E47: 416 | F47: 12428.02 | G47: 8916.28 | H47: 61.19 | I47: 244.35 | J47: 3206.2 | K47: 3188.7 | L47: 201.9 | O47: =(K47-L47) -> 2986.8 | P47: =SUM(G47,H47,I47,O47) -> 12208.62
A48: Aug 04 - Aug 10 2025 | B48: 12620.56 | C48: =(B48*0.06)*1.13 -> 855.67397 | D48: =(B48*0.02)*1.13 -> 285.22466 | E48: 471 | F48: 12848.5 | G48: 9392.17 | H48: 84.94 | I48: 198.26 | J48: 3173.13 | K48: 3070.86 | L48: 125.67 | O48: =(K48-L48) -> 2945.19 | P48: =SUM(G48,H48,I48,O48) -> 12620.56
A49: Aug 11 - Aug 17 2025 | B49: 13911.98 | C49: =(B49*0.06)*1.13 -> 943.23224 | D49: =(B49*0.02)*1.13 -> 314.41075 | E49: 510 | F49: 13969.3 | G49: 10515.06 | H49: 41.2 | I49: 236.53 | J49: 3176.51 | K49: 3277.69 | L49: 158.5 | O49: =(K49-L49) -> 3119.19 | P49: =SUM(G49,H49,I49,O49) -> 13911.98
A50: Aug 18 - Aug 24 2025 | B50: 13665 | C50: =(B50*0.06)*1.13 -> 926.487 | D50: =(B50*0.02)*1.13 -> 308.829 | E50: 443 | F50: 13805.16 | G50: 8749.72 | H50: 232.19 | I50: 313.19 | J50: 4510.06 | K50: 4626.65 | L50: 256.75 | O50: =(K50-L50) -> 4369.9 | P50: =SUM(G50,H50,I50,O50) -> 13665
A51: Aug 25 - Aug 31 2025 | B51: 12849.65 | C51: =(B51*0.06)*1.13 -> 871.20627 | D51: =(B51*0.02)*1.13 -> 290.40209 | E51: 435 | F51: 13092.51 | G51: 8926.41 | H51: 240.59 | I51: 476.81 | J51: 3448.7 | K51: 3413.3 | L51: 207.46 | O51: =(K51-L51) -> 3205.84 | P51: =SUM(G51,H51,I51,O51) -> 12849.65
A52: Sep 01 - Sep 07 2025 | B52: 11568.72 | C52: =(B52*0.06)*1.13 -> 784.35922 | D52: =(B52*0.02)*1.13 -> 261.45307 | E52: 401 | F52: 11745.27 | G52: 8121.39 | H52: 243.03 | I52: 266.99 | J52: 3113.86 | K52: 3113.86 | L52: 176.55 | O52: =(K52-L52) -> 2937.31 | P52: =SUM(G52,H52,I52,O52) -> 11568.72
A53: Sep 08 - Sep 14 2025 | B53: 10450.63 | C53: =(B53*0.06)*1.13 -> 708.55271 | D53: =(B53*0.02)*1.13 -> 236.18424 | E53: 386 | F53: 10572.32 | G53: 7742.8 | H53: 52.79 | I53: 414.93 | J53: 2361.8 | K53: 2370.19 | L53: 130.08 | O53: =(K53-L53) -> 2240.11 | P53: =SUM(G53,H53,I53,O53) -> 10450.63
A54: Sep 15 - Sep 21 2025 | B54: 11429.22 | C54: =(B54*0.06)*1.13 -> 774.90112 | D54: =(B54*0.02)*1.13 -> 258.30037 | E54: 381 | F54: 11658.72 | G54: 7543.01 | H54: 238.89 | I54: 337.58 | J54: 3539.24 | K54: 3486.7 | L54: 176.96 | O54: =(K54-L54) -> 3309.74 | P54: =SUM(G54,H54,I54,O54) -> 11429.22
A55: Sep 22 - Sep 28 2025 | B55: 12826.56 | C55: =(B55*0.06)*1.13 -> 869.64077 | D55: =(B55*0.02)*1.13 -> 289.88026 | E55: 413 | F55: 12885.22 | G55: 8620.01 | H55: 230.69 | I55: 383.97 | J55: 3650.55 | K55: 3788.79 | L55: 196.9 | O55: =(K55-L55) -> 3591.89 | P55: =SUM(G55,H55,I55,O55) -> 12826.56
A56: Sep 29 - Oct 05 2025 | B56: 10581.15 | C56: =(B56*0.06)*1.13 -> 717.40197 | D56: =(B56*0.02)*1.13 -> 239.13399 | E56: 364 | F56: 10592.93 | G56: 7257.38 | H56: 121.5 | I56: 380.57 | J56: 2833.48 | K56: 2891.38 | L56: 69.68 | O56: =(K56-L56) -> 2821.7 | P56: =SUM(G56,H56,I56,O56) -> 10581.15
A57: Oct 6 - Oct 12 2025 | B57: 11089.2 | C57: =(B57*0.06)*1.13 -> 751.84776 | D57: =(B57*0.02)*1.13 -> 250.61592 | E57: 362 | F57: 11089.2 | G57: 8817.92 | H57: 36 | I57: 529.64 | J57: 1705.64 | K57: 1705.64 | L57: 0 | O57: =(K57-L57) -> 1705.64 | P57: =SUM(G57,H57,I57,O57) -> 11089.2
A58: Oct 13 - Oct 19 2025 | B58: 12209.31 | C58: =(B58*0.06)*1.13 -> 827.79122 | D58: =(B58*0.02)*1.13 -> 275.93041 | F58: 12237.08 | G58: 8992.1 | H58: 198 | I58: 397.59 | J58: 2649.39 | K58: 2621.62 | L58: 0 | O58: =(K58-L58) -> 2621.62 | P58: =SUM(G58,H58,I58,O58) -> 12209.31
A59: Oct 20 - Oct 26 2025 | B59: 10696.86 | C59: =(B59*0.06)*1.13 -> 725.24711 | D59: =(B59*0.02)*1.13 -> 241.74904 | F59: 10578.06 | G59: 7878.25 | H59: 106.79 | I59: 339.74 | J59: 2253.28 | K59: 2372.08 | L59: 0 | O59: =(K59-L59) -> 2372.08 | P59: =SUM(G59,H59,I59,O59) -> 10696.86
A60: Oct 27 - Nov 02 2025 | B60: 13574.07 | C60: =(B60*0.06)*1.13 -> 920.32195 | D60: =(B60*0.02)*1.13 -> 306.77398 | E60: 435 | F60: 13505.12 | G60: 9114.07 | H60: 208.78 | I60: 316.79 | J60: 3865.48 | K60: 3909.44 | L60: 0 | M60: 24.99 | N60: 0 | O60: =(K60-L60)+(M60-N60) -> 3934.43 | P60: =SUM(G60,H60,I60,O60) -> 13574.07
A61: Nov 03 - Nov 09 2025 | B61: 9919.73 | C61: =(B61*0.06)*1.13 -> 672.55769 | D61: =(B61*0.02)*1.13 -> 224.1859 | E61: 332 | F61: 9826.2 | G61: 6703.57 | H61: 376.55 | I61: 423.37 | J61: 2322.71 | K61: 2391.25 | L61: 0 | M61: 24.99 | N61: 0 | O61: =(K61-L61)+(M61-N61) -> 2416.24 | P61: =SUM(G61,H61,I61,O61) -> 9919.73
A62: Nov 10 - Nov 16 2025 | B62: 10293.43 | C62: =(B62*0.06)*1.13 -> 697.89455 | D62: =(B62*0.02)*1.13 -> 232.63152 | E62: 338 | F62: 10223.77 | G62: 7228.09 | H62: 209.55 | I62: 562.68 | J62: 2223.45 | K62: 2293.11 | L62: 0 | M62: 0 | N62: 0 | O62: =(K62-L62)+(M62-N62) -> 2293.11 | P62: =SUM(G62,H62,I62,O62) -> 10293.43
A63: Nov 17 - Nov 23 2025 | B63: 10456.45 | C63: =(B63*0.06)*1.13 -> 708.94731 | D63: =(B63*0.02)*1.13 -> 236.31577 | E63: 364 | F63: 10559.6 | G63: 7664.56 | H63: 210.48 | I63: 322.35 | J63: 2362.21 | K63: 2422.08 | L63: 163.02 | M63: 0 | N63: 0 | O63: =(K63-L63)+(M63-N63) -> 2259.06 | P63: =SUM(G63,H63,I63,O63) -> 10456.45
A64: Nov 24 - Nov 30 2025 | B64: 11747.29 | C64: =(B64*0.06)*1.13 -> 796.46626 | D64: =(B64*0.02)*1.13 -> 265.48875 | E64: 427 | F64: 11965.45 | G64: 8443.59 | H64: 205.09 | I64: 334.27 | J64: 2982.5 | K64: 2958.5 | L64: 194.16 | M64: 0 | N64: 0 | O64: =(K64-L64)+(M64-N64) -> 2764.34 | P64: =SUM(G64,H64,I64,O64) -> 11747.29
A65: Dec 01 - Dec 07 2025 | B65: 10414.41 | C65: =(B65*0.06)*1.13 -> 706.097 | D65: =(B65*0.02)*1.13 -> 235.36567 | E65: 354 | F65: 10538.43 | G65: 7191.91 | H65: 238.77 | I65: 319.2 | J65: 2788.55 | K65: 2812.55 | L65: 148.02 | M65: 0 | N65: 0 | O65: =(K65-L65)+(M65-N65) -> 2664.53 | P65: =SUM(G65,H65,I65,O65) -> 10414.41
A66: Dec 08 - Dec 14 2025 | B66: 8793 | C66: =(B66*0.06)*1.13 -> 596.1654 | D66: =(B66*0.02)*1.13 -> 198.7218 | E66: 340 | F66: 9132.06 | G66: 5423.94 | H66: 56.69 | I66: 343.8 | J66: 3307.63 | K66: 3306.44 | L66: 354.65 | M66: 16.78 | N66: 0 | O66: =(K66-L66)+(M66-N66) -> 2968.57 | P66: =SUM(G66,H66,I66,O66) -> 8793
A67: Dec 15 - Dec 21 2025 | B67: 10031.9 | C67: =(B67*0.06)*1.13 -> 680.16282 | D67: =(B67*0.02)*1.13 -> 226.72094 | E67: 342 | F67: 10394.72 | G67: 7228.19 | H67: 287.48 | I67: 367.69 | J67: 2511.36 | K67: 2475.36 | L67: 326.82 | M67: 0 | N67: 0 | O67: =(K67-L67)+(M67-N67) -> 2148.54 | P67: =SUM(G67,H67,I67,O67) -> 10031.9
A68: Dec 22 - Dec 28 2025 | B68: 12863.22 | C68: =(B68*0.06)*1.13 -> 872.12632 | D68: =(B68*0.02)*1.13 -> 290.70877 | E68: 405 | F68: 12852.93 | G68: 8913.5 | H68: 135.82 | I68: 202.3 | J68: 3601.31 | K68: 3675.92 | L68: 64.32 | M68: 0 | N68: 0 | O68: =(K68-L68)+(M68-N68) -> 3611.6 | P68: =SUM(G68,H68,I68,O68) -> 12863.22
A69: Dec 29 - Jan 04 2026 | B69: 12578.52 | C69: =(B69*0.06)*1.13 -> 852.82366 | D69: =(B69*0.02)*1.13 -> 284.27455 | E69: 385 | F69: 12810.18 | G69: 9079.56 | H69: 75.6 | I69: 141.6 | J69: 3513.42 | K69: 3566.22 | L69: 284.46 | M69: 0 | N69: 0 | O69: =(K69-L69)+(M69-N69) -> 3281.76 | P69: =SUM(G69,H69,I69,O69) -> 12578.52
A70: Jan 05 - Jan 11 2026 | B70: 8868.83 | C70: =(B70*0.06)*1.13 -> 601.30667 | D70: =(B70*0.02)*1.13 -> 200.43556 | E70: 310 | F70: 9128.11 | G70: 5883.24 | H70: 281.05 | I70: 172.07 | J70: 2791.75 | K70: 2818.54 | L70: 286.07 | M70: 0 | N70: 0 | O70: =(K70-L70)+(M70-N70) -> 2532.47 | P70: =SUM(G70,H70,I70,O70) -> 8868.83
A71: Jan 12 - Jan 18 2026 | B71: 9229.77 | C71: =(B71*0.06)*1.13 -> 625.77841 | D71: =(B71*0.02)*1.13 -> 208.5928 | E71: 319 | F71: 9305.44 | G71: 6888.94 | H71: 187.18 | I71: 275.5 | J71: 1953.82 | K71: 1989.81 | L71: 111.66 | M71: 0 | N71: 0 | O71: =(K71-L71)+(M71-N71) -> 1878.15 | P71: =SUM(G71,H71,I71,O71) -> 9229.77
A72: Jan 19 - Jan 25 2026 | B72: 7852.34 | C72: =(B72*0.06)*1.13 -> 532.38865 | D72: =(B72*0.02)*1.13 -> 177.46288 | E72: 280 | F72: 8084.09 | G72: 4874.67 | H72: 191.39 | I72: 174.4 | J72: 2843.63 | K72: 2791.47 | L72: 192.18 | M72: 12.59 | N72: 0 | O72: =(K72-L72)+(M72-N72) -> 2611.88 | P72: =SUM(G72,H72,I72,O72) -> 7852.34
A73: Jan 26 - Feb 01 2026 | B73: 9830.46 | C73: =(B73*0.06)*1.13 -> 666.50519 | D73: =(B73*0.02)*1.13 -> 222.1684 | E73: 310 | F73: 9998.38 | G73: 6859.64 | H73: 508.75 | I73: 310.27 | J73: 2319.72 | K73: 2419.9 | L73: 268.1 | M73: 0 | N73: 0 | O73: =(K73-L73)+(M73-N73) -> 2151.8 | P73: =SUM(G73,H73,I73,O73) -> 9830.46
A74: Feb 02 - Feb 08 2026 | B74: 9165.95 | C74: =(B74*0.06)*1.13 -> 621.45141 | D74: =(B74*0.02)*1.13 -> 207.15047 | E74: 325 | F74: 9231.47 | G74: 6603.93 | H74: 190.8 | I74: 171.33 | J74: 2265.41 | K74: 2265.41 | L74: 65.52 | M74: 0 | N74: 0 | O74: =(K74-L74)+(M74-N74) -> 2199.89 | P74: =SUM(G74,H74,I74,O74) -> 9165.95
A75: Feb 09 - Feb 15 2026 | B75: 11030.31 | C75: =(B75*0.06)*1.13 -> 747.85502 | D75: =(B75*0.02)*1.13 -> 249.28501 | E75: 355 | F75: 11125.16 | G75: 8156.99 | H75: 175.98 | I75: 384.06 | J75: 2408.13 | K75: 2405.13 | L75: 131.04 | M75: 56.17 | N75: 16.98 | O75: =(K75-L75)+(M75-N75) -> 2313.28 | P75: =SUM(G75,H75,I75,O75) -> 11030.31
A76: Feb 16 - Feb 22 2026 | B76: 8359.95 | C76: =(B76*0.06)*1.13 -> 566.80461 | D76: =(B76*0.02)*1.13 -> 188.93487 | E76: 285 | F76: 8579.51 | G76: 5611.71 | H76: 156.19 | I76: 171.9 | J76: 2639.71 | K76: 2599.73 | L76: 179.58 | M76: 0 | N76: 0 | O76: =(K76-L76)+(M76-N76) -> 2420.15 | P76: =SUM(G76,H76,I76,O76) -> 8359.95
A77: Feb 23 - Mar 1 2026 | B77: 8910.12 | C77: =(B77*0.06)*1.13 -> 604.10614 | D77: =(B77*0.02)*1.13 -> 201.36871 | E77: 317 | F77: 9120.43 | G77: 5696.3 | H77: 96.07 | I77: 702.15 | J77: 2625.91 | K77: 2689.29 | L77: 273.69 | M77: 0 | N77: 0 | O77: =(K77-L77)+(M77-N77) -> 2415.6 | P77: =SUM(G77,H77,I77,O77) -> 8910.12
A78: Mar 02 - Mar 08 2026 | B78: 8285.2 | C78: =(B78*0.06)*1.13 -> 561.73656 | D78: =(B78*0.02)*1.13 -> 187.24552 | E78: 302 | F78: 8559.67 | G78: 5569.37 | H78: 233.21 | I78: 538.9 | J78: 2218.19 | K78: 2218.19 | L78: 274.47 | M78: 0 | N78: 0 | O78: =(K78-L78)+(M78-N78) -> 1943.72 | P78: =SUM(G78,H78,I78,O78) -> 8285.2
A79: Mar 09 - Mar 15 2026 | B79: 9629.73 | C79: =(B79*0.06)*1.13 -> 652.89569 | D79: =(B79*0.02)*1.13 -> 217.6319 | E79: 316 | F79: 9796.41 | G79: 5952.67 | H79: 108.85 | I79: 384.14 | J79: 3350.75 | K79: 3509.69 | L79: 325.62 | M79: 0 | N79: 0 | O79: =(K79-L79)+(M79-N79) -> 3184.07 | P79: =SUM(G79,H79,I79,O79) -> 9629.73
A80: Mar 16 - Mar 22 2026 | B80: 11058.63 | C80: =(B80*0.06)*1.13 -> 749.77511 | D80: =(B80*0.02)*1.13 -> 249.92504 | E80: 349 | F80: 11351.4 | G80: 7770.23 | H80: 70.11 | I80: 330.16 | J80: 3180.9 | K80: 3197.19 | L80: 309.06 | M80: 0 | N80: 0 | O80: =(K80-L80)+(M80-N80) -> 2888.13 | P80: =SUM(G80,H80,I80,O80) -> 11058.63
... A85: Apr 20 - Apr 26 | B85: 7472.82 | C85: =(B85*0.06)*1.13 -> 506.6572 | D85: =(B85*0.02)*1.13 -> 168.88573 | E85: 267 | F85: 7626.34 | G85: 4612.74 | H85: 61.37 | I85: 378.76 | J85: 2573.47 | K85: 2615.52 | L85: 195.57 | M85: 0 | N85: 0 | O85: =(K85-L85)+(M85-N85) -> 2419.95 | P85: =SUM(G85,H85,I85,O85) -> 7472.82
A86: Apr 27 - May 03 | B86: 8601.07 | C86: =(B86*0.06)*1.13 -> 583.15255 | D86: =(B86*0.02)*1.13 -> 194.38418 | E86: 301 | F86: 8714.61 | G86: 5886.52 | H86: 143.13 | I86: 228.97 | J86: 2455.99 | K86: $2,474.69 | L86: $132.24 | M86: 0 | N86: 0 | O86: =(K86-L86)+(M86-N86) -> 2342.45 | P86: =SUM(G86,H86,I86,O86) -> 8601.07
A87: May 4 - May 10 | B87: 9769.83 | C87: =(B87*0.06)*1.13 -> 662.39447 | D87: =(B87*0.02)*1.13 -> 220.79816 | E87: 344 | F87: 9754.83 | G87: 7064.21 | H87: 26.38 | I87: 343.65 | J87: 2320.59 | K87: 2335.59 | L87: 0 | M87: 0 | N87: 0 | O87: =(K87-L87)+(M87-N87) -> 2335.59 | P87: =SUM(G87,H87,I87,O87) -> 9769.83
A88: May 11 - May 17 | B88: 8235.1 | C88: =(B88*0.06)*1.13 -> 558.33978 | D88: =(B88*0.02)*1.13 -> 186.11326 | E88: 306 | F88: 8136.72 | G88: 5798.02 | H88: 68.4 | I88: 522.56 | J88: 1747.74 | K88: 1846.12 | L88: 0 | M88: 0 | N88: 0 | O88: =(K88-L88)+(M88-N88) -> 1846.12 | P88: =SUM(G88,H88,I88,O88) -> 8235.1
A89: May 18 - May 24 | B89: 9724.81 | C89: =(B89*0.06)*1.13 -> 659.34212 | D89: =(B89*0.02)*1.13 -> 219.78071 | E89: 302 | F89: 9698.12 | G89: 6969.83 | H89: 83.16 | I89: 367.88 | J89: 2277.25 | K89: 2303.94 | L89: 0 | M89: 0 | N89: 0 | O89: =(K89-L89)+(M89-N89) -> 2303.94 | P89: =SUM(G89,H89,I89,O89) -> 9724.81
A90: May 25 - May 31 | B90: 8733.59 | C90: =(B90*0.06)*1.13 -> 592.1374 | D90: =(B90*0.02)*1.13 -> 197.37913 | E90: 275 | F90: 9049.3 | G90: 6214.83 | H90: 158.35 | I90: 363.29 | J90: 2312.83 | K90: 2312.83 | L90: 315.71 | M90: 0 | N90: 0 | O90: =(K90-L90)+(M90-N90) -> 1997.12 | P90: =SUM(G90,H90,I90,O90) -> 8733.59
A93: Ajax
A94: Statement For Selected Period | B94: Total Revenue (Net Sales) | C94: Royalties (6%) +HST | D94: Marketing (2%) +HST
A95: Mar 09 - Mar 15 2026 | B95: 9629.73 | C95: =(B92*0.06)*1.13 -> 0 | D95: =(B92*0.02)*1.13 -> 0
A96: Mar 16 - Mar 22 2026 | B96: 11058.63 | C96: =(B93*0.06)*1.13 -> 0 | D96: =(B93*0.02)*1.13 -> 0
A97: Mar 23 - Mar 29 2026 | B97: 8345.03 | C97: =(B94*0.06)*1.13 -> #VALUE! | D97: =(B94*0.02)*1.13 -> #VALUE!
A98: Mar 30 - Apr 05 2026 | B98: 9875.25 | C98: =(B95*0.06)*1.13 -> 652.89569 | D98: =(B95*0.02)*1.13 -> 217.6319
A99: Apr 06 - Apr 12 | B99: 8969.31 | C99: =(B96*0.06)*1.13 -> 749.77511 | D99: =(B96*0.02)*1.13 -> 249.92504
A100: Apr 13 - Apr 19 | B100: 8563.72 | C100: =(B97*0.06)*1.13 -> 565.79303 | D100: =(B97*0.02)*1.13 -> 188.59768
A101: Apr 20 - Apr 26 | B101: 7472.82 | C101: =(B98*0.06)*1.13 -> 669.54195 | D101: =(B98*0.02)*1.13 -> 223.18065
A102: Apr 27 - May 03 | B102: 8601.07 | C102: =(B100*0.06)*1.13 -> 580.62022 | D102: =(B100*0.02)*1.13 -> 193.54007
A103: May 4 - May 10 | B103: 9769.83 | C103: =(B101*0.06)*1.13 -> 506.6572 | D103: =(B101*0.02)*1.13 -> 168.88573
A104: May 11 - May 17 | B104: 8235.1 | C104: =(B103*0.06)*1.13 -> 662.39447 | D104: =(B103*0.02)*1.13 -> 220.79816
A105: May 18 - May 24 | B105: 9724.81 | C105: 659.34212 | D105: 219.78071
A106: May 25 - May 31 | B106: 8733.59 | C106: =(B106*0.06)*1.13 -> 592.1374 | D106: =(B106*0.02)*1.13 -> 197.37913

Sheet PKQueen
A1: PK Queen St.
A2: Statement For Selected Period | B2: Total Revenue (Net Sales) | C2: Royalties (6%) | D2: Marketing (2%)
A3: Oct 21 - Oct 27 2024 | C3: =(B3*0.06)*1.13 -> 0 | D3: =(B3*0.02)*1.13 -> 0
A4: Oct 28 - Nov 03 2024 | B4: 2261.82 | C4: =(B4*0.06)*1.13 -> 153.3514 | D4: =(B4*0.02)*1.13 -> 51.117132
A5: Nov 4 - Nov 10 2024 | B5: 5128.36 | C5: =(B5*0.06)*1.13 -> 347.70281 | D5: =(B5*0.02)*1.13 -> 115.90094
A6: Nov 11 - Nov 17 2024 | B6: 6350.06 | C6: =(B6*0.06)*1.13 -> 430.53407 | D6: =(B6*0.02)*1.13 -> 143.51136
A7: Nov 18 - Nov 24 2024 | B7: 7297.6 | C7: =(B7*0.06)*1.13 -> 494.77728 | D7: =(B7*0.02)*1.13 -> 164.92576
A8: Nov 25 - Dec 01 2024 | B8: 6278.52 | C8: =(B8*0.06)*1.13 -> 425.68366 | D8: =(B8*0.02)*1.13 -> 141.89455
A9: Dec 02 - Dec 08 2024 | B9: 7318.83 | C9: =(B9*0.06)*1.13 -> 496.21667 | D9: =(B9*0.02)*1.13 -> 165.40556
A10: Dec 09 - Dec 15 2024 | B10: 8909.29 | C10: =(B10*0.06)*1.13 -> 604.04986 | D10: =(B10*0.02)*1.13 -> 201.34995
A11: Dec 16 - Dec 22 2024 | B11: 9881.16 | C11: =(B11*0.06)*1.13 -> 669.94265 | D11: =(B11*0.02)*1.13 -> 223.31422
A12: Dec 23 - Dec 29 2024 | B12: 10740.81 | C12: =(B12*0.06)*1.13 -> 728.22692 | D12: =(B12*0.02)*1.13 -> 242.74231 | G12: 3794.73 | H12: 5063.33 | I12: 172.65 | J12: 1710.1
A13: Dec 30 - Jan 05 2025 | B13: 11526.52 | C13: =(B13*0.06)*1.13 -> 781.49806 | D13: =(B13*0.02)*1.13 -> 260.49935 | G13: 5010.36 | H13: 5289.89 | I13: 137.1 | J13: 1089.17
A14: Jan 06 - Jan 12 2025 | B14: 7725.15 | C14: =(B14*0.06)*1.13 -> 523.76517 | D14: =(B14*0.02)*1.13 -> 174.58839 | G14: In-Store | H14: Skip | I14: DD | J14: Uber (TB) | K14: Uber (Website) | L14: Subtract | M14: Final uber | N14: Total
A15: Jan 13 - Jan 19 2025 | B15: 10708.9 | C15: =(B15*0.06)*1.13 -> 726.06342 | D15: =(B15*0.02)*1.13 -> 242.02114 | G15: 4115.66 | H15: 141.98 | I15: 618.91 | J15: 6167.33 | K15: 6498 | L15: 665.65 | M15: =K15-L15 -> 5832.35 | N15: =SUM(G15,H15,I15,M15) -> 10708.9
A16: Jan 20 - Jan 26 2025 | B16: 9536.83 | C16: =(B16*0.06)*1.13 -> 646.59707 | D16: =(B16*0.02)*1.13 -> 215.53236 | G16: 3288.21 | H16: 360.78 | I16: 922.87 | J16: 5886.81 | K16: 5487.98 | L16: 523.01 | M16: =K16-L16 -> 4964.97 | N16: =SUM(G16,H16,I16,M16) -> 9536.83
A17: Jan 27 - Feb 02 2025 | B17: 10031.3 | C17: =(B17*0.06)*1.13 -> 680.12214 | D17: =(B17*0.02)*1.13 -> 226.70738 | G17: 3134.86 | H17: 116.27 | I17: 892.31 | J17: 6608.49 | K17: 6546.71 | L17: 658.85 | M17: =K17-L17 -> 5887.86 | N17: =SUM(G17,H17,I17,M17) -> 10031.3
C18: =(B18*0.06)*1.13 -> 0 | D18: =(B18*0.02)*1.13 -> 0 | E18: Bill Count | F18: TB Total | G18: In-Store | H18: Skip | I18: DD | J18: Uber (TB) | K18: PK Uber (Rev) | L18: PK Uber (Marketing) | M18: Ox Uber (Rev) | N18: Ox Uber (Marketing) | O18: Chickentarian Uber (Rev) | P18: Chickentarian Uber (Marketing) | Q18: Final Uber | R18: Total
A19: Feb 03 - Feb 09 2025 | B19: 9989.9 | C19: =(B19*0.06)*1.13 -> 677.31522 | D19: =(B19*0.02)*1.13 -> 225.77174 | G19: 3046.85 | H19: 191.24 | I19: 1554.46 | J19: 6048.37 | K19: 5985.12 | L19: 764.08 | M19: 0 | N19: 23.69 | Q19: =((K19-L19)+(M19-N19)) -> 5197.35 | R19: =SUM(G19,H19,I19,Q19) -> 9989.9
A20: Feb 10 - Feb 16 2025 | B20: 10366.24 | C20: =(B20*0.06)*1.13 -> 702.83107 | D20: =(B20*0.02)*1.13 -> 234.27702 | G20: 3813.2 | H20: 258.86 | I20: 1318.63 | J20: 5465.37 | K20: 5711.49 | L20: 726.31 | M20: 0 | N20: 9.63 | Q20: =((K20-L20)+(M20-N20)) -> 4975.55 | R20: =SUM(G20,H20,I20,Q20) -> 10366.24
A21: Feb 17 - Feb 23 2025 | B21: 11016.59 | C21: =(B21*0.06)*1.13 -> 746.9248 | D21: =(B21*0.02)*1.13 -> 248.97493 | G21: 3713.38 | H21: 144.94 | I21: 1470.88 | J21: 6566.33 | K21: 6441.86 | L21: 749.27 | M21: 0 | N21: 5.2 | Q21: =((K21-L21)+(M21-N21)) -> 5687.39 | R21: =SUM(G21,H21,I21,Q21) -> 11016.59
A22: Feb 24 - Mar 02 2025 | B22: 10510.49 | C22: =(B22*0.06)*1.13 -> 712.61122 | D22: =(B22*0.02)*1.13 -> 237.53707 | G22: 3365.12 | H22: 325.87 | I22: 1385.13 | J22: 6210.1 | K22: 6477.34 | L22: 1033.6 | M22: 0 | N22: 9.37 | Q22: =((K22-L22)+(M22-N22)) -> 5434.37 | R22: =SUM(G22,H22,I22,Q22) -> 10510.49
A23: Mar 03 - Mar 09 2025 | B23: 9931.58 | C23: =(B23*0.06)*1.13 -> 673.36112 | D23: =(B23*0.02)*1.13 -> 224.45371 | G23: 2763.72 | H23: 141.2 | I23: 1103.87 | J23: 6882.12 | K23: 6856.92 | L23: 919.06 | M23: 0 | N23: 15.07 | Q23: =((K23-L23)+(M23-N23)) -> 5922.79 | R23: =SUM(G23,H23,I23,Q23) -> 9931.58
A24: Mar 10 - Mar 16 2025 | B24: 10702.22 | C24: =(B24*0.06)*1.13 -> 725.61052 | D24: =(B24*0.02)*1.13 -> 241.87017 | G24: 3579.99 | H24: 241.88 | I24: 1197.78 | J24: 6516.21 | K24: 6558.71 | L24: 857.84 | M24: 0 | N24: 18.3 | Q24: =((K24-L24)+(M24-N24)) -> 5682.57 | R24: =SUM(G24,H24,I24,Q24) -> 10702.22
A25: Mar 17 - Mar 23 2025 | B25: 12097.52 | C25: =(B25*0.06)*1.13 -> 820.21186 | D25: =(B25*0.02)*1.13 -> 273.40395 | G25: 4509.91 | H25: 419.45 | I25: 1168.6 | J25: 7059.11 | K25: 7134.45 | L25: 1110.23 | M25: 0 | N25: 24.66 | Q25: =((K25-L25)+(M25-N25)) -> 5999.56 | R25: =SUM(G25,H25,I25,Q25) -> 12097.52
A26: Mar 24 - Mar 30 2025 | B26: 12606.67 | C26: =(B26*0.06)*1.13 -> 854.73223 | D26: =(B26*0.02)*1.13 -> 284.91074 | G26: 3955.85 | H26: 247.58 | I26: 1820.72 | J26: 7729.27 | K26: 7752.39 | L26: 1004.83 | M26: 194.23 | N26: 359.27 | Q26: =((K26-L26)+(M26-N26)) -> 6582.52 | R26: =SUM(G26,H26,I26,Q26) -> 12606.67
A27: Mar 31 - Apr 6 2025 | B27: =(10523.76 - 620.37) -> 9903.39 | C27: =(B27*0.06)*1.13 -> 671.44984 | D27: =(B27*0.02)*1.13 -> 223.81661 | G27: 3779.47 | H27: 149.6 | I27: 1433.27 | J27: 5337.88 | K27: 5351.37 | L27: 153.5 | M27: 0 | N27: 36.45 | Q27: =((K27-L27)+(M27-N27)) -> 5161.42 | R27: =SUM(G27,H27,I27,Q27) -> 10523.76
A28: Apr 7 - Apr 13 2025 | B28: 11452.13 | C28: =(B28*0.06)*1.13 -> 776.45441 | D28: =(B28*0.02)*1.13 -> 258.81814 | G28: 3535.88 | H28: 330.28 | I28: 1380.22 | J28: 6641.72 | K28: 6639.96 | L28: 437.83 | M28: 29.37 | N28: 25.75 | Q28: =((K28-L28)+(M28-N28)) -> 6205.75 | R28: =SUM(G28,H28,I28,Q28) -> 11452.13
A29: Apr 14 - Apr 20 2025 | B29: 11997.78 | C29: =(B29*0.06)*1.13 -> 813.44948 | D29: =(B29*0.02)*1.13 -> 271.14983 | G29: 3757.69 | H29: 151.2 | I29: 1978.17 | J29: 6624.85 | K29: 6589.1 | L29: 455.9 | M29: 0 | N29: 22.48 | Q29: =((K29-L29)+(M29-N29)) -> 6110.72 | R29: =SUM(G29,H29,I29,Q29) -> 11997.78
A30: Apr 21 - Apr 27 2025 | B30: 12128 | C30: =(B30*0.06)*1.13 -> 822.2784 | D30: =(B30*0.02)*1.13 -> 274.0928 | G30: 4046.75 | H30: 338.98 | I30: 1511.3 | J30: 6616 | K30: 6678.47 | L30: 451.43 | M30: 23.98 | N30: 20.05 | Q30: =((K30-L30)+(M30-N30)) -> 6230.97 | R30: =SUM(G30,H30,I30,Q30) -> 12128
A31: Apr 28 - May 04 2025 | B31: 13751.65 | C31: =(B31*0.06)*1.13 -> 932.36187 | D31: =(B31*0.02)*1.13 -> 310.78729 | F31: 14143.37 | G31: 5084.33 | H31: 264.78 | I31: 1538.62 | J31: 7255.64 | K31: 7340.46 | L31: 446.72 | M31: 0 | N31: 29.82 | Q31: =((K31-L31)+(M31-N31)) -> 6863.92 | R31: =SUM(G31,H31,I31,Q31) -> 13751.65
A32: May 05 - May 11 2025 | B32: 13226.86 | C32: =(B32*0.06)*1.13 -> 896.78111 | D32: =(B32*0.02)*1.13 -> 298.92704 | F32: 13618.49 | G32: 4056.91 | H32: 375.69 | I32: 2037.02 | J32: 7148.87 | K32: 7294.01 | L32: 517.46 | M32: 0 | N32: 19.31 | Q32: =((K32-L32)+(M32-N32)) -> 6757.24 | R32: =SUM(G32,H32,I32,Q32) -> 13226.86
A33: May 12 - May 18 2025 | B33: 12254.64 | C33: =(B33*0.06)*1.13 -> 830.86459 | D33: =(B33*0.02)*1.13 -> 276.95486 | F33: 12877.68 | G33: 4131.83 | H33: 369.6 | I33: 1855.22 | J33: 6521.03 | K33: 6362.97 | L33: 441.1 | M33: 0 | N33: 23.88 | Q33: =((K33-L33)+(M33-N33)) -> 5897.99 | R33: =SUM(G33,H33,I33,Q33) -> 12254.64
A34: May 19 - May 25 2025 | B34: 13263.23 | C34: =(B34*0.06)*1.13 -> 899.24699 | D34: =(B34*0.02)*1.13 -> 299.749 | F34: 13643.37 | G34: 3511.71 | H34: 186.97 | I34: 2082.91 | J34: 7861.78 | K34: 8006.63 | L34: 517.01 | M34: 0 | N34: 7.98 | Q34: =((K34-L34)+(M34-N34)) -> 7481.64 | R34: =SUM(G34,H34,I34,Q34) -> 13263.23
A35: May 26 - June 01 2025 | B35: 12676.84 | C35: =(B35*0.06)*1.13 -> 859.48975 | D35: =(B35*0.02)*1.13 -> 286.49658 | F35: 12886.76 | G35: 4188.9 | H35: 311.05 | I35: 1659.35 | J35: 6727.46 | K35: 6929.81 | L35: 411.48 | M35: 15.58 | N35: 16.37 | Q35: =((K35-L35)+(M35-N35)) -> 6517.54 | R35: =SUM(G35,H35,I35,Q35) -> 12676.84
A36: June 02 - June 08 2025 | B36: 12445.2 | C36: =(B36*0.06)*1.13 -> 843.78456 | D36: =(B36*0.02)*1.13 -> 281.26152 | F36: 12956.18 | G36: 3756.92 | H36: 162.3 | I36: 1535.15 | J36: 7501.81 | K36: 7508.04 | L36: 485.05 | M36: 0 | N36: 32.16 | Q36: =((K36-L36)+(M36-N36)) -> 6990.83 | R36: =SUM(G36,H36,I36,Q36) -> 12445.2
A37: June 09 - June 15 2025 | B37: 13944 | C37: =(B37*0.06)*1.13 -> 945.4032 | D37: =(B37*0.02)*1.13 -> 315.1344 | F37: 14232.26 | G37: 4461.48 | H37: 424.48 | I37: 1637.19 | J37: 7709.11 | K37: 7863.61 | L37: 460.53 | M37: 32.77 | N37: 15 | Q37: =((K37-L37)+(M37-N37)) -> 7420.85 | R37: =SUM(G37,H37,I37,Q37) -> 13944
A38: June 16 - June 22 2025 | B38: 14173.26 | C38: =(B38*0.06)*1.13 -> 960.94703 | D38: =(B38*0.02)*1.13 -> 320.31568 | F38: 14632.14 | G38: 4942.68 | H38: 177.18 | I38: 1703.43 | J38: 7808.85 | K38: 7803.71 | L38: 448.28 | M38: 21.98 | N38: 27.44 | Q38: =((K38-L38)+(M38-N38)) -> 7349.97 | R38: =SUM(G38,H38,I38,Q38) -> 14173.26
A39: June 23 - June 29 2025 | B39: 13029.85 | C39: =(B39*0.06)*1.13 -> 883.42383 | D39: =(B39*0.02)*1.13 -> 294.47461 | F39: 13312.48 | G39: 4305.79 | H39: 137.19 | I39: 2011.49 | J39: 6858.01 | K39: 6806.83 | L39: 210.74 | M39: 0 | N39: 20.71 | Q39: =((K39-L39)+(M39-N39)) -> 6575.38 | R39: =SUM(G39,H39,I39,Q39) -> 13029.85
A40: June 30 - July 06 2025 | B40: 15688.35 | C40: =(B40*0.06)*1.13 -> 1063.6701 | D40: =(B40*0.02)*1.13 -> 354.55671 | F40: 15865.18 | G40: 5143.43 | H40: 235.46 | I40: 2363.68 | J40: 8122.61 | K40: 8164.91 | L40: 200.01 | M40: 0 | N40: 19.12 | Q40: =((K40-L40)+(M40-N40)) -> 7945.78 | R40: =SUM(G40,H40,I40,Q40) -> 15688.35
A41: July 07 - July 13 2025 | B41: 13629.86 | C41: =(B41*0.06)*1.13 -> 924.10451 | D41: =(B41*0.02)*1.13 -> 308.03484 | F41: 14043.35 | G41: 4001.28 | H41: 434.28 | I41: 2145.82 | J41: 7461.97 | K41: 7550.49 | L41: 494.95 | M41: 0 | N41: 7.06 | Q41: =((K41-L41)+(M41-N41)) -> 7048.48 | R41: =SUM(G41,H41,I41,Q41) -> 13629.86
A42: July 14 - July 20 2025 | B42: 13979.17 | C42: =(B42*0.06)*1.13 -> 947.78773 | D42: =(B42*0.02)*1.13 -> 315.92924 | E42: 497 | F42: 14374.45 | G42: 4204.22 | H42: 227.68 | I42: 1761.07 | J42: 8181.48 | K42: 8253.88 | L42: 489.06 | M42: 34.77 | N42: 13.39 | Q42: =((K42-L42)+(M42-N42)) -> 7786.2 | R42: =SUM(G42,H42,I42,Q42) -> 13979.17
A43: July 21 - July 27 2025 | B43: 13594.48 | C43: =(B43*0.06)*1.13 -> 921.70574 | D43: =(B43*0.02)*1.13 -> 307.23525 | E43: 510 | F43: 14059.62 | G43: 4887.65 | H43: 452.43 | I43: 2190.45 | J43: 6529.09 | K43: 6561.89 | L43: 486.92 | M43: 16.18 | N43: 27.2 | Q43: =((K43-L43)+(M43-N43)) -> 6063.95 | R43: =SUM(G43,H43,I43,Q43) -> 13594.48
A44: July 28 - Aug 03 2025 | B44: 14246.77 | C44: =(B44*0.06)*1.13 -> 965.93101 | D44: =(B44*0.02)*1.13 -> 321.977 | E44: 541 | F44: 14524.74 | G44: 4297.22 | H44: 378.75 | I44: 2019.45 | J44: 7829.32 | K44: 7931.91 | L44: 465.44 | M44: 95.12 | N44: 10.24 | Q44: =((K44-L44)+(M44-N44)) -> 7551.35 | R44: =SUM(G44,H44,I44,Q44) -> 14246.77
A45: Aug 04 - Aug 10 2025 | B45: 14740.27 | C45: =(B45*0.06)*1.13 -> 999.39031 | D45: =(B45*0.02)*1.13 -> 333.1301 | E45: 539 | F45: 14988.93 | G45: 4262.86 | H45: 474.54 | I45: 1822.52 | J45: 8429.01 | K45: 8791.36 | L45: 611.01 | M45: 0 | N45: 0 | Q45: =((K45-L45)+(M45-N45)) -> 8180.35 | R45: =SUM(G45,H45,I45,Q45) -> 14740.27
A46: Aug 11 - Aug 17 2025 | B46: 14038.04 | C46: =(B46*0.06)*1.13 -> 951.77911 | D46: =(B46*0.02)*1.13 -> 317.2597 | E46: 536 | F46: 14502.32 | G46: 4401.66 | H46: 318.97 | I46: 2060.22 | J46: 7721.47 | K46: 7787.71 | L46: 515.22 | M46: 0 | N46: 15.3 | Q46: =((K46-L46)+(M46-N46)) -> 7257.19 | R46: =SUM(G46,H46,I46,Q46) -> 14038.04
A47: Aug 18 - Aug 24 2025 | B47: 15466.5 | C47: =(B47*0.06)*1.13 -> 1048.6287 | D47: =(B47*0.02)*1.13 -> 349.5429 | E47: 588 | F47: 15996.94 | G47: 5524.64 | H47: 248.38 | I47: 2308.81 | J47: 7915.11 | K47: 7920.44 | L47: 582.38 | M47: 83.72 | N47: 37.11 | Q47: =((K47-L47)+(M47-N47)) -> 7384.67 | R47: =SUM(G47,H47,I47,Q47) -> 15466.5
A48: Aug 25 - Aug 31 2025 | B48: 15746.22 | C48: =(B48*0.06)*1.13 -> 1067.5937 | D48: =(B48*0.02)*1.13 -> 355.86457 | E48: 595 | F48: 16456.65 | G48: 5612.57 | H48: 275.86 | I48: 1831.86 | J48: 8736.36 | K48: 8524.16 | L48: 547.66 | M48: 78.13 | N48: 28.7 | Q48: =((K48-L48)+(M48-N48)) -> 8025.93 | R48: =SUM(G48,H48,I48,Q48) -> 15746.22
A49: Sep 01 - Sep 07 2025 | B49: 15591.35 | C49: =(B49*0.06)*1.13 -> 1057.0935 | D49: =(B49*0.02)*1.13 -> 352.36451 | E49: 582 | F49: 16037.12 | G49: 5152.11 | H49: 253.6 | I49: 2286.43 | J49: 8344.98 | K49: 8525.07 | L49: 604.05 | M49: 0 | N49: 21.81 | Q49: =((K49-L49)+(M49-N49)) -> 7899.21 | R49: =SUM(G49,H49,I49,Q49) -> 15591.35
A50: Sep 08 - Sep 14 2025 | B50: 14303.51 | C50: =(B50*0.06)*1.13 -> 969.77798 | D50: =(B50*0.02)*1.13 -> 323.25933 | E50: 561 | F50: 14383.2 | G50: 5311.31 | H50: 288.16 | I50: 1789.2 | J50: 6994.53 | K50: 7071.81 | L50: 217.45 | M50: 113.31 | N50: 52.83 | Q50: =((K50-L50)+(M50-N50)) -> 6914.84 | R50: =SUM(G50,H50,I50,Q50) -> 14303.51
A51: Sep 15 - Sep 21 2025 | B51: 14290.72 | C51: =(B51*0.06)*1.13 -> 968.91082 | D51: =(B51*0.02)*1.13 -> 322.97027 | E51: 532 | F51: 14277.18 | G51: 5225.7 | H51: 368.71 | I51: 2444.64 | J51: 6238.13 | K51: 6314.84 | L51: 97.82 | M51: 84.32 | N51: 49.67 | Q51: =((K51-L51)+(M51-N51)) -> 6251.67 | R51: =SUM(G51,H51,I51,Q51) -> 14290.72
A52: Sep 22 - Sep 28 2025 | B52: 14411.99 | C52: =(B52*0.06)*1.13 -> 977.13292 | D52: =(B52*0.02)*1.13 -> 325.71097 | E52: 531 | F52: 14750.47 | G52: 5722.28 | H52: 275.05 | I52: 2688.11 | J52: 6065.03 | K52: 5830.62 | L52: 96.23 | M52: 54.36 | N52: 62.2 | O52: 0 | P52: 0 | Q52: =((K52-L52)+(M52-N52)) -> 5726.55 | R52: =SUM(G52,H52,I52,Q52) -> 14411.99
A53: Sep 29 - Oct 05 2025 | B53: 15349.09 | C53: =(B53*0.06)*1.13 -> 1040.6683 | D53: =(B53*0.02)*1.13 -> 346.88943 | E53: 568 | F53: 15936.55 | G53: 6124.68 | H53: 404.22 | I53: 2324.93 | J53: 7082.72 | K53: 7344.28 | L53: 857.19 | M53: 73.54 | N53: 65.37 | O53: 1.5 | P53: 0 | Q53: =((K53-L53)+(M53-N53)) -> 6495.26 | R53: =SUM(G53,H53,I53,Q53) -> 15349.09
A54: Oct 6 - Oct 12 2025 | B54: 14123.37 | C54: =(B54*0.06)*1.13 -> 957.56449 | D54: =(B54*0.02)*1.13 -> 319.18816 | E54: 549 | F54: 15243.53 | G54: 4903.59 | H54: 361.26 | I54: 2206.9 | J54: 7771.78 | K54: 7649.43 | L54: 970.38 | M54: 0 | N54: 27.43 | O54: 0 | P54: 0 | Q54: =((K54-L54)+(M54-N54)) -> 6651.62 | R54: =SUM(G54,H54,I54,Q54) -> 14123.37
A55: Oct 13 - Oct 19 2025 | B55: 13972.31 | C55: =(B55*0.06)*1.13 -> 947.32262 | D55: =(B55*0.02)*1.13 -> 315.77421 | F55: 14616.12 | G55: 4897.89 | H55: 285.84 | I55: 2361.54 | J55: 7070.85 | K55: 7283.07 | L55: 885.05 | M55: 0 | N55: 54.32 | O55: 83.34 | P55: 0 | Q55: =((K55-L55)+(M55-N55)+(O55-P55)) -> 6427.04 | R55: =SUM(G55,H55,I55,Q55) -> 13972.31
A56: Oct 20 - Oct 26 2025 | B56: 15697.34 | C56: =(B56*0.06)*1.13 -> 1064.2797 | D56: =(B56*0.02)*1.13 -> 354.75988 | F56: 16085.22 | G56: 4864.93 | H56: 268.54 | I56: 2891.47 | J56: 8060.28 | K56: 8493.49 | L56: 816.33 | M56: 28.76 | N56: 33.52 | O56: 0 | P56: 0 | Q56: =((K56-L56)+(M56-N56)+(O56-P56)) -> 7672.4 | R56: =SUM(G56,H56,I56,Q56) -> 15697.34
A57: Oct 27 - Nov 02 2025 | B57: 18104.04 | C57: =(B57*0.06)*1.13 -> 1227.4539 | D57: =(B57*0.02)*1.13 -> 409.1513 | E57: 646 | F57: 19146.18 | G57: 5857.52 | H57: 682.53 | I57: 2155.16 | J57: 10450.97 | K57: 10781.5 | L57: 1371.33 | M57: 0 | N57: 1.34 | O57: 0 | P57: 0 | Q57: =((K57-L57)+(M57-N57)+(O57-P57)) -> 9408.83 | R57: =SUM(G57,H57,I57,Q57) -> 18104.04
A58: Nov 03 - Nov 09 2025 | B58: 13482.43 | C58: =(B58*0.06)*1.13 -> 914.10875 | D58: =(B58*0.02)*1.13 -> 304.70292 | E58: 472 | F58: 14414.4 | G58: 4023.23 | H58: 176.3 | I58: 1988.43 | J58: 8226.44 | K58: 8241.56 | L58: 1019.43 | M58: 31.16 | N58: 0 | O58: 41.18 | P58: 0 | Q58: =((K58-L58)+(M58-N58)+(O58-P58)) -> 7294.47 | R58: =SUM(G58,H58,I58,Q58) -> 13482.43
A59: Nov 10 - Nov 16 2025 | B59: 15113.06 | C59: =(B59*0.06)*1.13 -> 1024.6655 | D59: =(B59*0.02)*1.13 -> 341.55516 | E59: 583 | F59: 16282.4 | G59: 5185.84 | H59: 333.54 | I59: 2764.88 | J59: 7998.14 | K59: 8020.34 | L59: 1191.54 | M59: 0 | N59: 0 | O59: 0 | P59: 0 | Q59: =((K59-L59)+(M59-N59)+(O59-P59)) -> 6828.8 | R59: =SUM(G59,H59,I59,Q59) -> 15113.06
A60: Nov 17 - Nov 23 2025 | B60: 15151.53 | C60: =(B60*0.06)*1.13 -> 1027.2737 | D60: =(B60*0.02)*1.13 -> 342.42458 | E60: 551 | F60: 16411.18 | G60: 4361.81 | H60: 336.43 | I60: 2789.42 | J60: 8923.52 | K60: 8948.41 | L60: 1284.54 | M60: 0 | N60: 0 | O60: 0 | P60: 0 | Q60: =((K60-L60)+(M60-N60)+(O60-P60)) -> 7663.87 | R60: =SUM(G60,H60,I60,Q60) -> 15151.53
A61: Nov 24 - Nov 30 2025 | B61: 14775.71 | C61: =(B61*0.06)*1.13 -> 1001.7931 | D61: =(B61*0.02)*1.13 -> 333.93105 | E61: 517 | F61: 15736.51 | G61: 4182.18 | H61: 293.19 | I61: 2856.44 | J61: 8404.7 | K61: 8353.82 | L61: 939.89 | M61: 29.97 | N61: 0 | O61: 0 | P61: 0 | Q61: =((K61-L61)+(M61-N61)+(O61-P61)) -> 7443.9 | R61: =SUM(G61,H61,I61,Q61) -> 14775.71
A62: Dec 01 - Dec 07 2025 | B62: 16102.93 | C62: =(B62*0.06)*1.13 -> 1091.7787 | D62: =(B62*0.02)*1.13 -> 363.92622 | E62: 527 | F62: 17534.8 | G62: 3355.88 | H62: 239.48 | I62: 2668.25 | J62: 11271.19 | K62: 11384.08 | L62: 1544.76 | M62: 0 | N62: 0 | O62: 0 | P62: 0 | Q62: =((K62-L62)+(M62-N62)+(O62-P62)) -> 9839.32 | R62: =SUM(G62,H62,I62,Q62) -> 16102.93
A63: Dec 08 - Dec 14 2025 | B63: 14416.25 | C63: =(B63*0.06)*1.13 -> 977.42175 | D63: =(B63*0.02)*1.13 -> 325.80725 | E63: 503 | F63: 15700.42 | G63: 4130.92 | H63: 337.92 | I63: 2475.19 | J63: 8756.39 | K63: 8952.2 | L63: 1479.98 | M63: 0 | N63: 0 | O63: 0 | P63: 0 | Q63: =((K63-L63)+(M63-N63)+(O63-P63)) -> 7472.22 | R63: =SUM(G63,H63,I63,Q63) -> 14416.25
A64: Dec 15 - Dec 21 2025 | B64: 16929.6 | C64: =(B64*0.06)*1.13 -> 1147.8269 | D64: =(B64*0.02)*1.13 -> 382.60896 | E64: 603 | F64: 18287.58 | G64: 4828.2 | H64: 444.34 | I64: 3392.98 | J64: 9622.06 | K64: 9498.39 | L64: 1258.3 | M64: 23.99 | N64: 0 | O64: 0 | P64: 0 | Q64: =((K64-L64)+(M64-N64)+(O64-P64)) -> 8264.08 | R64: =SUM(G64,H64,I64,Q64) -> 16929.6
A65: Dec 22 - Dec 28 2025 | B65: 17682.99 | C65: =(B65*0.06)*1.13 -> 1198.9067 | D65: =(B65*0.02)*1.13 -> 399.63557 | E65: 598 | F65: 19207.39 | G65: 5110.45 | H65: 550.96 | I65: 3326.17 | J65: 10219.81 | K65: 10255.11 | L65: 1559.7 | M65: 0 | N65: 0 | O65: 0 | P65: 0 | Q65: =((K65-L65)+(M65-N65)+(O65-P65)) -> 8695.41 | R65: =SUM(G65,H65,I65,Q65) -> 17682.99
A66: Dec 29 - Jan 04 2026 | B66: 19321.66 | C66: =(B66*0.06)*1.13 -> 1310.0085 | D66: =(B66*0.02)*1.13 -> 436.66952 | E66: 673 | F66: 21062.7 | G66: 5611.34 | H66: 289.97 | I66: 2908.89 | J66: 12252.5 | K66: 12375.8 | L66: 1864.34 | M66: 0 | N66: 0 | O66: 0 | P66: 0 | Q66: =((K66-L66)+(M66-N66)+(O66-P66)) -> 10511.46 | R66: =SUM(G66,H66,I66,Q66) -> 19321.66
A67: Jan 05 - Jan 11 2026 | B67: 14161.67 | C67: =(B67*0.06)*1.13 -> 960.16123 | D67: =(B67*0.02)*1.13 -> 320.05374 | E67: 520 | F67: 15596.32 | G67: 4027.45 | H67: 304.4 | I67: 2650.29 | J67: 8614.18 | K67: 8722.43 | L67: 1542.9 | M67: 0 | N67: 0 | O67: 0 | P67: 0 | Q67: =((K67-L67)+(M67-N67)+(O67-P67)) -> 7179.53 | R67: =SUM(G67,H67,I67,Q67) -> 14161.67
A68: Jan 12 - Jan 18 2026 | B68: 14412.41 | C68: =(B68*0.06)*1.13 -> 977.1614 | D68: =(B68*0.02)*1.13 -> 325.72047 | E68: 535 | F68: 15755.66 | G68: 3847.33 | H68: 206.04 | I68: 2793.87 | J68: 8908.42 | K68: 8861.41 | L68: 1333.82 | M68: 0 | N68: 0 | O68: 58.56 | P68: 20.98 | Q68: =((K68-L68)+(M68-N68)+(O68-P68)) -> 7565.17 | R68: =SUM(G68,H68,I68,Q68) -> 14412.41
A69: Jan 19 - Jan 25 2026 | B69: 15090.76 | C69: =(B69*0.06)*1.13 -> 1023.1535 | D69: =(B69*0.02)*1.13 -> 341.05118 | E69: 523 | F69: 16471.79 | G69: 3305.09 | H69: 382.33 | I69: 3515.47 | J69: 9268.9 | K69: 9140.8 | L69: 1252.93 | M69: 0 | N69: 0 | O69: 0 | P69: 0 | Q69: =((K69-L69)+(M69-N69)+(O69-P69)) -> 7887.87 | R69: =SUM(G69,H69,I69,Q69) -> 15090.76
A70: Jan 26 - Feb 01 2026 | B70: 16414.45 | C70: =(B70*0.06)*1.13 -> 1112.8997 | D70: =(B70*0.02)*1.13 -> 370.96657 | E70: 552 | F70: 17620.16 | G70: 4598.74 | H70: 504.36 | I70: 3179.34 | J70: 9337.72 | K70: 9480.79 | L70: 1371.56 | M70: 22.78 | N70: 0 | O70: 0 | P70: 0 | Q70: =((K70-L70)+(M70-N70)+(O70-P70)) -> 8132.01 | R70: =SUM(G70,H70,I70,Q70) -> 16414.45
A71: Feb 02 - Feb 08 2026 | B71: 15697.18 | C71: =(B71*0.06)*1.13 -> 1064.2688 | D71: =(B71*0.02)*1.13 -> 354.75627 | E71: 524 | F71: 16752.89 | G71: 4242.85 | H71: 477.89 | I71: 2710.88 | J71: 9321.27 | K71: 9527.71 | L71: 1314.33 | M71: 67.56 | N71: 15.38 | O71: 0 | P71: 0 | Q71: =((K71-L71)+(M71-N71)+(O71-P71)) -> 8265.56 | R71: =SUM(G71,H71,I71,Q71) -> 15697.18
A72: Feb 09 - Feb 15 2026 | B72: 16905.03 | C72: =(B72*0.06)*1.13 -> 1146.161 | D72: =(B72*0.02)*1.13 -> 382.05368 | E72: 567 | F72: 17757.49 | G72: 5128.11 | H72: 373.34 | I72: 3874 | J72: 8382.04 | K72: 8311.27 | L72: 802.29 | M72: 35.98 | N72: 15.38 | O72: 0 | P72: 0 | Q72: =((K72-L72)+(M72-N72)+(O72-P72)) -> 7529.58 | R72: =SUM(G72,H72,I72,Q72) -> 16905.03
A73: Feb 16 - Feb 22 2026 | B73: 14559.85 | C73: =(B73*0.06)*1.13 -> 987.15783 | D73: =(B73*0.02)*1.13 -> 329.05261 | E73: 502 | F73: 15221.08 | G73: 4454.4 | H73: 406 | I73: 2533.52 | J73: 7827.16 | K73: 8219.55 | L73: 1074.22 | M73: 35.98 | N73: 15.38 | O73: 0 | P73: 0 | Q73: =((K73-L73)+(M73-N73)+(O73-P73)) -> 7165.93 | R73: =SUM(G73,H73,I73,Q73) -> 14559.85
A74: Feb 23 - Mar 1 2026 | B74: 14119.95 | C74: =(B74*0.06)*1.13 -> 957.33261 | D74: =(B74*0.02)*1.13 -> 319.11087 | E74: 516 | F74: 14981.57 | G74: 3577.18 | H74: 211.32 | I74: 2833.46 | J74: 8359.61 | K74: 8504.48 | L74: 1006.49 | M74: 0 | N74: 0 | O74: 0 | P74: 0 | Q74: =((K74-L74)+(M74-N74)+(O74-P74)) -> 7497.99 | R74: =SUM(G74,H74,I74,Q74) -> 14119.95
A75: Mar 02 - Mar 08 2026 | B75: 15045.01 | C75: =(B75*0.06)*1.13 -> 1020.0517 | D75: =(B75*0.02)*1.13 -> 340.01723 | E75: 520 | F75: 15899.01 | G75: 3850.88 | H75: 513.71 | I75: 2919.66 | J75: 8614.76 | K75: 8715.39 | L75: 1008.5 | M75: 45.57 | N75: 15.38 | O75: 23.68 | P75: 0 | Q75: =((K75-L75)+(M75-N75)+(O75-P75)) -> 7760.76 | R75: =SUM(G75,H75,I75,Q75) -> 15045.01
A76: Mar 09 - Mar 15 2026 | B76: 14325.5 | C76: =(B76*0.06)*1.13 -> 971.2689 | D76: =(B76*0.02)*1.13 -> 323.7563 | E76: 501 | F76: 15308.32 | G76: 4091.21 | H76: 314.74 | I76: 2842.76 | J76: 8059.61 | K76: 8105.03 | L76: 1047.64 | M76: 33.98 | N76: 14.58 | O76: 0 | P76: 0 | Q76: =((K76-L76)+(M76-N76)+(O76-P76)) -> 7076.79 | R76: =SUM(G76,H76,I76,Q76) -> 14325.5
A77: Mar 16 - Mar 22 2026 | B77: 15858.82 | C77: =(B77*0.06)*1.13 -> 1075.228 | D77: =(B77*0.02)*1.13 -> 358.40933 | E77: 511 | F77: 16675.07 | G77: 3829.3 | H77: 271.45 | I77: 2129.81 | J77: 10444.51 | K77: 10831.8 | L77: 1268.72 | M77: 97.54 | N77: 32.36 | O77: 0 | P77: 0 | Q77: =((K77-L77)+(M77-N77)+(O77-P77)) -> 9628.26 | R77: =SUM(G77,H77,I77,Q77) -> 15858.82
... A82: Apr 20 - Apr 26 | B82: 16027.28 | C82: =(B82*0.06)*1.13 -> 1086.6496 | D82: =(B82*0.02)*1.13 -> 362.21653 | E82: 552 | F82: 17021.79 | G82: 4501.84 | H82: 324.65 | I82: 3050.9 | J82: 9144.4 | K82: 9251.22 | L82: 1133.92 | M82: 48.77 | N82: 16.18 | O82: 0 | P82: 0 | Q82: =((K82-L82)+(M82-N82)+(O82-P82)) -> 8149.89 | R82: =SUM(G82,H82,I82,Q82) -> 16027.28
A83: Apr 27 - May 03 | B83: 16047.12 | C83: =(B83*0.06)*1.13 -> 1087.9947 | D83: =(B83*0.02)*1.13 -> 362.66491 | E83: 558 | F83: 16696.35 | G83: 5758.91 | H83: 132.51 | I83: 2154.92 | J83: 8650.01 | K83: $8,660.02 | L83: $659.24 | M83: 0 | N83: 0 | O83: 0 | P83: 0 | Q83: =((K83-L83)+(M83-N83)+(O83-P83)) -> 8000.78 | R83: =SUM(G83,H83,I83,Q83) -> 16047.12
A84: May 4 - May 10 | B84: 16939.43 | C84: =(B84*0.06)*1.13 -> 1148.4934 | D84: =(B84*0.02)*1.13 -> 382.83112 | E84: 562 | F84: 17719.41 | G84: 5868.17 | H84: 244.16 | I84: 3123.83 | J84: 8483.25 | K84: 8892.51 | L84: 1189.24 | M84: 0 | N84: 0 | O84: 0 | P84: 0 | Q84: =((K84-L84)+(M84-N84)+(O84-P84)) -> 7703.27 | R84: =SUM(G84,H84,I84,Q84) -> 16939.43
A85: May 11 - May 17 | B85: 16229.03 | C85: =(B85*0.06)*1.13 -> 1100.3282 | D85: =(B85*0.02)*1.13 -> 366.77608 | E85: 552 | F85: 17857.86 | G85: 5469.41 | H85: 239.64 | I85: 2007.22 | J85: 10141.59 | K85: 10071.36 | L85: 1558.6 | M85: 0 | N85: 0 | O85: 0 | P85: 0 | Q85: =((K85-L85)+(M85-N85)+(O85-P85)) -> 8512.76 | R85: =SUM(G85,H85,I85,Q85) -> 16229.03
A86: May 18 - May 24 | B86: 15162.52 | C86: =(B86*0.06)*1.13 -> 1028.0189 | D86: =(B86*0.02)*1.13 -> 342.67295 | E86: 533 | F86: 16072.88 | G86: 5188.95 | H86: 123.36 | I86: 2130.72 | J86: 8629.85 | K86: 9079.16 | L86: 1393.25 | M86: 33.58 | N86: 0 | O86: 0 | P86: 0 | Q86: =((K86-L86)+(M86-N86)+(O86-P86)) -> 7719.49 | R86: =SUM(G86,H86,I86,Q86) -> 15162.52
A87: May 25 - May 31 | B87: 14629.58 | C87: =(B87*0.06)*1.13 -> 991.88552 | D87: =(B87*0.02)*1.13 -> 330.62851 | E87: 535 | F87: 15783.72 | G87: 4951.65 | H87: 287.54 | I87: 2308.83 | J87: 8235.7 | K87: 8187.34 | L87: 1140.26 | M87: 0 | N87: 0 | O87: 45.46 | P87: 10.98 | Q87: =((K87-L87)+(M87-N87)+(O87-P87)) -> 7081.56 | R87: =SUM(G87,H87,I87,Q87) -> 14629.58
A90: PK Queen St.
A91: Statement For Selected Period | B91: Total Revenue (Net Sales) | C91: Royalties (6%) +HST | D91: Marketing (2%) +HST
A92: Mar 09 - Mar 15 2026 | B92: 14325.5 | C92: =(B89*0.06)*1.13 -> 0 | D92: =(B89*0.02)*1.13 -> 0
A93: Mar 16 - Mar 22 2026 | B93: 15858.82 | C93: =(B90*0.06)*1.13 -> 0 | D93: =(B90*0.02)*1.13 -> 0
A94: Mar 23 - Mar 29 2026 | B94: 17564.11 | C94: =(B91*0.06)*1.13 -> #VALUE! | D94: =(B91*0.02)*1.13 -> #VALUE!
A95: Mar 30 - Apr 05 2026 | B95: 16208.28 | C95: =(B92*0.06)*1.13 -> 971.2689 | D95: =(B92*0.02)*1.13 -> 323.7563
A96: Apr 06 - Apr 12 | B96: 15776.96 | C96: =(B93*0.06)*1.13 -> 1075.228 | D96: =(B93*0.02)*1.13 -> 358.40933
A97: Apr 13 - Apr 19 | B97: 15478.96 | C97: =(B94*0.06)*1.13 -> 1190.8467 | D97: =(B94*0.02)*1.13 -> 396.94889
A98: Apr 20 - Apr 26 | B98: 16027.28 | C98: =(B95*0.06)*1.13 -> 1098.9214 | D98: =(B95*0.02)*1.13 -> 366.30713
A99: Apr 27 - May 03 | B99: 16047.12 | C99: =(B97*0.06)*1.13 -> 1049.4735 | D99: =(B97*0.02)*1.13 -> 349.8245
A100: May 4 - May 10 | B100: 16939.43 | C100: =(B98*0.06)*1.13 -> 1086.6496 | D100: =(B98*0.02)*1.13 -> 362.21653
A101: May 11 - May 17 | B101: 16229.03 | C101: =(B100*0.06)*1.13 -> 1148.4934 | D101: =(B100*0.02)*1.13 -> 382.83112
A102: May 18 - May 24 | B102: 15162.52 | C102: 1028.0189 | D102: 342.67295
A103: May 25 - May 31 | B103: 14629.58 | C103: =(B103*0.06)*1.13 -> 991.88552 | D103: =(B103*0.02)*1.13 -> 330.62851

Sheet KKWQueen
A1: Queen KKW
A2: Statement For Selected Period | B2: Total Revenue (Net Sales) | C2: Royalties (6%) +HST | D2: Marketing (2%) +HST | E2: Bill Count | F2: POS Total | G2: In-Store | H2: Skip | I2: DD | J2: Uber (TB) | K2: Uber (Rev) | L2: Uber (Marketing) | M2: Final Uber | N2: Total
A3: May 12 - May 18 2025 | B3: 664.16 | C3: =(B3*0.06)*1.13 -> 45.030048 | D3: =(B3*0.02)*1.13 -> 15.010016 | F3: 664.16 | G3: 664.16 | N3: =SUM(G3,H3,I3,M3) -> 664.16
A4: May 19 - May 25 2025 | B4: 1547.11 | C4: =(B4*0.06)*1.13 -> 104.89406 | D4: =(B4*0.02)*1.13 -> 34.964686
A5: May 26 - June 01 2025 | B5: 2799.9 | C5: =(B5*0.06)*1.13 -> 189.83322 | D5: =(B5*0.02)*1.13 -> 63.27774 | F5: 2799.9 | G5: 2799.9 | K5: 291.93 | L5: 0 | M5: =K5-L5 -> 291.93
A6: June 02 - June 08 2025 | B6: 4365.58 | C6: =(B6*0.06)*1.13 -> 295.98632 | D6: =(B6*0.02)*1.13 -> 98.662108 | F6: 4365.58 | G6: 4365.58 | K6: 1235.52 | L6: 105.1 | M6: =K6-L6 -> 1130.42
A7: June 09 - June 15 2025 | B7: 4947.29 | C7: =(B7*0.06)*1.13 -> 335.42626 | D7: =(B7*0.02)*1.13 -> 111.80875 | G7: 4947.29 | K7: 1186.64 | L7: 86.8 | M7: =K7-L7 -> 1099.84
A8: June 16 - June 22 2025 | B8: 4793.11 | C8: =(B8*0.06)*1.13 -> 324.97286 | D8: =(B8*0.02)*1.13 -> 108.32429 | G8: 4793.11 | K8: 1830.45 | L8: 70.2 | M8: =K8-L8 -> 1760.25
A9: June 23 - June 29 2025 | B9: 5624.88 | C9: =(B9*0.06)*1.13 -> 381.36686 | D9: =(B9*0.02)*1.13 -> 127.12229 | G9: 5624.88 | K9: 1263.81 | L9: 99.44 | M9: =K9-L9 -> 1164.37
A10: June 30 - July 06 2025 | B10: 6403.23 | C10: =(B10*0.06)*1.13 -> 434.13899 | D10: =(B10*0.02)*1.13 -> 144.713 | F10: 6403.23 | G10: 6403.23 | K10: 1556.64 | L10: 79.56 | M10: =K10-L10 -> 1477.08
A11: July 07 - July 13 2025 | B11: 6338.56 | C11: =(B11*0.06)*1.13 -> 429.75437 | D11: =(B11*0.02)*1.13 -> 143.25146 | F11: 6338.56 | G11: 6338.56 | K11: 1515.09 | L11: 105.05 | M11: =K11-L11 -> 1410.04
A12: July 14 - July 20 2025 | B12: 6910.99 | C12: =(B12*0.06)*1.13 -> 468.56512 | D12: =(B12*0.02)*1.13 -> 156.18837 | E12: 292 | F12: 6910.99 | G12: 6910.99 | K12: 972.39 | L12: 132.79 | M12: =K12-L12 -> 839.6
A13: July 21 - July 27 2025 | B13: 7603.96 | C13: =(B13*0.06)*1.13 -> 515.54849 | D13: =(B13*0.02)*1.13 -> 171.8495 | E13: 272 | F13: 7016.72 | G13: 5957.03 | J13: 1059.69 | K13: 1791.65 | L13: 144.72 | M13: =K13-L13 -> 1646.93 | N13: =SUM(G13,H13,I13,M13) -> 7603.96
A14: July 28 - Aug 03 2025 | B14: 7021.72 | C14: =(B14*0.06)*1.13 -> 476.07262 | D14: =(B14*0.02)*1.13 -> 158.69087 | E14: 295 | F14: 7104.35 | G14: 5850.61 | J14: 1253.74 | K14: 1310.71 | L14: 139.6 | M14: =K14-L14 -> 1171.11 | N14: =SUM(G14,H14,I14,M14) -> 7021.72
A15: Aug 04 - Aug 10 2025 | B15: 9389.62 | C15: =(B15*0.06)*1.13 -> 636.61624 | D15: =(B15*0.02)*1.13 -> 212.20541 | E15: 362 | F15: 9626.57 | G15: 7180.12 | I15: 513.74 | J15: 1932.71 | K15: 1857.15 | L15: 161.39 | M15: =K15-L15 -> 1695.76 | N15: =SUM(G15,H15,I15,M15) -> 9389.62
A16: Aug 11 - Aug 17 2025 | B16: 7673.65 | C16: =(B16*0.06)*1.13 -> 520.27347 | D16: =(B16*0.02)*1.13 -> 173.42449 | E16: 320 | F16: 7809.76 | G16: 6042.25 | I16: 217.4 | J16: 1550.11 | K16: 1568.7 | L16: 154.7 | M16: =K16-L16 -> 1414 | N16: =SUM(G16,H16,I16,M16) -> 7673.65
A17: Aug 18 - Aug 24 2025 | B17: 7636.43 | C17: =(B17*0.06)*1.13 -> 517.74995 | D17: =(B17*0.02)*1.13 -> 172.58332 | E17: 327 | F17: 7730.38 | G17: 5813.68 | I17: 111.05 | J17: 1805.65 | K17: 1849.11 | L17: 137.41 | M17: =K17-L17 -> 1711.7 | N17: =SUM(G17,H17,I17,M17) -> 7636.43
A18: Aug 25 - Aug 31 2025 | B18: 9006.58 | C18: =(B18*0.06)*1.13 -> 610.64612 | D18: =(B18*0.02)*1.13 -> 203.54871 | E18: 355 | F18: 9233.72 | G18: 7099.5 | I18: 242.59 | J18: 1891.63 | K18: 1814.57 | L18: 150.08 | M18: =K18-L18 -> 1664.49 | N18: =SUM(G18,H18,I18,M18) -> 9006.58
A19: Sep 01 - Sep 07 2025 | B19: 8431.4 | C19: =(B19*0.06)*1.13 -> 571.64892 | D19: =(B19*0.02)*1.13 -> 190.54964 | E19: 334 | F19: 8531.43 | G19: 6374 | I19: 115.78 | J19: 2041.65 | K19: 2023.36 | L19: 81.74 | M19: =K19-L19 -> 1941.62 | N19: =SUM(G19,H19,I19,M19) -> 8431.4
A20: Sep 08 - Sep 14 2025 | B20: 7397.47 | C20: =(B20*0.06)*1.13 -> 501.54847 | D20: =(B20*0.02)*1.13 -> 167.18282 | E20: 311 | F20: 7386.62 | G20: 5610.51 | I20: 72.9 | J20: 1703.21 | K20: 1798.56 | L20: 84.5 | M20: =K20-L20 -> 1714.06 | N20: =SUM(G20,H20,I20,M20) -> 7397.47
A21: Sep 15 - Sep 21 2025 | B21: 7398.78 | C21: =(B21*0.06)*1.13 -> 501.63728 | D21: =(B21*0.02)*1.13 -> 167.21243 | E21: 323 | F21: 7513.93 | G21: 5237.2 | I21: 217.16 | J21: 2059.57 | K21: 2026.84 | L21: 82.42 | M21: =K21-L21 -> 1944.42 | N21: =SUM(G21,H21,I21,M21) -> 7398.78
A22: Sep 22 - Sep 28 2025 | B22: 7341.94 | C22: =(B22*0.06)*1.13 -> 497.78353 | D22: =(B22*0.02)*1.13 -> 165.92784 | E22: 293 | F22: 7334.35 | G22: 5453.04 | I22: 293.34 | J22: 1587.97 | K22: 1680.62 | L22: 85.06 | M22: =K22-L22 -> 1595.56 | N22: =SUM(G22,H22,I22,M22) -> 7341.94
A23: Sep 29 - Oct 05 2025 | B23: 9463.4 | C23: =(B23*0.06)*1.13 -> 641.61852 | D23: =(B23*0.02)*1.13 -> 213.87284 | E23: 358 | F23: 9546.61 | G23: 6246.2 | I23: 494.71 | J23: 2805.7 | K23: 2804.51 | L23: 82.02 | M23: =K23-L23 -> 2722.49 | N23: =SUM(G23,H23,I23,M23) -> 9463.4
A24: Oct 6 - Oct 12 2025 | B24: 8229.9 | C24: =(B24*0.06)*1.13 -> 557.98722 | D24: =(B24*0.02)*1.13 -> 185.99574 | E24: 340 | F24: 8237.23 | G24: 5767.37 | I24: 739.57 | J24: 1730.29 | K24: 1807.58 | L24: 84.62 | M24: =K24-L24 -> 1722.96 | N24: =SUM(G24,H24,I24,M24) -> 8229.9
A25: Oct 13 - Oct 19 2025 | B25: 7408.42 | C25: =(B25*0.06)*1.13 -> 502.29088 | D25: =(B25*0.02)*1.13 -> 167.43029 | F25: 7456.76 | G25: 4598.46 | H25: 0 | I25: 454.67 | J25: 2403.63 | K25: 2457.81 | L25: 102.52 | M25: =K25-L25 -> 2355.29 | N25: =SUM(G25,H25,I25,M25) -> 7408.42
A26: Oct 20 - Oct 26 2025 | B26: 9439.54 | C26: =(B26*0.06)*1.13 -> 640.00081 | D26: =(B26*0.02)*1.13 -> 213.3336 | E26: 376 | F26: 9422.55 | G26: 5553.79 | H26: 0 | I26: 210.9 | J26: 3657.86 | K26: 3782.69 | L26: 107.84 | M26: =K26-L26 -> 3674.85 | N26: =SUM(G26,H26,I26,M26) -> 9439.54
A27: Oct 27 - Nov 02 2025 | B27: 9180.19 | C27: =(B27*0.06)*1.13 -> 622.41688 | D27: =(B27*0.02)*1.13 -> 207.47229 | E27: 346 | F27: 8082.91 | G27: 6768.21 | H27: 0 | I27: 70.76 | J27: 1243.94 | K27: 2629.83 | L27: 288.61 | M27: =K27-L27 -> 2341.22 | N27: =SUM(G27,H27,I27,M27) -> 9180.19
A28: Nov 03 - Nov 09 2025 | B28: 9148.1 | C28: =(B28*0.06)*1.13 -> 620.24118 | D28: =(B28*0.02)*1.13 -> 206.74706 | E28: 346 | F28: 8885.45 | G28: 5311.78 | H28: 0 | I28: 242.31 | J28: 3331.36 | K28: 3914.5 | L28: 320.49 | M28: =K28-L28 -> 3594.01 | N28: =SUM(G28,H28,I28,M28) -> 9148.1
A29: Nov 10 - Nov 16 2025 | B29: 7638.78 | C29: =(B29*0.06)*1.13 -> 517.90928 | D29: =(B29*0.02)*1.13 -> 172.63643 | E29: 315 | F29: 7967.12 | G29: 3847.95 | H29: 0 | I29: 294.03 | J29: 3825.14 | K29: 3827.23 | L29: 330.43 | M29: =K29-L29 -> 3496.8 | N29: =SUM(G29,H29,I29,M29) -> 7638.78
A30: Nov 17 - Nov 23 2025 | B30: 6968.05 | C30: =(B30*0.06)*1.13 -> 472.43379 | D30: =(B30*0.02)*1.13 -> 157.47793 | E30: 305 | F30: 7318.71 | G30: 4338.26 | H30: 0 | I30: 177.36 | J30: 2803.09 | K30: 2787.59 | L30: 335.16 | M30: =K30-L30 -> 2452.43 | N30: =SUM(G30,H30,I30,M30) -> 6968.05
A31: Nov 24 - Nov 30 2025 | B31: 8782.19 | C31: =(B31*0.06)*1.13 -> 595.43248 | D31: =(B31*0.02)*1.13 -> 198.47749 | E31: 335 | F31: 8999.43 | G31: 4761.98 | H31: 0 | I31: 306.06 | J31: 3931.39 | K31: 3939.5 | L31: 225.35 | M31: =K31-L31 -> 3714.15 | N31: =SUM(G31,H31,I31,M31) -> 8782.19
A32: Dec 01 - Dec 07 2025 | B32: 7210.28 | C32: =(B32*0.06)*1.13 -> 488.85698 | D32: =(B32*0.02)*1.13 -> 162.95233 | E32: 282 | F32: 7372.1 | G32: 4225.44 | H32: 0 | I32: 117.42 | J32: 3029.24 | K32: 3049.33 | L32: 181.91 | M32: =K32-L32 -> 2867.42 | N32: =SUM(G32,H32,I32,M32) -> 7210.28
A33: Dec 08 - Dec 14 2025 | B33: 6637.35 | C33: =(B33*0.06)*1.13 -> 450.01233 | D33: =(B33*0.02)*1.13 -> 150.00411 | E33: 273 | F33: 6771.76 | G33: 3568.66 | H33: 0 | I33: 310.62 | J33: 2892.48 | K33: 2944.47 | L33: 186.4 | M33: =K33-L33 -> 2758.07 | N33: =SUM(G33,H33,I33,M33) -> 6637.35
A34: Dec 15 - Dec 21 2025 | B34: 7902.12 | C34: =(B34*0.06)*1.13 -> 535.76374 | D34: =(B34*0.02)*1.13 -> 178.58791 | E34: 343 | F34: 8311.76 | G34: 4860.79 | H34: 0 | I34: 198.22 | J34: 3252.75 | K34: 3264.29 | L34: 421.18 | M34: =K34-L34 -> 2843.11 | N34: =SUM(G34,H34,I34,M34) -> 7902.12
A35: Dec 22 - Dec 28 2025 | B35: 8908.59 | C35: =(B35*0.06)*1.13 -> 604.0024 | D35: =(B35*0.02)*1.13 -> 201.33413 | E35: 305 | F35: 9493.53 | G35: 5368.84 | H35: 0 | I35: 765.87 | J35: 3358.82 | K35: 3446.18 | L35: 672.3 | M35: =K35-L35 -> 2773.88 | N35: =SUM(G35,H35,I35,M35) -> 8908.59
A36: Dec 29 - Jan 04 2026 | B36: 7851.46 | C36: =(B36*0.06)*1.13 -> 532.32899 | D36: =(B36*0.02)*1.13 -> 177.443 | E36: 310 | F36: 8472.26 | G36: 4894.42 | H36: 0 | I36: 508.39 | J36: 3069.45 | K36: 3053.95 | L36: 605.3 | M36: =K36-L36 -> 2448.65 | N36: =SUM(G36,H36,I36,M36) -> 7851.46
A37: Jan 05 - Jan 11 2026 | B37: 7141.27 | C37: =(B37*0.06)*1.13 -> 484.17811 | D37: =(B37*0.02)*1.13 -> 161.3927 | E37: 308 | F37: 7857.99 | G37: 3981.81 | H37: 0 | I37: 253.79 | J37: 3622.39 | K37: 3568.23 | L37: 662.56 | M37: =K37-L37 -> 2905.67 | N37: =SUM(G37,H37,I37,M37) -> 7141.27
A38: Jan 12 - Jan 18 2026 | B38: 5922.81 | C38: =(B38*0.06)*1.13 -> 401.56652 | D38: =(B38*0.02)*1.13 -> 133.85551 | E38: 250 | F38: 6428.8 | G38: 3249.17 | H38: 0 | I38: 364.72 | J38: 2814.91 | K38: 2904.47 | L38: 595.55 | M38: =K38-L38 -> 2308.92 | N38: =SUM(G38,H38,I38,M38) -> 5922.81
A39: Jan 19 - Jan 25 2026 | B39: 6472.16 | C39: =(B39*0.06)*1.13 -> 438.81245 | D39: =(B39*0.02)*1.13 -> 146.27082 | E39: 279 | F39: 7110.51 | G39: 3635.23 | H39: 0 | I39: 226.12 | J39: 3249.16 | K39: 3249.16 | L39: 638.35 | M39: =K39-L39 -> 2610.81 | N39: =SUM(G39,H39,I39,M39) -> 6472.16
A40: Jan 26 - Feb 01 2026 | B40: 6003.96 | C40: =(B40*0.06)*1.13 -> 407.06849 | D40: =(B40*0.02)*1.13 -> 135.6895 | E40: 253 | F40: 6460.23 | G40: 3315.16 | H40: 0 | I40: 350.28 | J40: 2794.79 | K40: 2793.89 | L40: 455.37 | M40: =K40-L40 -> 2338.52 | N40: =SUM(G40,H40,I40,M40) -> 6003.96
A41: Feb 02 - Feb 08 2026 | B41: 6300.74 | C41: =(B41*0.06)*1.13 -> 427.19017 | D41: =(B41*0.02)*1.13 -> 142.39672 | E41: 280 | F41: 6764.51 | G41: 3123.66 | H41: 0 | I41: 216.12 | J41: 3424.73 | K41: 3361.23 | L41: 400.27 | M41: =K41-L41 -> 2960.96 | N41: =SUM(G41,H41,I41,M41) -> 6300.74
A42: Feb 09 - Feb 15 2026 | B42: 7769.29 | C42: =(B42*0.06)*1.13 -> 526.75786 | D42: =(B42*0.02)*1.13 -> 175.58595 | E42: 329 | F42: 7964.43 | G42: 4759.09 | H42: 0 | I42: 267.83 | J42: 2937.51 | K42: 3053.12 | L42: 310.75 | M42: =K42-L42 -> 2742.37 | N42: =SUM(G42,H42,I42,M42) -> 7769.29
A43: Feb 16 - Feb 22 2026 | B43: 7537.25 | C43: =(B43*0.06)*1.13 -> 511.02555 | D43: =(B43*0.02)*1.13 -> 170.34185 | E43: 308 | F43: 7902.25 | G43: 4225.49 | H43: 0 | I43: 191.21 | J43: 3485.55 | K43: 3683.2 | L43: 562.65 | M43: =K43-L43 -> 3120.55 | N43: =SUM(G43,H43,I43,M43) -> 7537.25
A44: Feb 23 - Mar 1 2026 | B44: 8615.56 | C44: =(B44*0.06)*1.13 -> 584.13497 | D44: =(B44*0.02)*1.13 -> 194.71166 | E44: 314 | F44: 9149.83 | G44: 3829.96 | H44: 0 | I44: 484.06 | J44: 4835.81 | K44: 4853.91 | L44: 552.37 | M44: =K44-L44 -> 4301.54 | N44: =SUM(G44,H44,I44,M44) -> 8615.56
A45: Mar 02 - Mar 08 2026 | B45: 8023.57 | C45: =(B45*0.06)*1.13 -> 543.99805 | D45: =(B45*0.02)*1.13 -> 181.33268 | E45: 310 | F45: 8593.11 | G45: 3258.45 | H45: 0 | I45: 562.46 | J45: 4772.2 | K45: 4808.99 | L45: 606.33 | M45: =K45-L45 -> 4202.66 | N45: =SUM(G45,H45,I45,M45) -> 8023.57
A46: Mar 09 - Mar 15 2026 | B46: 9469.56 | C46: =(B46*0.06)*1.13 -> 642.03617 | D46: =(B46*0.02)*1.13 -> 214.01206 | E46: 349 | F46: 10133.17 | G46: 4317.25 | H46: 0 | I46: 481.28 | J46: 5334.64 | K46: 5467.71 | L46: 796.68 | M46: =K46-L46 -> 4671.03 | N46: =SUM(G46,H46,I46,M46) -> 9469.56
A47: Mar 16 - Mar 22 2026 | B47: 10550.93 | C47: =(B47*0.06)*1.13 -> 715.35305 | D47: =(B47*0.02)*1.13 -> 238.45102 | E47: 393 | F47: 11116.48 | G47: 5451.66 | H47: 0 | I47: 253.05 | J47: 5411.77 | K47: 5466.58 | L47: 620.36 | M47: =K47-L47 -> 4846.22 | N47: =SUM(G47,H47,I47,M47) -> 10550.93
... A52: Apr 20 - Apr 26 | B52: 9410.12 | C52: =(B52*0.06)*1.13 -> 638.00614 | D52: =(B52*0.02)*1.13 -> 212.66871 | E52: 394 | F52: 10746.86 | G52: 5093.59 | H52: 0 | I52: 308.13 | J52: 5345.14 | K52: 5336.49 | L52: 1328.09 | M52: =K52-L52 -> 4008.4 | N52: =SUM(G52,H52,I52,M52) -> 9410.12
A53: Apr 27 - May 03 | B53: 10362.14 | C53: =(B53*0.06)*1.13 -> 702.55309 | D53: =(B53*0.02)*1.13 -> 234.18436 | E53: 411 | F53: 11626.19 | G53: 5978.6 | H53: 0 | I53: 386.3 | J53: 5261.29 | K53: $5,420.59 | L53: $1,423.35 | M53: =K53-L53 -> 3997.24 | N53: =SUM(G53,H53,I53,M53) -> 10362.14
A54: May 4 - May 10 | B54: 10059.3 | C54: =(B54*0.06)*1.13 -> 682.02054 | D54: =(B54*0.02)*1.13 -> 227.34018 | E54: 418 | F54: 11169.33 | G54: 6171.55 | H54: 0 | I54: 118.96 | J54: 4878.82 | K54: 4782.48 | L54: 1013.69 | M54: =K54-L54 -> 3768.79 | N54: =SUM(G54,H54,I54,M54) -> 10059.3
A55: May 11 - May 17 | B55: 9437.64 | C55: =(B55*0.06)*1.13 -> 639.87199 | D55: =(B55*0.02)*1.13 -> 213.29066 | E55: 385 | F55: 10353.53 | G55: 5487.71 | H55: 0 | I55: 516.77 | J55: 4349.05 | K55: 4416.87 | L55: 983.71 | M55: =K55-L55 -> 3433.16 | N55: =SUM(G55,H55,I55,M55) -> 9437.64
A56: May 18 - May 24 | B56: 9840.34 | C56: =(B56*0.06)*1.13 -> 667.17505 | D56: =(B56*0.02)*1.13 -> 222.39168 | E56: 385 | F56: 10862.45 | G56: 5741.77 | H56: 0 | I56: 248.13 | J56: 4872.55 | K56: 4773.78 | L56: 923.34 | M56: =K56-L56 -> 3850.44 | N56: =SUM(G56,H56,I56,M56) -> 9840.34
A57: May 25 - May 31 | B57: 12273.47 | C57: =(B57*0.06)*1.13 -> 832.14127 | D57: =(B57*0.02)*1.13 -> 277.38042 | E57: 435 | F57: 13171.28 | G57: 8276.54 | H57: 0 | I57: 221.07 | J57: 4673.67 | K57: 4818.95 | L57: 1043.09 | M57: =K57-L57 -> 3775.86 | N57: =SUM(G57,H57,I57,M57) -> 12273.47
A60: Queen KKW
A61: Statement For Selected Period | B61: Total Revenue (Net Sales) | C61: Royalties (6%) +HST | D61: Marketing (2%) +HST
A62: Mar 09 - Mar 15 2026 | B62: 9469.56 | C62: =(B59*0.06)*1.13 -> 0 | D62: =(B59*0.02)*1.13 -> 0
A63: Mar 16 - Mar 22 2026 | B63: 10550.93 | C63: =(B60*0.06)*1.13 -> 0 | D63: =(B60*0.02)*1.13 -> 0
A64: Mar 23 - Mar 29 2026 | B64: 8077.93 | C64: =(B61*0.06)*1.13 -> #VALUE! | D64: =(B61*0.02)*1.13 -> #VALUE!
A65: Mar 30 - Apr 05 2026 | B65: 10135.13 | C65: =(B62*0.06)*1.13 -> 642.03617 | D65: =(B62*0.02)*1.13 -> 214.01206
A66: Apr 06 - Apr 12 | B66: 9562.98 | C66: =(B63*0.06)*1.13 -> 715.35305 | D66: =(B63*0.02)*1.13 -> 238.45102
A67: Apr 13 - Apr 19 | B67: 8161.77 | C67: =(B64*0.06)*1.13 -> 547.68365 | D67: =(B64*0.02)*1.13 -> 182.56122
A68: Apr 20 - Apr 26 | B68: 9410.12 | C68: =(B65*0.06)*1.13 -> 687.16181 | D68: =(B65*0.02)*1.13 -> 229.05394
A69: Apr 27 - May 03 | B69: 10362.14 | C69: =(B67*0.06)*1.13 -> 553.36801 | D69: =(B67*0.02)*1.13 -> 184.456
A70: May 4 - May 10 | B70: 10059.3 | C70: =(B68*0.06)*1.13 -> 638.00614 | D70: =(B68*0.02)*1.13 -> 212.66871
A71: May 11 - May 17 | B71: 9437.64 | C71: =(B70*0.06)*1.13 -> 682.02054 | D71: =(B70*0.02)*1.13 -> 227.34018
A72: May 18 - May 24 | B72: 9840.34 | C72: =(B72*0.06)*1.13 -> 667.17505 | D72: =(B72*0.02)*1.13 -> 222.39168
A73: May 25 - May 31 | B73: 12273.47 | C73: =(B73*0.06)*1.13 -> 832.14127 | D73: =(B73*0.02)*1.13 -> 277.38042

Sheet Lebovic
A1: Lebovic
A2: Statement For Selected Period | B2: Total Revenue (Net Sales) | C2: Royalties (6%) +HST | D2: Marketing (2%) +HST | E2: Bill Count | F2: POS Total | G2: In-Store | H2: Skip | I2: DD | J2: Uber (TB) | K2: PK Uber (Rev) | L2: PK Uber (Marketing) | M2: Chickentarian Uber (Rev) | N2: Chickentarian Uber (Marketing) | O2: Final Uber | P2: Total
A3: Mar 07 - Mar 09 2025 | B3: 1358.01 | C3: =(B3*0.06)*1.13 -> 92.073078 | D3: =(B3*0.02)*1.13 -> 30.691026 | G3: 1358.01 | K3: 138.56 | L3: 18.1 | M3: 0 | N3: 0 | O3: =K3-L3 -> 120.46
A4: Mar 10 - Mar 16 2025 | B4: 6551.2 | C4: =(B4*0.06)*1.13 -> 444.17136 | D4: =(B4*0.02)*1.13 -> 148.05712 | K4: 1147.55 | L4: 174.79 | O4: =K4-L4 -> 972.76
A5: Mar 17 - Mar 23 2025 | B5: 6541.54 | C5: =(B5*0.06)*1.13 -> 443.51641 | D5: =(B5*0.02)*1.13 -> 147.8388 | G5: 5648.64 | H5: 0 | I5: 378.89 | J5: 611.14 | K5: 613.95 | L5: 99.94 | O5: =K5-L5 -> 514.01 | P5: =SUM(G5,H5,I5,O5) -> 6541.54
A6: Mar 24 - Mar 30 2025 | B6: 11256.19 | C6: =(B6*0.06)*1.13 -> 763.16968 | D6: =(B6*0.02)*1.13 -> 254.38989 | G6: 9146.42 | H6: 45.58 | I6: 643.8 | J6: 1507.24 | K6: 1428.04 | L6: 7.65 | O6: =K6-L6 -> 1420.39 | P6: =SUM(G6,H6,I6,O6) -> 11256.19
A7: Mar 31 - Apr 6 2025 | B7: 12830.78 | C7: =(B7*0.06)*1.13 -> 869.92688 | D7: =(B7*0.02)*1.13 -> 289.97563 | G7: 10209.73 | H7: 57.89 | I7: 678.18 | J7: 1871.77 | K7: 1884.98 | L7: 0 | O7: =K7-L7 -> 1884.98 | P7: =SUM(G7,H7,I7,O7) -> 12830.78
A8: Apr 7 - Apr 13 2025 | B8: 11068.59 | C8: =(B8*0.06)*1.13 -> 750.4504 | D8: =(B8*0.02)*1.13 -> 250.15013 | G8: 8238.21 | H8: 147.88 | I8: 550.39 | J8: 2079.43 | K8: 2311.9 | L8: 179.79 | O8: =K8-L8 -> 2132.11 | P8: =SUM(G8,H8,I8,O8) -> 11068.59
A9: Apr 14 - Apr 20 2025 | B9: 12721.55 | C9: =(B9*0.06)*1.13 -> 862.52109 | D9: =(B9*0.02)*1.13 -> 287.50703 | G9: 10280.08 | H9: 189.09 | I9: 341.64 | J9: 2100.59 | K9: 2061 | L9: 150.26 | O9: =K9-L9 -> 1910.74 | P9: =SUM(G9,H9,I9,O9) -> 12721.55
A10: Apr 21 - Apr 27 2025 | B10: 12290.19 | C10: =(B10*0.06)*1.13 -> 833.27488 | D10: =(B10*0.02)*1.13 -> 277.75829 | G10: 9891.12 | H10: 275.94 | I10: 356.63 | J10: 1881.72 | K10: 1921.31 | L10: 154.81 | O10: =K10-L10 -> 1766.5 | P10: =SUM(G10,H10,I10,O10) -> 12290.19
A11: Apr 28 - May 04 2025 | B11: 11476.5 | C11: =(B11*0.06)*1.13 -> 778.1067 | D11: =(B11*0.02)*1.13 -> 259.3689 | G11: 9723.35 | H11: 0 | I11: 429 | J11: 1464.57 | K11: 1414.63 | L11: 90.48 | M11: 0 | N11: 0 | O11: =K11-L11 -> 1324.15 | P11: =SUM(G11,H11,I11,O11) -> 11476.5
A12: May 05 - May 11 2025 | B12: 11751.38 | C12: =(B12*0.06)*1.13 -> 796.74356 | D12: =(B12*0.02)*1.13 -> 265.58119 | F12: 11836.23 | G12: 9769.66 | H12: 142.18 | I12: 508.31 | J12: 1416.08 | K12: 1417.03 | L12: 85.8 | M12: 0 | N12: 0 | O12: =K12-L12 -> 1331.23 | P12: =SUM(G12,H12,I12,O12) -> 11751.38
A13: May 12 - May 18 2025 | B13: 10854.11 | C13: =(B13*0.06)*1.13 -> 735.90866 | D13: =(B13*0.02)*1.13 -> 245.30289 | F13: 11010.2 | G13: 8491.04 | H13: 121.8 | I13: 523.69 | J13: 1873.67 | K13: 1851.46 | L13: 133.88 | M13: 0 | N13: 0 | O13: =K13-L13 -> 1717.58 | P13: =SUM(G13,H13,I13,O13) -> 10854.11
A14: May 19 - May 25 2025 | B14: 13336.76 | C14: =(B14*0.06)*1.13 -> 904.23233 | D14: =(B14*0.02)*1.13 -> 301.41078 | F14: 13507.97 | G14: 9697.44 | H14: 217.18 | I14: 712.54 | J14: 2880.81 | K14: 2884.87 | L14: 192.05 | M14: 16.78 | N14: 0 | O14: =(K14-L14)+(M14-N14) -> 2709.6 | P14: =SUM(G14,H14,I14,O14) -> 13336.76
A15: May 26 - June 01 2025 | B15: 11398.24 | C15: =(B15*0.06)*1.13 -> 772.80067 | D15: =(B15*0.02)*1.13 -> 257.60022 | F15: 11545.8 | G15: 8647.53 | H15: 141.7 | I15: 466.14 | J15: 2290.43 | K15: 2310.57 | L15: 183.9 | M15: 16.2 | N15: 0 | O15: =(K15-L15)+(M15-N15) -> 2142.87 | P15: =SUM(G15,H15,I15,O15) -> 11398.24
A16: June 02 - June 08 2025 | B16: 12039.09 | C16: =(B16*0.06)*1.13 -> 816.2503 | D16: =(B16*0.02)*1.13 -> 272.08343 | F16: 12047.67 | G16: 9433.31 | H16: 158.94 | I16: 590.33 | J16: 1865.09 | K16: 1978.48 | L16: 138.17 | M16: 16.2 | N16: 0 | O16: =(K16-L16)+(M16-N16) -> 1856.51 | P16: =SUM(G16,H16,I16,O16) -> 12039.09
A17: June 09 - June 15 2025 | B17: 13055.04 | C17: =(B17*0.06)*1.13 -> 885.13171 | D17: =(B17*0.02)*1.13 -> 295.0439 | F17: 13288.84 | G17: 9385.52 | H17: 185.69 | I17: 549.69 | J17: 3167.94 | K17: 3141.24 | L17: 237.08 | M17: 29.98 | N17: 0 | O17: =(K17-L17)+(M17-N17) -> 2934.14 | P17: =SUM(G17,H17,I17,O17) -> 13055.04
A18: June 16 - June 22 2025 | B18: 12983.72 | C18: =(B18*0.06)*1.13 -> 880.29622 | D18: =(B18*0.02)*1.13 -> 293.43207 | F18: 13103.48 | G18: 10064.45 | H18: 65.2 | I18: 625.54 | J18: 2348.29 | K18: 2347.39 | L18: 168.32 | M18: 49.46 | N18: 0 | O18: =(K18-L18)+(M18-N18) -> 2228.53 | P18: =SUM(G18,H18,I18,O18) -> 12983.72
A19: June 23 - June 29 2025 | B19: 13364.94 | C19: =(B19*0.06)*1.13 -> 906.14293 | D19: =(B19*0.02)*1.13 -> 302.04764 | F19: 13603.33 | G19: 10254.47 | H19: 167.99 | I19: 515.75 | J19: 2665.12 | K19: 2541.82 | L19: 133.99 | M19: 18.9 | N19: 0 | O19: =(K19-L19)+(M19-N19) -> 2426.73 | P19: =SUM(G19,H19,I19,O19) -> 13364.94
A20: June 30 - July 06 2025 | B20: 14314.06 | C20: =(B20*0.06)*1.13 -> 970.49327 | D20: =(B20*0.02)*1.13 -> 323.49776 | F20: 14252.5 | G20: 11199.44 | H20: 135.29 | I20: 839.42 | J20: 2078.35 | K20: 2147.79 | L20: 44.14 | M20: 36.26 | N20: 0 | O20: =(K20-L20)+(M20-N20) -> 2139.91 | P20: =SUM(G20,H20,I20,O20) -> 14314.06
A21: July 07 - July 13 2025 | B21: 11942.82 | C21: =(B21*0.06)*1.13 -> 809.7232 | D21: =(B21*0.02)*1.13 -> 269.90773 | F21: 11966.52 | G21: 9037.18 | H21: 148.95 | I21: 490.59 | J21: 2289.8 | K21: 2371.26 | L21: 105.16 | M21: 0 | N21: 0 | O21: =(K21-L21)+(M21-N21) -> 2266.1 | P21: =SUM(G21,H21,I21,O21) -> 11942.82
A22: July 14 - July 20 2025 | B22: 10989.53 | C22: =(B22*0.06)*1.13 -> 745.09013 | D22: =(B22*0.02)*1.13 -> 248.36338 | E22: 425 | F22: 11211.55 | G22: 8389.05 | H22: 108.08 | I22: 194.95 | J22: 2519.47 | K22: 2443.4 | L22: 162.15 | M22: 16.2 | N22: 0 | O22: =(K22-L22)+(M22-N22) -> 2297.45 | P22: =SUM(G22,H22,I22,O22) -> 10989.53
A23: July 21 - July 27 2025 | B23: 11974.6 | C23: =(B23*0.06)*1.13 -> 811.87788 | D23: =(B23*0.02)*1.13 -> 270.62596 | E23: 478 | F23: 12054.1 | G23: 9404.54 | H23: 76.19 | I23: 266.44 | J23: 2306.93 | K23: 2377.42 | L23: 166.78 | M23: 16.79 | N23: 0 | O23: =(K23-L23)+(M23-N23) -> 2227.43 | P23: =SUM(G23,H23,I23,O23) -> 11974.6
A24: July 28 - Aug 03 2025 | B24: 12947.61 | C24: =(B24*0.06)*1.13 -> 877.84796 | D24: =(B24*0.02)*1.13 -> 292.61599 | E24: 494 | F24: 13150.05 | G24: 10118.94 | H24: 137.13 | I24: 308.57 | J24: 2585.41 | K24: 2486.67 | L24: 123.19 | M24: 19.49 | N24: 0 | O24: =(K24-L24)+(M24-N24) -> 2382.97 | P24: =SUM(G24,H24,I24,O24) -> 12947.61
A25: Aug 04 - Aug 10 2025 | B25: 12241.33 | C25: =(B25*0.06)*1.13 -> 829.96217 | D25: =(B25*0.02)*1.13 -> 276.65406 | E25: 499 | F25: 12343 | G25: 8964.03 | H25: 80.79 | I25: 472.79 | J25: 2825.39 | K25: 2938.83 | L25: 215.11 | M25: 0 | N25: 0 | O25: =(K25-L25)+(M25-N25) -> 2723.72 | P25: =SUM(G25,H25,I25,O25) -> 12241.33
A26: Aug 11 - Aug 17 2025 | B26: 11820.22 | C26: =(B26*0.06)*1.13 -> 801.41092 | D26: =(B26*0.02)*1.13 -> 267.13697 | E26: 487 | F26: 12114.39 | G26: 9038.79 | H26: 78.18 | I26: 515.1 | J26: 2482.32 | K26: 2403.12 | L26: 214.97 | M26: 0 | N26: 0 | O26: =(K26-L26)+(M26-N26) -> 2188.15 | P26: =SUM(G26,H26,I26,O26) -> 11820.22
A27: Aug 18 - Aug 24 2025 | B27: 10592.17 | C27: =(B27*0.06)*1.13 -> 718.14913 | D27: =(B27*0.02)*1.13 -> 239.38304 | E27: 406 | F27: 10627.64 | G27: 7569.74 | H27: 240.1 | I27: 548.85 | J27: 2268.95 | K27: 2321.49 | L27: 169.27 | M27: 81.26 | N27: 0 | O27: =(K27-L27)+(M27-N27) -> 2233.48 | P27: =SUM(G27,H27,I27,O27) -> 10592.17
A28: Aug 25 - Aug 31 2025 | B28: 13732.56 | C28: =(B28*0.06)*1.13 -> 931.06757 | D28: =(B28*0.02)*1.13 -> 310.35586 | E28: 521 | F28: 14046.06 | G28: 10729.44 | H28: 102.3 | I28: 396.59 | J28: 2817.73 | K28: 2724.14 | L28: 219.91 | M28: 0 | N28: 0 | O28: =(K28-L28)+(M28-N28) -> 2504.23 | P28: =SUM(G28,H28,I28,O28) -> 13732.56
A29: Sep 01 - Sep 07 2025 | B29: 10690.28 | C29: =(B29*0.06)*1.13 -> 724.80098 | D29: =(B29*0.02)*1.13 -> 241.60033 | E29: 407 | F29: 10806.05 | G29: 7596.4 | H29: 83.2 | I29: 364.3 | J29: 2762.15 | K29: 2850.94 | L29: 204.56 | M29: 0 | N29: 0 | O29: =(K29-L29)+(M29-N29) -> 2646.38 | P29: =SUM(G29,H29,I29,O29) -> 10690.28
A30: Sep 08 - Sep 14 2025 | B30: 10419.98 | C30: =(B30*0.06)*1.13 -> 706.47464 | D30: =(B30*0.02)*1.13 -> 235.49155 | E30: 384 | F30: 10568.22 | G30: 7718.52 | H30: 96.7 | I30: 389.75 | J30: 2363.25 | K30: 2398.06 | L30: 183.05 | M30: 0 | N30: 0 | O30: =(K30-L30)+(M30-N30) -> 2215.01 | P30: =SUM(G30,H30,I30,O30) -> 10419.98
A31: Sep 15 - Sep 21 2025 | B31: 10981.98 | C31: =(B31*0.06)*1.13 -> 744.57824 | D31: =(B31*0.02)*1.13 -> 248.19275 | E31: 414 | F31: 11221.66 | G31: 8565.72 | H31: 27.47 | I31: 377.71 | J31: 2250.76 | K31: 2175.16 | L31: 164.08 | M31: 0 | N31: 0 | O31: =(K31-L31)+(M31-N31) -> 2011.08 | P31: =SUM(G31,H31,I31,O31) -> 10981.98
A32: Sep 22 - Sep 28 2025 | B32: 13592.58 | C32: =(B32*0.06)*1.13 -> 921.57692 | D32: =(B32*0.02)*1.13 -> 307.19231 | E32: 474 | F32: 13726.19 | G32: 10686.02 | H32: 50.4 | I32: 524.32 | J32: 2465.45 | K32: 2511.84 | L32: 180 | M32: 0 | N32: 0 | O32: =(K32-L32)+(M32-N32) -> 2331.84 | P32: =SUM(G32,H32,I32,O32) -> 13592.58
A33: Sep 29 - Oct 05 2025 | B33: 12630.49 | C33: =(B33*0.06)*1.13 -> 856.34722 | D33: =(B33*0.02)*1.13 -> 285.44907 | E33: 465 | F33: 12502 | G33: 10063.39 | H33: 78.39 | I33: 369.19 | J33: 1991.03 | K33: 2150.13 | L33: 47.4 | M33: 16.79 | N33: 0 | O33: =(K33-L33)+(M33-N33) -> 2119.52 | P33: =SUM(G33,H33,I33,O33) -> 12630.49
